Workbook

Sheet Overwiew 
B2: Conversion Technology | C2: Capacity Existing | D2: Capacity Limit | E2: OPEX | F2: CAPEX | G2: Carbon Footprint | H2: Notes
A3: Mineral Mining | B3: Bauxite mining | C3: yes | D3: 0 | E3: yes | F3: one value | G3: one value | H3: used CAPEX of copper/nickel mining
B4: Iron mining | C4: yes | D4: 0 | E4: yes | F4: one value | G4: one value | H4: used CAPEX of copper/nickel mining
B5: Nickel mining | C5: yes | D5: 0 | E5: yes | F5: one value | G5: one value
B6: Copper mining | C6: yes | D6: 0 | E6: yes | F6: one value | G6: yes
A7: Material Production | B7: Aluminium Production | C7: yes | D7: 0 | E7: yes | F7: one value | G7: yes
B8: Steel Production | C8: yes | D8: yes | E8: yes | F8: one value | G8: yes
B9: Copper Refinement | C9: yes | D9: 0 | E9: yes | F9: one value | G9: yes
A10: Component Manufacturing | B10: Compressor Manufacturing | C10: yes | D10: yes | E10: yes | F10: yes | G10: no
B11: HEX Manufacturing | C11: yes | D11: yes | E11: yes | F11: yes | G11: no
A12: Final Assembly | B12: HP Assembly | C12: yes | D12: yes | E12: yes | F12: yes | G12: no

Sheet compressor production
A1: Country | B1: year | C1: installed capacity | D1: unit | E1: type | F1: source | G1: Notes: | I1: Conversion of compressor prodcution | J1: Source: Rewlay-ngoen, 2020
A2: China | B2: 2018 | C2: =198*10^6 -> 198000000 | D2: units/year | E2: rotary compressor | F2: Nicholson,2019 | G2: specified for cooling | I2: Material type | J2: Component | K2: Weight | L2: Ratio | O2: https://www.bsria.com/us/news/article/world_compressor_market_an_overview/?srsltid=AfmBOoofS_VauHvF8VQmVHWe5OgWs4tQRiutDIwbD5xMriB5_O1y6Fwz
A3: Thailand | B3: 2018 | C3: =13*10^6 -> 13000000 | D3: units/year | E3: rotary compressor | F3: Nicholson,2019 | G3: specified for cooling | K3: (kg) | L3: (%)
A4: South Korea | B4: 2017 | C4: =5.5*10^6 -> 5500000 | D4: units/year | E4: rotary compressor | F4: Nicholson,2019 | G4: specified for cooling | I4: Cast iron | J4: Cylinder, shaft, rotor | K4: 4.8 | L4: 20.24
A5: Japan | B5: 2018 | C5: =4.1*10^6 -> 4100000 | D5: units/year | E5: rotary compressor | F5: Nicholson,2019 | G5: specified for cooling | I5: Steel sheet | J5: upper / lower housing, Accumulator | K5: 5.13 | L5: 21.64
A6: Malaysie | B6: 2018 | C6: =3.5*10^6 -> 3500000 | D6: units/year | E6: rotary compressor | F6: Nicholson,2019 | G6: specified for cooling | I6: High grade steel | J6: Rolling piston | K6: 0.56 | L6: 2.36
A7: Czech republik | B7: 2018 | C7: 790000 | D7: units/year | E7: rotary compressor | F7: Nicholson,2019 | G7: specified for cooling | I7: Sintering steel | J7: Upper / lower bearing | K7: 0.19 | L7: 0.8
A8: United states | B8: 2017 | C8: =1*10^6 -> 1000000 | D8: units/year | E8: rotary compressor | F8: Nicholson,2019 | G8: specified for cooling | I8: Silicon steel | J8: Stator, rotor | K8: 7.8 | L8: 32.9
A9: India | B9: 2017 | C9: =3*10^6 -> 3000000 | D9: units/year | E9: rotary compressor | F9: Nicholson,2019 | G9: specified for cooling | I9: Copper | J9: Copper wire | K9: 2.26 | L9: 9.53
A10: Brazil | B10: 2017 | C10: =1.9*10^6 -> 1900000 | D10: units/year | E10: rotary compressor | F10: Nicholson,2019 | G10: specified for cooling | J10: copper tube | K10: 0.44 | L10: 1.86
A11: europe | C11: =0.8*10^6 -> 800000 | D11: units/year | F11: Nicholson,2019 | I11: Aluminum ingot | J11: Rotor core | K11: 0.37 | L11: 1.56
A12: australia | C12: 8000 | D12: units/year | F12: Nicholson,2019 | I12: HCFC-22 (R22) | J12: Refrigerant | K12: 1.5 | L12: 6.33
A14: Country | B14: year | C14: Compressor Production Value | D14: unit | E14: source | F14: For Czechia | I14: Mineral oil | J14: Lubricant oil | K14: 0.653 | L14: 2.75
A15: Germany | B15: 2021 | C15: =805.9*10^6 -> 805900000 | D15: € | E15: ENEL, 2023 | F15: =C17/C7 -> 341.39241 | I15: Paint | J15: Compressor coating | K15: 0.008 | L15: 0.03
A16: Slovakia | B16: 2021 | C16: =349.1*10^6 -> 349100000 | D16: € | E16: ENEL, 2024 | I16: Total | K16: 23.711 | L16: 100
A17: Czechia | B17: 2021 | C17: =269.7*10^6 -> 269700000 | D17: € | E17: ENEL, 2025 | I17: Steel total | K17: =(K5+K6+K8+K7)/K16 -> 0.57694741 | L17: =L5+L6+L8+L7 -> 57.7 | M17: kg Steel/kg compressor
A18: Hungary | B18: 2021 | C18: =181.6*10^6 -> 181600000 | D18: € | E18: ENEL, 2026 | I18: Copper total | K18: =SUM(K9:K10)/K16 -> 0.1138712 | L18: =SUM(L9:L10) -> 11.39 | M18: kg Copper/kg compressor
A19: Itlay | B19: 2021 | C19: =166.4*10^6 -> 166400000 | D19: € | E19: ENEL, 2027 | I19: Umrechnungsfaktor von unit ro kW | K19: 2 | L19: kW/unit | M19: assumed COP of 3.5
A20: Spain | B20: 2021 | C20: =60.9*10^6 -> 60900000 | D20: € | E20: ENEL, 2028
A21: Europe | B21: 2024 | C21: =4.6*10^9*0.84 -> 3864000000 | D21: € | E21: https://www.gminsights.com/industry-analysis/europe-heat-pump-compressors-market
A22: World | C22: =486*10^6 -> 486000000 | D22: units | E22: https://www.bsria.com/us/news/article/world_compressor_market_an_overview/?srsltid=AfmBOoofS_VauHvF8VQmVHWe5OgWs4tQRiutDIwbD5xMriB5_O1y6Fwz
A23: World | C23: =42.4*10^9*0.84 -> 35616000000 | D23: € | E23: https://www.bsria.com/us/news/article/world_compressor_market_an_overview/?srsltid=AfmBOoofS_VauHvF8VQmVHWe5OgWs4tQRiutDIwbD5xMriB5_O1y6Fwz
A24: Country | B24: year | C24: sales volume | D24: unit | E24: Increased sales volume 2021-2023 | F24: source | G24: Notes:
A25: China | B25: 2023 | C25: =6673.5*1000 -> 6673500 | D25: units | E25: 0.024 | F25: http://www.chinaiol.com/download/Global%20Heat%20Pump%20Market%20Report%202024.pdf
B27: installed capacity | C27: €/yr | E27: unit | F27: Carbon footprint | I27: CAGR
A28: AUS | B28: =218*10^6*0.84 -> 183120000 | C28: €/yr | D28: =B28/'cost estimate'!$B$6*'cost estimate'!$B$31/10^6 -> 1.3025676 | E28: GW | I28: 0.059 | J28: https://www.nextmsc.com/report/australia-air-compressor-market#:~:text=The%20Australia%20Air%20Compressor%20Market,5.9%25%20from%202024%20to%202030.
A29: AUT | B29: 0 | C29: €/yr | D29: 0 | E29: GW | I29: 0.176 | J29: no data
A30: BRA | B30: =900*1000 -> 900000 | C30: units/year | D30: =B30*'cost estimate'!$B$31/10^6*$B$49 -> 7.2 | E30: GW | I30: 0.03 | J30: https://www.clasp.ngo/wp-content/uploads/2021/01/ENG-2018-Technical-and-Economic-Feasibility-Study-for-a-High-Efficiency-Compressor-Market-in-Brazil.pdf
A31: CHN | B31: =6673.5*1000 -> 6673500 | C31: units/year | D31: =B31*'cost estimate'!$B$31/10^6*$B$49 -> 53.388 | E31: GW | I31: 0.078 | J31: https://www.maximizemarketresearch.com/market-report/air-conditioning-compressor-market/169709/#:~:text=Air%20Conditioning%20Compressor%20Market%20–%20increasing,to%20boost%20the%20market%20growth&text=Air%20Conditioning%20Compressor%20Market%20size,5.2%20%25%20during%20the%20forecast%20period.
A32: CZE | B32: =269.7*10^6 -> 269700000 | C32: €/yr | D32: =B32/'cost estimate'!$B$6*'cost estimate'!$B$31/10^6 -> 1.9184277 | E32: GW | I32: 0.176
A33: DEU | B33: =805.9*10^6 -> 805900000 | C33: €/yr | D33: =B33/'cost estimate'!$B$6*'cost estimate'!$B$31/10^6 -> 5.732521 | E33: GW | I33: 0.176
A34: ITA | B34: =166.4*10^6 -> 166400000 | C34: €/yr | D34: =B34/'cost estimate'!$B$6*'cost estimate'!$B$31/10^6 -> 1.1836351 | E34: GW | I34: 0.176
A35: JPN | B35: =4.1*10^6 -> 4100000 | C35: units/year | D35: =B35*K19/10^6*$B$49 -> 8.2 | E35: GW | I35: 0.078 | J35: https://www.maximizemarketresearch.com/market-report/air-conditioning-compressor-market/169709/#:~:text=Air%20Conditioning%20Compressor%20Market%20–%20increasing,to%20boost%20the%20market%20growth&text=Air%20Conditioning%20Compressor%20Market%20size,5.2%20%25%20during%20the%20forecast%20period.
A36: KOR | B36: =754*10^6*0.84 -> 633360000 | C36: €/yr | D36: =B36/'cost estimate'!$B$6*'cost estimate'!$B$31/10^6 -> 4.505211 | E36: GW | I36: 0.078 | J36: https://www.grandviewresearch.com/horizon/outlook/air-compressor-market/south-korea
A37: ROE | B37: =(4.6*10^9*0.84-B32-B33-B34-B29) -> 2622000000 | C37: €/yr | D37: =B37/'cost estimate'!$B$6*'cost estimate'!$B$31/10^6 -> 18.650788 | E37: GW | F37: 850.33 | I37: 0.176 | J37: https://www.gminsights.com/industry-analysis/europe-heat-pump-compressors-market
A38: ROW | B38: =B51*10^9*0.84 -> 1.91184e+10 | C38: €/yr | D38: =(B38/'cost estimate'!$B$6*'cost estimate'!$B$31/10^6)-SUM(D28:D37,D39) -> 25.91169 | E38: GW | F38: 836.2 | G38: kg Co2-eq / 4 Kw compressor | H38: ecoinevent | I38: 0.13766667 | J38: https://www.maximizemarketresearch.com/market-report/air-conditioning-compressor-market/169709/#:~:text=Air%20Conditioning%20Compressor%20Market%20–%20increasing,to%20boost%20the%20market%20growth&text=Air%20Conditioning%20Compressor%20Market%20size,5.2%20%25%20during%20the%20forecast%20period.
A39: USA | B39: =1*10^6 -> 1000000 | C39: units/year | D39: =B39*'cost estimate'!$B$31/10^6*$B$49 -> 8 | E39: GW | I39: 0.057
A42: Market size compressors | B42: 46.7 | C42: 10^9 USD | D42: 5.3 | E42: https://www.bsria.com/us/news/article/world_compressor_market_an_overview/?srsltid=AfmBOoofS_VauHvF8VQmVHWe5OgWs4tQRiutDIwbD5xMriB5_O1y6Fwz | F42: 1% market share heat pump
A43: Market size compressors | B43: 25.9 | C43: 10^9 USD | D43: 5 | E43: https://www.futuremarketinsights.com/reports/air-conditioning-compressor-market
A44: Average market size compressors HVAC | B44: =AVERAGE(B42:B43) -> 36.3
A45: in heat pumop | B45: =13.9 -> 13.9 | C45: 10^9 USD | D45: 13.7 | E45: https://www.gminsights.com/industry-analysis/heat-pump-compressors-market
A46: in heat pumop | B46: 13.1 | C46: 10^9 USD | D46: 13.7 | E46: https://www.verifiedmarketresearch.com/product/heat-pump-compressor-market/
A47: in heat pumop | B47: 14.2 | C47: 10^9 USD | D47: 13.9 | E47: https://www.strategicmarketresearch.com/market-report/heat-pump-compressors-market
A48: avergea hp global | B48: =AVERAGE(B45:B47) -> 13.733333 | D48: =AVERAGE(D45:D47) -> 13.766667
A49: conversino factor for heat pumps in compressors | B49: 1
B50: 0.37832874
A51: Average total | B51: =AVERAGE(B42:B43,B45:B47) -> 22.76
A53: Year | B53: AUS | C53: AUT | D53: BRA | E53: CHN | F53: CZE | G53: DEU | H53: ITA | I53: JPN | J53: KOR | K53: ROE | L53: ROW | M53: USA
A54: 2022 | B54: 1.3025676 | C54: 0 | D54: =D30 -> 7.2 | E54: 53.388 | F54: 1.9184277 | G54: 5.732521 | H54: 1.1836351 | I54: =D35 -> 8.2 | J54: =D36 -> 4.505211 | K54: 18.650788 | L54: =D38 -> 25.91169 | M54: 8
A55: 2023 | B55: =B$54*(1+$I$28)^($A55-$A$54) -> 1.3794191 | C55: =C$54*(1+$I$29)^($A55-$A$54) -> 0 | D55: =D$54*(1+$I$30)^($A55-$A$54) -> 7.416 | E55: =E$54*(1+$I$31)^($A55-$A$54) -> 57.552264 | F55: =F$54*(1+$I$32)^($A55-$A$54) -> 2.256071 | G55: =G$54*(1+$I$33)^($A55-$A$54) -> 6.7414447 | H55: =H$54*(1+$I$34)^($A55-$A$54) -> 1.3919548 | I55: =I$54*(1+$I$35)^($A55-$A$54) -> 8.8396 | J55: =J$54*(1+$I$36)^($A55-$A$54) -> 4.8566174 | K55: =K$54*(1+$I$37)^($A55-$A$54) -> 21.933327 | L55: =L$54*(1+$I$38)^($A55-$A$54) -> 29.478866 | M55: =M$54*(1+$I$39)^($A55-$A$54) -> 8.456
A56: 2024 | B56: =B$54*(1+$I$28)^($A56-$A$54) -> 1.4608048 | C56: =C$54*(1+$I$29)^($A56-$A$54) -> 0 | D56: =D$54*(1+$I$30)^($A56-$A$54) -> 7.63848 | E56: =E$54*(1+$I$31)^($A56-$A$54) -> 62.041341 | F56: =F$54*(1+$I$32)^($A56-$A$54) -> 2.6531395 | G56: =G$54*(1+$I$33)^($A56-$A$54) -> 7.927939 | H56: =H$54*(1+$I$34)^($A56-$A$54) -> 1.6369389 | I56: =I$54*(1+$I$35)^($A56-$A$54) -> 9.5290888 | J56: =J$54*(1+$I$36)^($A56-$A$54) -> 5.2354336 | K56: =K$54*(1+$I$37)^($A56-$A$54) -> 25.793592 | L56: =L$54*(1+$I$38)^($A56-$A$54) -> 33.537123 | M56: =M$54*(1+$I$39)^($A56-$A$54) -> 8.937992
A57: 2025 | B57: =B$54*(1+$I$28)^($A57-$A$54) -> 1.5469923 | C57: =C$54*(1+$I$29)^($A57-$A$54) -> 0 | D57: =D$54*(1+$I$30)^($A57-$A$54) -> 7.8676344 | E57: =E$54*(1+$I$31)^($A57-$A$54) -> 66.880565 | F57: =F$54*(1+$I$32)^($A57-$A$54) -> 3.1200921 | G57: =G$54*(1+$I$33)^($A57-$A$54) -> 9.3232563 | H57: =H$54*(1+$I$34)^($A57-$A$54) -> 1.9250401 | I57: =I$54*(1+$I$35)^($A57-$A$54) -> 10.272358 | J57: =J$54*(1+$I$36)^($A57-$A$54) -> 5.6437974 | K57: =K$54*(1+$I$37)^($A57-$A$54) -> 30.333265 | L57: =L$54*(1+$I$38)^($A57-$A$54) -> 38.154067 | M57: =M$54*(1+$I$39)^($A57-$A$54) -> 9.4474575
A58: 2026 | B58: =B$54*(1+$I$28)^($A58-$A$54) -> 1.6382649 | C58: =C$54*(1+$I$29)^($A58-$A$54) -> 0 | D58: =D$54*(1+$I$30)^($A58-$A$54) -> 8.1036634 | E58: =E$54*(1+$I$31)^($A58-$A$54) -> 72.097249 | F58: =F$54*(1+$I$32)^($A58-$A$54) -> 3.6692283 | G58: =G$54*(1+$I$33)^($A58-$A$54) -> 10.964149 | H58: =H$54*(1+$I$34)^($A58-$A$54) -> 2.2638472 | I58: =I$54*(1+$I$35)^($A58-$A$54) -> 11.073602 | J58: =J$54*(1+$I$36)^($A58-$A$54) -> 6.0840136 | K58: =K$54*(1+$I$37)^($A58-$A$54) -> 35.671919 | L58: =L$54*(1+$I$38)^($A58-$A$54) -> 43.40661 | M58: =M$54*(1+$I$39)^($A58-$A$54) -> 9.9859626
A59: 2027 | B59: =B$54*(1+$I$28)^($A59-$A$54) -> 1.7349225 | C59: =C$54*(1+$I$29)^($A59-$A$54) -> 0 | D59: =D$54*(1+$I$30)^($A59-$A$54) -> 8.3467733 | E59: =E$54*(1+$I$31)^($A59-$A$54) -> 77.720835 | F59: =F$54*(1+$I$32)^($A59-$A$54) -> 4.3150125 | G59: =G$54*(1+$I$33)^($A59-$A$54) -> 12.89384 | H59: =H$54*(1+$I$34)^($A59-$A$54) -> 2.6622843 | I59: =I$54*(1+$I$35)^($A59-$A$54) -> 11.937343 | J59: =J$54*(1+$I$36)^($A59-$A$54) -> 6.5585667 | K59: =K$54*(1+$I$37)^($A59-$A$54) -> 41.950177 | L59: =L$54*(1+$I$38)^($A59-$A$54) -> 49.382253 | M59: =M$54*(1+$I$39)^($A59-$A$54) -> 10.555162
A60: 2028 | B60: =B$54*(1+$I$28)^($A60-$A$54) -> 1.8372829 | C60: =C$54*(1+$I$29)^($A60-$A$54) -> 0 | D60: =D$54*(1+$I$30)^($A60-$A$54) -> 8.5971765 | E60: =E$54*(1+$I$31)^($A60-$A$54) -> 83.78306 | F60: =F$54*(1+$I$32)^($A60-$A$54) -> 5.0744547 | G60: =G$54*(1+$I$33)^($A60-$A$54) -> 15.163155 | H60: =H$54*(1+$I$34)^($A60-$A$54) -> 3.1308463 | I60: =I$54*(1+$I$35)^($A60-$A$54) -> 12.868455 | J60: =J$54*(1+$I$36)^($A60-$A$54) -> 7.0701348 | K60: =K$54*(1+$I$37)^($A60-$A$54) -> 49.333408 | L60: =L$54*(1+$I$38)^($A60-$A$54) -> 56.180543 | M60: =M$54*(1+$I$39)^($A60-$A$54) -> 11.156807
A61: 2029 | B61: =B$54*(1+$I$28)^($A61-$A$54) -> 1.9456826 | C61: =C$54*(1+$I$29)^($A61-$A$54) -> 0 | D61: =D$54*(1+$I$30)^($A61-$A$54) -> 8.8550918 | E61: =E$54*(1+$I$31)^($A61-$A$54) -> 90.318138 | F61: =F$54*(1+$I$32)^($A61-$A$54) -> 5.9675587 | G61: =G$54*(1+$I$33)^($A61-$A$54) -> 17.831871 | H61: =H$54*(1+$I$34)^($A61-$A$54) -> 3.6818753 | I61: =I$54*(1+$I$35)^($A61-$A$54) -> 13.872195 | J61: =J$54*(1+$I$36)^($A61-$A$54) -> 7.6216054 | K61: =K$54*(1+$I$37)^($A61-$A$54) -> 58.016088 | L61: =L$54*(1+$I$38)^($A61-$A$54) -> 63.914731 | M61: =M$54*(1+$I$39)^($A61-$A$54) -> 11.792745
A62: 2030 | B62: =B$54*(1+$I$28)^($A62-$A$54) -> 2.0604779 | C62: =C$54*(1+$I$29)^($A62-$A$54) -> 0 | D62: =D$54*(1+$I$30)^($A62-$A$54) -> 9.1207446 | E62: =E$54*(1+$I$31)^($A62-$A$54) -> 97.362953 | F62: =F$54*(1+$I$32)^($A62-$A$54) -> 7.017849 | G62: =G$54*(1+$I$33)^($A62-$A$54) -> 20.97028 | H62: =H$54*(1+$I$34)^($A62-$A$54) -> 4.3298853 | I62: =I$54*(1+$I$35)^($A62-$A$54) -> 14.954226 | J62: =J$54*(1+$I$36)^($A62-$A$54) -> 8.2160906 | K62: =K$54*(1+$I$37)^($A62-$A$54) -> 68.226919 | L62: =L$54*(1+$I$38)^($A62-$A$54) -> 72.713659 | M62: =M$54*(1+$I$39)^($A62-$A$54) -> 12.464931
A63: 2031 | B63: =B$54*(1+$I$28)^($A63-$A$54) -> 2.1820461 | C63: =C$54*(1+$I$29)^($A63-$A$54) -> 0 | D63: =D$54*(1+$I$30)^($A63-$A$54) -> 9.3943669 | E63: =E$54*(1+$I$31)^($A63-$A$54) -> 104.95726 | F63: =F$54*(1+$I$32)^($A63-$A$54) -> 8.2529904 | G63: =G$54*(1+$I$33)^($A63-$A$54) -> 24.661049 | H63: =H$54*(1+$I$34)^($A63-$A$54) -> 5.0919452 | I63: =I$54*(1+$I$35)^($A63-$A$54) -> 16.120656 | J63: =J$54*(1+$I$36)^($A63-$A$54) -> 8.8569457 | K63: =K$54*(1+$I$37)^($A63-$A$54) -> 80.234857 | L63: =L$54*(1+$I$38)^($A63-$A$54) -> 82.723907 | M63: =M$54*(1+$I$39)^($A63-$A$54) -> 13.175432
A64: 2032 | B64: =B$54*(1+$I$28)^($A64-$A$54) -> 2.3107868 | C64: =C$54*(1+$I$29)^($A64-$A$54) -> 0 | D64: =D$54*(1+$I$30)^($A64-$A$54) -> 9.6761979 | E64: =E$54*(1+$I$31)^($A64-$A$54) -> 113.14393 | F64: =F$54*(1+$I$32)^($A64-$A$54) -> 9.7055168 | G64: =G$54*(1+$I$33)^($A64-$A$54) -> 29.001394 | H64: =H$54*(1+$I$34)^($A64-$A$54) -> 5.9881275 | I64: =I$54*(1+$I$35)^($A64-$A$54) -> 17.378067 | J64: =J$54*(1+$I$36)^($A64-$A$54) -> 9.5477874 | K64: =K$54*(1+$I$37)^($A64-$A$54) -> 94.356192 | L64: =L$54*(1+$I$38)^($A64-$A$54) -> 94.112231 | M64: =M$54*(1+$I$39)^($A64-$A$54) -> 13.926432
A65: 2033 | B65: =B$54*(1+$I$28)^($A65-$A$54) -> 2.4471232 | C65: =C$54*(1+$I$29)^($A65-$A$54) -> 0 | D65: =D$54*(1+$I$30)^($A65-$A$54) -> 9.9664839 | E65: =E$54*(1+$I$31)^($A65-$A$54) -> 121.96916 | F65: =F$54*(1+$I$32)^($A65-$A$54) -> 11.413688 | G65: =G$54*(1+$I$33)^($A65-$A$54) -> 34.105639 | H65: =H$54*(1+$I$34)^($A65-$A$54) -> 7.042038 | I65: =I$54*(1+$I$35)^($A65-$A$54) -> 18.733556 | J65: =J$54*(1+$I$36)^($A65-$A$54) -> 10.292515 | K65: =K$54*(1+$I$37)^($A65-$A$54) -> 110.96288 | L65: =L$54*(1+$I$38)^($A65-$A$54) -> 107.06835 | M65: =M$54*(1+$I$39)^($A65-$A$54) -> 14.720239
A66: 2034 | B66: =B$54*(1+$I$28)^($A66-$A$54) -> 2.5915035 | C66: =C$54*(1+$I$29)^($A66-$A$54) -> 0 | D66: =D$54*(1+$I$30)^($A66-$A$54) -> 10.265478 | E66: =E$54*(1+$I$31)^($A66-$A$54) -> 131.48275 | F66: =F$54*(1+$I$32)^($A66-$A$54) -> 13.422497 | G66: =G$54*(1+$I$33)^($A66-$A$54) -> 40.108232 | H66: =H$54*(1+$I$34)^($A66-$A$54) -> 8.2814366 | I66: =I$54*(1+$I$35)^($A66-$A$54) -> 20.194773 | J66: =J$54*(1+$I$36)^($A66-$A$54) -> 11.095331 | K66: =K$54*(1+$I$37)^($A66-$A$54) -> 130.49235 | L66: =L$54*(1+$I$38)^($A66-$A$54) -> 121.80809 | M66: =M$54*(1+$I$39)^($A66-$A$54) -> 15.559292
A67: 2035 | B67: =B$54*(1+$I$28)^($A67-$A$54) -> 2.7444022 | C67: =C$54*(1+$I$29)^($A67-$A$54) -> 0 | D67: =D$54*(1+$I$30)^($A67-$A$54) -> 10.573443 | E67: =E$54*(1+$I$31)^($A67-$A$54) -> 141.73841 | F67: =F$54*(1+$I$32)^($A67-$A$54) -> 15.784856 | G67: =G$54*(1+$I$33)^($A67-$A$54) -> 47.167281 | H67: =H$54*(1+$I$34)^($A67-$A$54) -> 9.7389695 | I67: =I$54*(1+$I$35)^($A67-$A$54) -> 21.769966 | J67: =J$54*(1+$I$36)^($A67-$A$54) -> 11.960767 | K67: =K$54*(1+$I$37)^($A67-$A$54) -> 153.459 | L67: =L$54*(1+$I$38)^($A67-$A$54) -> 138.577 | M67: =M$54*(1+$I$39)^($A67-$A$54) -> 16.446172
A69: Leanring rate | B69: 0.1 | C69: http://www.strategosinc.com/downloads/learning-curves-dl1.pdf
A71: OPEX evolution | B71: AUS | C71: AUT | D71: BRA | E71: CHN | F71: CZE | G71: DEU | H71: ITA | I71: JPN | J71: KOR | K71: ROE | L71: ROW | M71: USA | O71: OPEX evolution | P71: AUS | Q71: AUT | R71: BRA | S71: CHN | T71: CZE | U71: DEU | V71: ITA | W71: JPN | X71: KOR | Y71: ROE | Z71: ROW | AA71: USA
A72: 2022 | B72: 56.094164 | C72: 86.351237 | D72: 50.159654 | E72: 28.287745 | F72: 77.674003 | G72: 87.446801 | H72: 84.229333 | I72: 79.449915 | J72: 53.106283 | K72: 77.734502 | L72: 53.991165 | M72: 96.95507 | O72: 2022 | P72: 56.094164 | Q72: 86.351237 | R72: 50.159654 | S72: 28.287745 | T72: 77.674003 | U72: 87.446801 | V72: 84.229333 | W72: 79.449915 | X72: 53.106283 | Y72: 77.734502 | Z72: 53.991165 | AA72: 96.95507
A73: 2023 | B73: =B$72*(1-$B$69)^LOG(B55/B$54,2) -> 55.607506 | C73: =IF(C54>0,C$72*(1-$B$69)^LOG(C55/C$54,2),C72) -> 86.351237 | D73: =IF(D54>0,D$72*(1-$B$69)^LOG(D55/D$54,2),D72) -> 49.934791 | E73: =IF(E54>0,E$72*(1-$B$69)^LOG(E55/E$54,2),E72) -> 27.966632 | F73: =IF(F54>0,F$72*(1-$B$69)^LOG(F55/F$54,2),F72) -> 75.783308 | G73: =IF(G54>0,G$72*(1-$B$69)^LOG(G55/G$54,2),G72) -> 85.318222 | H73: =IF(H54>0,H$72*(1-$B$69)^LOG(H55/H$54,2),H72) -> 82.179071 | I73: =IF(I54>0,I$72*(1-$B$69)^LOG(I55/I$54,2),I72) -> 78.548028 | J73: =IF(J54>0,J$72*(1-$B$69)^LOG(J55/J$54,2),J72) -> 52.503439 | ... M73: =IF(M54>0,M$72*(1-$B$69)^LOG(M55/M$54,2),M72) -> 96.141535 | O73: 2023 | P73: 55.607506 | Q73: 86.351237 | R73: 49.934791 | S73: 27.966632 | T73: 75.783308 | U73: 85.318222 | V73: 82.179071 | W73: 78.548028 | X73: 52.503439 | Y73: 75.842334 | Z73: 52.942962 | AA73: 96.141535
A74: 2024 | B74: =B$72*(1-$B$69)^LOG(B56/B$54,2) -> 55.12507 | C74: =IF(C55>0,C$72*(1-$B$69)^LOG(C56/C$54,2),C73) -> 86.351237 | D74: =IF(D55>0,D$72*(1-$B$69)^LOG(D56/D$54,2),D73) -> 49.710936 | E74: =IF(E55>0,E$72*(1-$B$69)^LOG(E56/E$54,2),E73) -> 27.649165 | F74: =IF(F55>0,F$72*(1-$B$69)^LOG(F56/F$54,2),F73) -> 73.938635 | G74: =IF(G55>0,G$72*(1-$B$69)^LOG(G56/G$54,2),G73) -> 83.241456 | H74: =IF(H55>0,H$72*(1-$B$69)^LOG(H56/H$54,2),H73) -> 80.178716 | I74: =IF(I55>0,I$72*(1-$B$69)^LOG(I56/I$54,2),I73) -> 77.656379 | J74: =IF(J55>0,J$72*(1-$B$69)^LOG(J56/J$54,2),J73) -> 51.907439 | ... M74: =IF(M55>0,M$72*(1-$B$69)^LOG(M56/M$54,2),M73) -> 95.334826 | O74: 2024 | P74: 55.12507 | Q74: 86.351237 | R74: 49.710936 | S74: 27.649165 | T74: 73.938635 | U74: 83.241456 | V74: 80.178716 | W74: 77.656379 | X74: 51.907439 | Y74: 73.996224 | Z74: 51.91511 | AA74: 95.334826
A75: 2025 | B75: =B$72*(1-$B$69)^LOG(B57/B$54,2) -> 54.64682 | C75: =IF(C56>0,C$72*(1-$B$69)^LOG(C57/C$54,2),C74) -> 86.351237 | D75: =IF(D56>0,D$72*(1-$B$69)^LOG(D57/D$54,2),D74) -> 49.488084 | E75: =IF(E56>0,E$72*(1-$B$69)^LOG(E57/E$54,2),E74) -> 27.335301 | F75: =IF(F56>0,F$72*(1-$B$69)^LOG(F57/F$54,2),F74) -> 72.138864 | G75: =IF(G56>0,G$72*(1-$B$69)^LOG(G57/G$54,2),G74) -> 81.215241 | H75: =IF(H56>0,H$72*(1-$B$69)^LOG(H57/H$54,2),H74) -> 78.227053 | I75: =IF(I56>0,I$72*(1-$B$69)^LOG(I57/I$54,2),I74) -> 76.774851 | J75: =IF(J56>0,J$72*(1-$B$69)^LOG(J57/J$54,2),J74) -> 51.318204 | ... M75: =IF(M56>0,M$72*(1-$B$69)^LOG(M57/M$54,2),M74) -> 94.534886 | O75: 2025 | P75: 54.64682 | Q75: 86.351237 | R75: 49.488084 | S75: 27.335301 | T75: 72.138864 | U75: 81.215241 | V75: 78.227053 | W75: 76.774851 | X75: 51.318204 | Y75: 72.195051 | Z75: 50.907213 | AA75: 94.534886
A76: 2026 | B76: =B$72*(1-$B$69)^LOG(B58/B$54,2) -> 54.172719 | C76: =IF(C57>0,C$72*(1-$B$69)^LOG(C58/C$54,2),C75) -> 86.351237 | D76: =IF(D57>0,D$72*(1-$B$69)^LOG(D58/D$54,2),D75) -> 49.266232 | E76: =IF(E57>0,E$72*(1-$B$69)^LOG(E58/E$54,2),E75) -> 27.025001 | F76: =IF(F57>0,F$72*(1-$B$69)^LOG(F58/F$54,2),F75) -> 70.382901 | G76: =IF(G57>0,G$72*(1-$B$69)^LOG(G58/G$54,2),G75) -> 79.238347 | H76: =IF(H57>0,H$72*(1-$B$69)^LOG(H58/H$54,2),H75) -> 76.322895 | I76: =IF(I57>0,I$72*(1-$B$69)^LOG(I58/I$54,2),I75) -> 75.90333 | J76: =IF(J57>0,J$72*(1-$B$69)^LOG(J58/J$54,2),J75) -> 50.735658 | ... M76: =IF(M57>0,M$72*(1-$B$69)^LOG(M58/M$54,2),M75) -> 93.741659 | O76: 2026 | P76: 54.172719 | Q76: 86.351237 | R76: 49.266232 | S76: 27.025001 | T76: 70.382901 | U76: 79.238347 | V76: 76.322895 | W76: 75.90333 | X76: 50.735658 | Y76: 70.437721 | Z76: 49.918883 | AA76: 93.741659
A77: 2027 | B77: =B$72*(1-$B$69)^LOG(B59/B$54,2) -> 53.702731 | C77: =IF(C58>0,C$72*(1-$B$69)^LOG(C59/C$54,2),C76) -> 86.351237 | D77: =IF(D58>0,D$72*(1-$B$69)^LOG(D59/D$54,2),D76) -> 49.045374 | E77: =IF(E58>0,E$72*(1-$B$69)^LOG(E59/E$54,2),E76) -> 26.718222 | F77: =IF(F58>0,F$72*(1-$B$69)^LOG(F59/F$54,2),F76) -> 68.669682 | G77: =IF(G58>0,G$72*(1-$B$69)^LOG(G59/G$54,2),G76) -> 77.309573 | H77: =IF(H58>0,H$72*(1-$B$69)^LOG(H59/H$54,2),H76) -> 74.465088 | I77: =IF(I58>0,I$72*(1-$B$69)^LOG(I59/I$54,2),I76) -> 75.041702 | J77: =IF(J58>0,J$72*(1-$B$69)^LOG(J59/J$54,2),J76) -> 50.159725 | ... M77: =IF(M58>0,M$72*(1-$B$69)^LOG(M59/M$54,2),M76) -> 92.955087 | O77: 2027 | P77: 53.702731 | Q77: 86.351237 | R77: 49.045374 | S77: 26.718222 | T77: 68.669682 | U77: 77.309573 | V77: 74.465088 | W77: 75.041702 | X77: 50.159725 | Y77: 68.723167 | Z77: 48.949742 | AA77: 92.955087
A78: 2028 | B78: =B$72*(1-$B$69)^LOG(B60/B$54,2) -> 53.23682 | C78: =IF(C59>0,C$72*(1-$B$69)^LOG(C60/C$54,2),C77) -> 86.351237 | D78: =IF(D59>0,D$72*(1-$B$69)^LOG(D60/D$54,2),D77) -> 48.825506 | E78: =IF(E59>0,E$72*(1-$B$69)^LOG(E60/E$54,2),E77) -> 26.414926 | F78: =IF(F59>0,F$72*(1-$B$69)^LOG(F60/F$54,2),F77) -> 66.998164 | G78: =IF(G59>0,G$72*(1-$B$69)^LOG(G60/G$54,2),G77) -> 75.427748 | H78: =IF(H59>0,H$72*(1-$B$69)^LOG(H60/H$54,2),H77) -> 72.652502 | I78: =IF(I59>0,I$72*(1-$B$69)^LOG(I60/I$54,2),I77) -> 74.189855 | J78: =IF(J59>0,J$72*(1-$B$69)^LOG(J60/J$54,2),J77) -> 49.590329 | ... M78: =IF(M59>0,M$72*(1-$B$69)^LOG(M60/M$54,2),M77) -> 92.175115 | O78: 2028 | P78: 53.23682 | Q78: 86.351237 | R78: 48.825506 | S78: 26.414926 | T78: 66.998164 | U78: 75.427748 | V78: 72.652502 | W78: 74.189855 | X78: 49.590329 | Y78: 67.050348 | Z78: 47.999415 | AA78: 92.175115
A79: 2029 | B79: =B$72*(1-$B$69)^LOG(B61/B$54,2) -> 52.774951 | C79: =IF(C60>0,C$72*(1-$B$69)^LOG(C61/C$54,2),C78) -> 86.351237 | D79: =IF(D60>0,D$72*(1-$B$69)^LOG(D61/D$54,2),D78) -> 48.606623 | E79: =IF(E60>0,E$72*(1-$B$69)^LOG(E61/E$54,2),E78) -> 26.115074 | F79: =IF(F60>0,F$72*(1-$B$69)^LOG(F61/F$54,2),F78) -> 65.367334 | G79: =IF(G60>0,G$72*(1-$B$69)^LOG(G61/G$54,2),G78) -> 73.59173 | H79: =IF(H60>0,H$72*(1-$B$69)^LOG(H61/H$54,2),H78) -> 70.884037 | I79: =IF(I60>0,I$72*(1-$B$69)^LOG(I61/I$54,2),I78) -> 73.347678 | J79: =IF(J60>0,J$72*(1-$B$69)^LOG(J61/J$54,2),J78) -> 49.027397 | ... M79: =IF(M60>0,M$72*(1-$B$69)^LOG(M61/M$54,2),M78) -> 91.401688 | O79: 2029 | P79: 52.774951 | Q79: 86.351237 | R79: 48.606623 | S79: 26.115074 | T79: 65.367334 | U79: 73.59173 | V79: 70.884037 | W79: 73.347678 | X79: 49.027397 | Y79: 65.418248 | Z79: 47.067538 | AA79: 91.401688
A80: 2030 | B80: =B$72*(1-$B$69)^LOG(B62/B$54,2) -> 52.31709 | C80: =IF(C61>0,C$72*(1-$B$69)^LOG(C62/C$54,2),C79) -> 86.351237 | D80: =IF(D61>0,D$72*(1-$B$69)^LOG(D62/D$54,2),D79) -> 48.388722 | E80: =IF(E61>0,E$72*(1-$B$69)^LOG(E62/E$54,2),E79) -> 25.818624 | F80: =IF(F61>0,F$72*(1-$B$69)^LOG(F62/F$54,2),F79) -> 63.776201 | G80: =IF(G61>0,G$72*(1-$B$69)^LOG(G62/G$54,2),G79) -> 71.800403 | H80: =IF(H61>0,H$72*(1-$B$69)^LOG(H62/H$54,2),H79) -> 69.158619 | I80: =IF(I61>0,I$72*(1-$B$69)^LOG(I62/I$54,2),I79) -> 72.515061 | J80: =IF(J61>0,J$72*(1-$B$69)^LOG(J62/J$54,2),J79) -> 48.470856 | ... M80: =IF(M61>0,M$72*(1-$B$69)^LOG(M62/M$54,2),M79) -> 90.634751 | O80: 2030 | P80: 52.31709 | Q80: 86.351237 | R80: 48.388722 | S80: 25.818624 | T80: 63.776201 | U80: 71.800403 | V80: 69.158619 | W80: 72.515061 | X80: 48.470856 | Y80: 63.825875 | Z80: 46.153754 | AA80: 90.634751
A81: 2031 | B81: =B$72*(1-$B$69)^LOG(B63/B$54,2) -> 51.863201 | C81: =IF(C62>0,C$72*(1-$B$69)^LOG(C63/C$54,2),C80) -> 86.351237 | D81: =IF(D62>0,D$72*(1-$B$69)^LOG(D63/D$54,2),D80) -> 48.171798 | E81: =IF(E62>0,E$72*(1-$B$69)^LOG(E63/E$54,2),E80) -> 25.525541 | F81: =IF(F62>0,F$72*(1-$B$69)^LOG(F63/F$54,2),F80) -> 62.223797 | G81: =IF(G62>0,G$72*(1-$B$69)^LOG(G63/G$54,2),G80) -> 70.05268 | H81: =IF(H62>0,H$72*(1-$B$69)^LOG(H63/H$54,2),H80) -> 67.4752 | I81: =IF(I62>0,I$72*(1-$B$69)^LOG(I63/I$54,2),I80) -> 71.691896 | J81: =IF(J62>0,J$72*(1-$B$69)^LOG(J63/J$54,2),J80) -> 47.920632 | ... M81: =IF(M62>0,M$72*(1-$B$69)^LOG(M63/M$54,2),M80) -> 89.874248 | O81: 2031 | P81: 51.863201 | Q81: 86.351237 | R81: 48.171798 | S81: 25.525541 | T81: 62.223797 | U81: 70.05268 | V81: 67.4752 | W81: 71.691896 | X81: 47.920632 | Y81: 62.272263 | Z81: 45.257709 | AA81: 89.874248
A82: 2032 | B82: =B$72*(1-$B$69)^LOG(B64/B$54,2) -> 51.413249 | C82: =IF(C63>0,C$72*(1-$B$69)^LOG(C64/C$54,2),C81) -> 86.351237 | D82: =IF(D63>0,D$72*(1-$B$69)^LOG(D64/D$54,2),D81) -> 47.955846 | E82: =IF(E63>0,E$72*(1-$B$69)^LOG(E64/E$54,2),E81) -> 25.235784 | F82: =IF(F63>0,F$72*(1-$B$69)^LOG(F64/F$54,2),F81) -> 60.709182 | G82: =IF(G63>0,G$72*(1-$B$69)^LOG(G64/G$54,2),G81) -> 68.347498 | H82: =IF(H63>0,H$72*(1-$B$69)^LOG(H64/H$54,2),H81) -> 65.832758 | I82: =IF(I63>0,I$72*(1-$B$69)^LOG(I64/I$54,2),I81) -> 70.878075 | J82: =IF(J63>0,J$72*(1-$B$69)^LOG(J64/J$54,2),J81) -> 47.376653 | ... M82: =IF(M63>0,M$72*(1-$B$69)^LOG(M64/M$54,2),M81) -> 89.120127 | O82: 2032 | P82: 51.413249 | Q82: 86.351237 | R82: 47.955846 | S82: 25.235784 | T82: 60.709182 | U82: 68.347498 | V82: 65.832758 | W82: 70.878075 | X82: 47.376653 | Y82: 60.756467 | Z82: 44.379061 | AA82: 89.120127
A83: 2033 | B83: =B$72*(1-$B$69)^LOG(B65/B$54,2) -> 50.967202 | C83: =IF(C64>0,C$72*(1-$B$69)^LOG(C65/C$54,2),C82) -> 86.351237 | D83: =IF(D64>0,D$72*(1-$B$69)^LOG(D65/D$54,2),D82) -> 47.740862 | E83: =IF(E64>0,E$72*(1-$B$69)^LOG(E65/E$54,2),E82) -> 24.949316 | F83: =IF(F64>0,F$72*(1-$B$69)^LOG(F65/F$54,2),F82) -> 59.231435 | G83: =IF(G64>0,G$72*(1-$B$69)^LOG(G65/G$54,2),G82) -> 66.683823 | H83: =IF(H64>0,H$72*(1-$B$69)^LOG(H65/H$54,2),H82) -> 64.230296 | I83: =IF(I64>0,I$72*(1-$B$69)^LOG(I65/I$54,2),I82) -> 70.073492 | J83: =IF(J64>0,J$72*(1-$B$69)^LOG(J65/J$54,2),J82) -> 46.83885 | ... M83: =IF(M64>0,M$72*(1-$B$69)^LOG(M65/M$54,2),M82) -> 88.372334 | O83: 2033 | P83: 50.967202 | Q83: 86.351237 | R83: 47.740862 | S83: 24.949316 | T83: 59.231435 | U83: 66.683823 | V83: 64.230296 | W83: 70.073492 | X83: 46.83885 | Y83: 59.277569 | Z83: 43.517471 | AA83: 88.372334
A84: 2034 | B84: =B$72*(1-$B$69)^LOG(B66/B$54,2) -> 50.525024 | C84: =IF(C65>0,C$72*(1-$B$69)^LOG(C66/C$54,2),C83) -> 86.351237 | D84: =IF(D65>0,D$72*(1-$B$69)^LOG(D66/D$54,2),D83) -> 47.526842 | E84: =IF(E65>0,E$72*(1-$B$69)^LOG(E66/E$54,2),E83) -> 24.6661 | F84: =IF(F65>0,F$72*(1-$B$69)^LOG(F66/F$54,2),F83) -> 57.789657 | G84: =IF(G65>0,G$72*(1-$B$69)^LOG(G66/G$54,2),G83) -> 65.060644 | H84: =IF(H65>0,H$72*(1-$B$69)^LOG(H66/H$54,2),H83) -> 62.666839 | I84: =IF(I65>0,I$72*(1-$B$69)^LOG(I66/I$54,2),I83) -> 69.278043 | J84: =IF(J65>0,J$72*(1-$B$69)^LOG(J66/J$54,2),J83) -> 46.307152 | ... M84: =IF(M65>0,M$72*(1-$B$69)^LOG(M66/M$54,2),M83) -> 87.630816 | O84: 2034 | P84: 50.525024 | Q84: 86.351237 | R84: 47.526842 | S84: 24.6661 | T84: 57.789657 | U84: 65.060644 | V84: 62.666839 | W84: 69.278043 | X84: 46.307152 | Y84: 57.834669 | Z84: 42.672609 | AA84: 87.630816
A85: 2035 | B85: =B$72*(1-$B$69)^LOG(B67/B$54,2) -> 50.086682 | C85: =IF(C66>0,C$72*(1-$B$69)^LOG(C67/C$54,2),C84) -> 86.351237 | D85: =IF(D66>0,D$72*(1-$B$69)^LOG(D67/D$54,2),D84) -> 47.313782 | E85: =IF(E66>0,E$72*(1-$B$69)^LOG(E67/E$54,2),E84) -> 24.386099 | F85: =IF(F66>0,F$72*(1-$B$69)^LOG(F67/F$54,2),F84) -> 56.382975 | G85: =IF(G66>0,G$72*(1-$B$69)^LOG(G67/G$54,2),G84) -> 63.476976 | H85: =IF(H66>0,H$72*(1-$B$69)^LOG(H67/H$54,2),H84) -> 61.14144 | I85: =IF(I66>0,I$72*(1-$B$69)^LOG(I67/I$54,2),I84) -> 68.491623 | J85: =IF(J66>0,J$72*(1-$B$69)^LOG(J67/J$54,2),J84) -> 45.78149 | ... M85: =IF(M66>0,M$72*(1-$B$69)^LOG(M67/M$54,2),M84) -> 86.895519 | O85: 2035 | P85: 50.086682 | Q85: 86.351237 | R85: 47.313782 | S85: 24.386099 | T85: 56.382975 | U85: 63.476976 | V85: 61.14144 | W85: 68.491623 | X85: 45.78149 | Y85: 56.426891 | Z85: 41.844149 | AA85: 86.895519
A87: OPEX evolution | B87: 2022 | C87: 2023 | D87: 2024 | E87: 2025 | F87: 2026 | G87: 2027 | H87: 2028 | I87: 2029 | J87: 2030 | K87: 2031 | L87: 2032 | M87: 2033 | N87: 2034 | O87: 2035
A88: AUS | B88: 0.0064034434 | C88: 0.0063478889 | D88: 0.0062928163 | E88: 0.0062382215 | F88: 0.0061841003 | G88: 0.0061304487 | H88: 0.0060772625 | I88: 0.0060245378 | J88: 0.0059722705 | K88: 0.0059204567 | L88: 0.0058690924 | M88: 0.0058181737 | N88: 0.0057676968 | O88: 0.0057176578
A89: AUT | B89: 0.0098574471 | C89: 0.0098574471 | D89: 0.0098574471 | E89: 0.0098574471 | F89: 0.0098574471 | G89: 0.0098574471 | H89: 0.0098574471 | I89: 0.0098574471 | J89: 0.0098574471 | K89: 0.0098574471 | L89: 0.0098574471 | M89: 0.0098574471 | N89: 0.0098574471 | O89: 0.0098574471
A90: BRA | B90: 0.005725988 | C90: 0.0057003186 | D90: 0.0056747644 | E90: 0.0056493247 | F90: 0.005623999 | G90: 0.0055987869 | H90: 0.0055736879 | I90: 0.0055487013 | J90: 0.0055238267 | K90: 0.0054990637 | L90: 0.0054744117 | M90: 0.0054498701 | N90: 0.0054254386 | O90: 0.0054011167
A91: CHN | B91: 0.0032291946 | C91: 0.0031925379 | D91: 0.0031562973 | E91: 0.0031204682 | F91: 0.0030850457 | G91: 0.0030500254 | H91: 0.0030154026 | I91: 0.0029811728 | J91: 0.0029473316 | K91: 0.0029138745 | L91: 0.0028807972 | M91: 0.0028480954 | N91: 0.0028157649 | O91: 0.0027838013
A92: CZE | B92: 0.0088668953 | C92: 0.0086510625 | D92: 0.0084404834 | E92: 0.0082350301 | F92: 0.0080345778 | G92: 0.0078390048 | H92: 0.0076481923 | I92: 0.0074620244 | J92: 0.0072803882 | K92: 0.0071031732 | L92: 0.0069302719 | M92: 0.0067615793 | N92: 0.0065969929 | O92: 0.0064364127
A93: DEU | B93: 0.0099825116 | C93: 0.0097395231 | D93: 0.0095024493 | E93: 0.0092711462 | F93: 0.0090454734 | G93: 0.0088252937 | H93: 0.0086104736 | I93: 0.0084008824 | J93: 0.008196393 | K93: 0.0079968812 | L93: 0.0078022258 | M93: 0.0076123086 | N93: 0.0074270142 | O93: 0.0072462301
A94: ITA | B94: 0.0096152206 | C94: 0.0093811725 | D94: 0.0091528215 | E94: 0.0089300288 | F94: 0.0087126593 | G94: 0.0085005808 | H94: 0.0082936646 | I94: 0.0080917851 | J94: 0.0078948195 | K94: 0.0077026484 | L94: 0.0075151551 | M94: 0.0073322255 | N94: 0.0071537488 | O94: 0.0069796164
A95: JPN | B95: 0.0090696251 | C95: 0.0089666699 | D95: 0.0088648834 | E95: 0.0087642524 | F95: 0.0086647637 | G95: 0.0085664044 | H95: 0.0084691616 | I95: 0.0083730226 | J95: 0.008277975 | K95: 0.0081840064 | L95: 0.0080911045 | M95: 0.0079992571 | N95: 0.0079084524 | O95: 0.0078186784
A96: KOR | B96: 0.0060623611 | C96: 0.0059935433 | D96: 0.0059255067 | E96: 0.0058582425 | F96: 0.0057917418 | G96: 0.005725996 | H96: 0.0056609965 | I96: 0.0055967348 | J96: 0.0055332027 | K96: 0.0054703917 | L96: 0.0054082938 | M96: 0.0053469007 | N96: 0.0052862046 | O96: 0.0052261975
A97: ROE | B97: 0.0088738016 | C97: 0.0086578007 | D97: 0.0084470576 | E97: 0.0082414442 | F97: 0.0080408358 | G97: 0.0078451104 | H97: 0.0076541493 | I97: 0.0074678365 | J97: 0.0072860588 | K97: 0.0071087058 | L97: 0.0069356698 | M97: 0.0067668458 | N97: 0.0066021311 | O97: 0.0064414259
A98: ROW | B98: 0.0061633749 | C98: 0.0060437171 | D98: 0.0059263824 | E98: 0.0058113257 | F98: 0.0056985027 | G98: 0.00558787 | H98: 0.0054793853 | I98: 0.0053730067 | J98: 0.0052686933 | K98: 0.0051664052 | L98: 0.0050661029 | M98: 0.0049677479 | N98: 0.0048713024 | O98: 0.0047767293
A99: USA | B99: 0.01106793 | C99: 0.010975061 | D99: 0.010882971 | E99: 0.010791654 | F99: 0.010701103 | G99: 0.010611311 | H99: 0.010522273 | I99: 0.010433983 | J99: 0.010346433 | K99: 0.010259617 | L99: 0.010173531 | M99: 0.010088166 | N99: 0.010003518 | O99: 0.0099195798
B102: =B72/8760 -> 0.0064034434 | C102: =C72/8760 -> 0.0098574471

Sheet Heat Exchanger
A1: Country | B1: Market value | C1: Unit | D1: Year | E1: CAGR | F1: Source | G1: Notes
A2: Europe | B2: =6000*0.84 -> 5040 | C2: Mio. € | D2: 2024 | E2: 0.042 | F2: https://www.imarcgroup.com/europe-heat-exchanger-market
B3: =8800*0.84 -> 7392 | C3: Mio. € | D3: 2032
A4: Europe | B4: 900 | C4: Mio. € | D4: 2024 | E4: 18.9 | F4: https://www.gminsights.com/industry-analysis/europe-heat-pump-brazed-plate-heat-exchangers-market | G4: value fopr brazed plate heat exchanger in HP used in AC
A5: Europe | B5: 4700 | C5: Mio. € | D5: 2032 | F5: https://www.gminsights.com/industry-analysis/europe-heat-pump-brazed-plate-heat-exchangers-market | G5: estimate
A6: Italy | B6: =B4*0.26 -> 234 | C6: Mio. € | D6: 2024 | F6: https://www.cbi.eu/sites/default/files/market-information/product-factsheet-europe-heat-exchangers-2016.pdf | G6: used share to estimate HP value in country
A7: Germany | B7: =B4*0.2 -> 180 | C7: Mio. € | D7: 2024 | F7: https://www.cbi.eu/sites/default/files/market-information/product-factsheet-europe-heat-exchangers-2016.pdf | G7: used share to estimate HP value in country
A8: France | B8: =B4*0.13 -> 117 | C8: Mio. € | D8: 2024 | F8: https://www.cbi.eu/sites/default/files/market-information/product-factsheet-europe-heat-exchangers-2016.pdf | G8: used share to estimate HP value in country
A9: Austria | B9: =B4*0.04 -> 36 | C9: Mio. € | D9: 2024 | F9: https://www.cbi.eu/sites/default/files/market-information/product-factsheet-europe-heat-exchangers-2016.pdf | G9: used share to estimate HP value in country
A10: Czech Republic | B10: =B4*0.03 -> 27 | C10: Mio. € | D10: 2024 | F10: https://www.cbi.eu/sites/default/files/market-information/product-factsheet-europe-heat-exchangers-2016.pdf | G10: used share to estimate HP value in country
A11: Sweden | B11: =0.09*B4 -> 81 | C11: Mio. € | D11: 2024
A12: China | B12: 4242.5 | C12: Mio. USD | D12: 2023 | E12: 0.065 | F12: https://www.nextmsc.com/report/china-heat-exchangers-market | G12: aound 30% of HX industry are in petroleum and chemical industry source: https://heat-exchanger-world.com/featured-story-the-fast-growing-heat-exchanger-market-in-china/)
A13: China | B13: 6872.1 | C13: Mio. USD | D13: 2030 | F13: https://www.nextmsc.com/report/china-heat-exchangers-market
A14: China | B14: =3.2*10^3 -> 3200 | C14: Mio. RMB | D14: 2021 | F14: http://www.chinaiol.com/download/Global%20Heat%20Pump%20Market%20Report%202024.pdf
B15: =B14/6.45 -> 496.12403 | C15: Mio. USD
A16: Australia | B16: 287.2 | C16: Mio. USD | D16: 2023 | F16: https://www.nextmsc.com/news/australia-heat-exchangers-market
A17: Australia | B17: 560.5 | C17: Mio. USD | D17: 2030 | E17: 0.094 | F17: https://www.nextmsc.com/news/australia-heat-exchangers-market
A18: global | B18: 17610 | C18: Mio. USD | D18: 2022 | F18: https://www.fortunebusinessinsights.com/industry-reports/heat-exchangers-market-100919#
A19: global | B19: =35.34*10^3 -> 35340 | C19: Mio. USD | D19: 2032 | E19: 0.0826 | F19: https://www.fortunebusinessinsights.com/industry-reports/heat-exchangers-market-100919#
A20: global | B20: 255000 | C20: Mio. USD | D20: 2030 | E20: 0.053 | F20: https://www.strategicmarketresearch.com/market-report/heat-exchangers-market#:~:text=The%20global%20heat%20exchanger%20market,to%20%2425.5%20billion%20by%202030.
A21: South korea | B21: 66.1 | C21: Mio USD | D21: 2023 | F21: https://www.grandviewresearch.com/horizon/outlook/plate-frame-heat-exchangers-market/south-korea
A22: South Korea | B22: 101.7 | C22: Mio USD | D22: 2030 | E22: 0.063 | F22: https://www.grandviewresearch.com/horizon/outlook/plate-frame-heat-exchangers-market/south-korea
A23: Japan | B23: 826.5 | C23: Mio USD | D23: 2023 | F23: https://www.nextmsc.com/report/japan-heat-exchangers-market
A24: Japan | B24: 1451.5 | C24: Mio USD | D24: 2030 | E24: 0.078 | F24: https://www.nextmsc.com/report/japan-heat-exchangers-market
A25: Brazil | B25: 158.1 | C25: Mio USD | D25: 2022 | F25: https://www.grandviewresearch.com/horizon/outlook/shell-and-tube-heat-exchanger-market/brazil
A26: Brazil | B26: 226.7 | C26: Mio USD | D26: 2030 | E26: 0.046 | F26: https://www.grandviewresearch.com/horizon/outlook/shell-and-tube-heat-exchanger-market/brazil
A27: USA | B27: 2700 | D27: 2022 | F27: https://www.grandviewresearch.com/industry-analysis/us-heat-exchangers-market-report
A28: USA | D28: 2030 | E28: 0.044 | F28: https://www.grandviewresearch.com/industry-analysis/us-heat-exchangers-market-report
A30: facror application HVAC to all applications
A31: Europe | B31: =B4/B2 -> 0.17857143
A32: China | B32: =B15/B12 -> 0.11694143
A33: Assumption | B33: 1 | C33: > based ont he sahre of e.g shell and tube -> sufficient if i found a source
C34: Market Value Current | D34: Per HX in HP | E34: In units production capacity per 8 kW HP (see cost sheet) | F34: Unit | G34: CAGR (2024 - 2032)
A35: AUS | B35: 2022 | C35: =B16*B33*0.84 -> 241.248 | D35: Mio. € | E35: =C35/'cost estimate'!$B$7*10^6 -> 335164.69 | F35: units HEX wit assumption 1 HX per 1 HP | G35: 0.094
A36: AUT | B36: 2022 | C36: 36 | D36: Mio. € | E36: =C36/'cost estimate'!$B$7*10^6 -> 50014.628 | F36: units HEX wit assumption 1 HX per 1 HP | G36: 0.189
A37: BRA | B37: 2022 | C37: =B25*0.84*B33 -> 132.804 | D37: Mio. € | E37: =C37/'cost estimate'!$B$7*10^6 -> 184503.96 | F37: units HEX wit assumption 1 HX per 1 HP | G37: 0.046
A38: CHN | B38: 2022 | C38: =B12*0.84 -> 3563.7 | D38: Mio. € | E38: =C38/'cost estimate'!$B$7*10^6 -> 4951031.3 | F38: units HEX wit assumption 1 HX per 1 HP | G38: 0.07
A39: CZE | B39: 2022 | C39: 27 | D39: Mio. € | E39: =C39/'cost estimate'!$B$7*10^6 -> 37510.971 | F39: units HEX wit assumption 1 HX per 1 HP | G39: 0.189
A40: DEU | B40: 2022 | C40: 180 | D40: Mio. € | E40: =C40/'cost estimate'!$B$7*10^6 -> 250073.14 | F40: units HEX wit assumption 1 HX per 1 HP | G40: 0.189
A41: ITA | B41: 2022 | C41: 234 | D41: Mio. € | E41: =C41/'cost estimate'!$B$7*10^6 -> 325095.08 | F41: units HEX wit assumption 1 HX per 1 HP | G41: 0.189
A42: JPN | B42: 2022 | C42: =B23*0.84*B33 -> 694.26 | D42: Mio. € | E42: =C42/'cost estimate'!$B$7*10^6 -> 964532.09 | F42: units HEX wit assumption 1 HX per 1 HP | G42: 0.065
A43: KOR | B43: 2022 | C43: =66.1*0.84 -> 55.524 | D43: Mio. € | E43: =C43/'cost estimate'!$B$7*10^6 -> 77139.227 | F43: units HEX wit assumption 1 HX per 1 HP | G43: 0.063
A44: ROE | B44: 2022 | C44: =B4-SUM(C40,C41,C39,C36) -> 423 | D44: Mio. € | E44: =C44/'cost estimate'!$B$7*10^6 -> 587671.88 | F44: units HEX wit assumption 1 HX per 1 HP | G44: 0.189
A45: ROW | B45: 2022 | C45: =B18*B33*0.84 - SUM(C38:C44,C46,C35:C37) -> 6936.864 | D45: Mio. € | E45: =C45/'cost estimate'!$B$7*10^6 -> 9637351.9 | F45: units HEX wit assumption 1 HX per 1 HP | G45: 0.0826
A46: USA | B46: 2022 | C46: =B27*B33*0.84 -> 2268 | D46: Mio. € | E46: =C46/'cost estimate'!$B$7*10^6 -> 3150921.5 | F46: units HEX wit assumption 1 HX per 1 HP | G46: 0.04
E47: =SUM(E35:E46) -> 20551011
A48: valdiate market shares with: https://oec.world/en/profile/hs/heat-exchange-units-non-domestic-non-electric
A49: makes sense,ITALY AND germany are big exporters
A51: Conversion factor
A52: =1/32.3 -> 0.030959752
A53: CAGR | B53: 0.094 | C53: 0.189 | D53: 0.046 | E53: 0.065 | F53: 0.189 | G53: 0.189 | H53: 0.189 | I53: 0.065 | J53: 0.065 | K53: 0.189 | L53: 0.0826 | M53: 0.04
B54: AUS | C54: AUT | D54: BRA | E54: CHN | F54: CZE | G54: DEU | H54: ITA | I54: JPN | J54: KOR | K54: ROE | L54: ROW | M54: USA | N54: Unit
A55: 2022 | B55: =C35/'cost estimate'!D7 -> 2.6813175 | C55: =C36/'cost estimate'!D7 -> 0.40011702 | D55: =C37/'cost estimate'!D7 -> 1.4760317 | E55: =C38/'cost estimate'!D7 -> 39.608251 | F55: =C39/'cost estimate'!D7 -> 0.30008777 | G55: =C40/'cost estimate'!D7 -> 2.0005851 | H55: =C41/'cost estimate'!D7 -> 2.6007606 | I55: =C42/'cost estimate'!D7 -> 7.7162568 | J55: =C43/'cost estimate'!D7 -> 0.61711382 | K55: =C44/'cost estimate'!D7 -> 4.701375 | L55: =C45/'cost estimate'!D7 -> 77.098816 | M55: =C46/'cost estimate'!D7 -> 25.207372 | N55: GW
A56: 2023 | B56: =B$55*(1+B$53)^($A56-$A$55) -> 2.9333614 | C56: =C$55*(1+C$53)^($A56-$A$55) -> 0.47573914 | D56: =D$55*(1+D$53)^($A56-$A$55) -> 1.5439291 | E56: =E$55*(1+E$53)^($A56-$A$55) -> 42.182787 | F56: =F$55*(1+F$53)^($A56-$A$55) -> 0.35680435 | G56: =G$55*(1+G$53)^($A56-$A$55) -> 2.3786957 | H56: =H$55*(1+H$53)^($A56-$A$55) -> 3.0923044 | I56: =I$55*(1+I$53)^($A56-$A$55) -> 8.2178134 | ... M56: =M$55*(1+M$53)^($A56-$A$55) -> 26.215667 | N56: GW
A57: 2024 | B57: =B$55*(1+B$53)^($A57-$A$55) -> 3.2090973 | C57: =C$55*(1+C$53)^($A57-$A$55) -> 0.56565384 | D57: =D$55*(1+D$53)^($A57-$A$55) -> 1.6149499 | E57: =E$55*(1+E$53)^($A57-$A$55) -> 44.924668 | F57: =F$55*(1+F$53)^($A57-$A$55) -> 0.42424038 | G57: =G$55*(1+G$53)^($A57-$A$55) -> 2.8282692 | H57: =H$55*(1+H$53)^($A57-$A$55) -> 3.6767499 | I57: =I$55*(1+I$53)^($A57-$A$55) -> 8.7519713 | ... M57: =M$55*(1+M$53)^($A57-$A$55) -> 27.264294 | N57: GW
A58: 2025 | B58: =B$55*(1+B$53)^($A58-$A$55) -> 3.5107525 | C58: =C$55*(1+C$53)^($A58-$A$55) -> 0.67256241 | D58: =D$55*(1+D$53)^($A58-$A$55) -> 1.6892376 | E58: =E$55*(1+E$53)^($A58-$A$55) -> 47.844772 | F58: =F$55*(1+F$53)^($A58-$A$55) -> 0.50442181 | G58: =G$55*(1+G$53)^($A58-$A$55) -> 3.3628121 | H58: =H$55*(1+H$53)^($A58-$A$55) -> 4.3716557 | I58: =I$55*(1+I$53)^($A58-$A$55) -> 9.3208495 | ... M58: =M$55*(1+M$53)^($A58-$A$55) -> 28.354866 | N58: GW
A59: 2026 | B59: =B$55*(1+B$53)^($A59-$A$55) -> 3.8407632 | C59: =C$55*(1+C$53)^($A59-$A$55) -> 0.79967671 | D59: =D$55*(1+D$53)^($A59-$A$55) -> 1.7669425 | E59: =E$55*(1+E$53)^($A59-$A$55) -> 50.954682 | F59: =F$55*(1+F$53)^($A59-$A$55) -> 0.59975753 | G59: =G$55*(1+G$53)^($A59-$A$55) -> 3.9983835 | H59: =H$55*(1+H$53)^($A59-$A$55) -> 5.1978986 | I59: =I$55*(1+I$53)^($A59-$A$55) -> 9.9267047 | ... M59: =M$55*(1+M$53)^($A59-$A$55) -> 29.48906 | N59: GW
A60: 2027 | B60: =B$55*(1+B$53)^($A60-$A$55) -> 4.201795 | C60: =C$55*(1+C$53)^($A60-$A$55) -> 0.9508156 | D60: =D$55*(1+D$53)^($A60-$A$55) -> 1.8482219 | E60: =E$55*(1+E$53)^($A60-$A$55) -> 54.266736 | F60: =F$55*(1+F$53)^($A60-$A$55) -> 0.7131117 | G60: =G$55*(1+G$53)^($A60-$A$55) -> 4.754078 | H60: =H$55*(1+H$53)^($A60-$A$55) -> 6.1803014 | I60: =I$55*(1+I$53)^($A60-$A$55) -> 10.57194 | ... M60: =M$55*(1+M$53)^($A60-$A$55) -> 30.668623 | N60: GW
A61: 2028 | B61: =B$55*(1+B$53)^($A61-$A$55) -> 4.5967637 | C61: =C$55*(1+C$53)^($A61-$A$55) -> 1.1305198 | D61: =D$55*(1+D$53)^($A61-$A$55) -> 1.9332401 | E61: =E$55*(1+E$53)^($A61-$A$55) -> 57.794074 | F61: =F$55*(1+F$53)^($A61-$A$55) -> 0.84788981 | G61: =G$55*(1+G$53)^($A61-$A$55) -> 5.6525988 | H61: =H$55*(1+H$53)^($A61-$A$55) -> 7.3483784 | I61: =I$55*(1+I$53)^($A61-$A$55) -> 11.259117 | ... M61: =M$55*(1+M$53)^($A61-$A$55) -> 31.895368 | N61: GW
A62: 2029 | B62: =B$55*(1+B$53)^($A62-$A$55) -> 5.0288595 | C62: =C$55*(1+C$53)^($A62-$A$55) -> 1.344188 | D62: =D$55*(1+D$53)^($A62-$A$55) -> 2.0221691 | E62: =E$55*(1+E$53)^($A62-$A$55) -> 61.550689 | F62: =F$55*(1+F$53)^($A62-$A$55) -> 1.008141 | G62: =G$55*(1+G$53)^($A62-$A$55) -> 6.7209399 | H62: =H$55*(1+H$53)^($A62-$A$55) -> 8.7372219 | I62: =I$55*(1+I$53)^($A62-$A$55) -> 11.990959 | ... M62: =M$55*(1+M$53)^($A62-$A$55) -> 33.171182 | N62: GW
A63: 2030 | B63: =B$55*(1+B$53)^($A63-$A$55) -> 5.5015723 | C63: =C$55*(1+C$53)^($A63-$A$55) -> 1.5982395 | D63: =D$55*(1+D$53)^($A63-$A$55) -> 2.1151889 | E63: =E$55*(1+E$53)^($A63-$A$55) -> 65.551484 | F63: =F$55*(1+F$53)^($A63-$A$55) -> 1.1986796 | G63: =G$55*(1+G$53)^($A63-$A$55) -> 7.9911976 | H63: =H$55*(1+H$53)^($A63-$A$55) -> 10.388557 | I63: =I$55*(1+I$53)^($A63-$A$55) -> 12.770372 | ... M63: =M$55*(1+M$53)^($A63-$A$55) -> 34.49803 | N63: GW
A64: 2031 | B64: =B$55*(1+B$53)^($A64-$A$55) -> 6.0187201 | C64: =C$55*(1+C$53)^($A64-$A$55) -> 1.9003068 | D64: =D$55*(1+D$53)^($A64-$A$55) -> 2.2124876 | E64: =E$55*(1+E$53)^($A64-$A$55) -> 69.81233 | F64: =F$55*(1+F$53)^($A64-$A$55) -> 1.4252301 | G64: =G$55*(1+G$53)^($A64-$A$55) -> 9.5015339 | H64: =H$55*(1+H$53)^($A64-$A$55) -> 12.351994 | I64: =I$55*(1+I$53)^($A64-$A$55) -> 13.600446 | ... M64: =M$55*(1+M$53)^($A64-$A$55) -> 35.877951 | N64: GW
A65: 2032 | B65: =B$55*(1+B$53)^($A65-$A$55) -> 6.5844798 | C65: =C$55*(1+C$53)^($A65-$A$55) -> 2.2594648 | D65: =D$55*(1+D$53)^($A65-$A$55) -> 2.314262 | E65: =E$55*(1+E$53)^($A65-$A$55) -> 74.350132 | F65: =F$55*(1+F$53)^($A65-$A$55) -> 1.6945986 | G65: =G$55*(1+G$53)^($A65-$A$55) -> 11.297324 | H65: =H$55*(1+H$53)^($A65-$A$55) -> 14.686521 | I65: =I$55*(1+I$53)^($A65-$A$55) -> 14.484475 | ... M65: =M$55*(1+M$53)^($A65-$A$55) -> 37.313069 | N65: GW
A66: 2033 | B66: =B$55*(1+B$53)^($A66-$A$55) -> 7.2034209 | C66: =C$55*(1+C$53)^($A66-$A$55) -> 2.6865036 | D66: =D$55*(1+D$53)^($A66-$A$55) -> 2.4207181 | E66: =E$55*(1+E$53)^($A66-$A$55) -> 79.18289 | F66: =F$55*(1+F$53)^($A66-$A$55) -> 2.0148777 | G66: =G$55*(1+G$53)^($A66-$A$55) -> 13.432518 | H66: =H$55*(1+H$53)^($A66-$A$55) -> 17.462273 | I66: =I$55*(1+I$53)^($A66-$A$55) -> 15.425965 | ... M66: =M$55*(1+M$53)^($A66-$A$55) -> 38.805592 | N66: GW
A67: 2034 | B67: =B$55*(1+B$53)^($A67-$A$55) -> 7.8805424 | C67: =C$55*(1+C$53)^($A67-$A$55) -> 3.1942528 | D67: =D$55*(1+D$53)^($A67-$A$55) -> 2.5320711 | E67: =E$55*(1+E$53)^($A67-$A$55) -> 84.329778 | F67: =F$55*(1+F$53)^($A67-$A$55) -> 2.3956896 | G67: =G$55*(1+G$53)^($A67-$A$55) -> 15.971264 | H67: =H$55*(1+H$53)^($A67-$A$55) -> 20.762643 | I67: =I$55*(1+I$53)^($A67-$A$55) -> 16.428653 | ... M67: =M$55*(1+M$53)^($A67-$A$55) -> 40.357815 | N67: GW
A68: 2035 | B68: =B$55*(1+B$53)^($A68-$A$55) -> 8.6213134 | C68: =C$55*(1+C$53)^($A68-$A$55) -> 3.7979666 | D68: =D$55*(1+D$53)^($A68-$A$55) -> 2.6485464 | E68: =E$55*(1+E$53)^($A68-$A$55) -> 89.811213 | F68: =F$55*(1+F$53)^($A68-$A$55) -> 2.8484749 | G68: =G$55*(1+G$53)^($A68-$A$55) -> 18.989833 | H68: =H$55*(1+H$53)^($A68-$A$55) -> 24.686783 | I68: =I$55*(1+I$53)^($A68-$A$55) -> 17.496516 | ... M68: =M$55*(1+M$53)^($A68-$A$55) -> 41.972128 | N68: GW
A70: Learning rate | B70: 0.1
A72: 2022 | B72: 30.158022 | C72: 46.425194 | D72: 26.967439 | E72: 15.208399 | F72: 41.760035 | G72: 47.014205 | H72: 45.284391 | I72: 42.714823 | J72: 28.551641 | K72: 41.792562 | L72: 29.027382 | M72: 52.126155
A73: 2023 | B73: =B$72*(1-$B$70)^LOG(B56/B$55,2) -> 29.748981 | C73: =C$72*(1-$B$70)^LOG(C56/C$55,2) -> 45.219511 | D73: =D$72*(1-$B$70)^LOG(D56/D$55,2) -> 26.783716 | E73: =E$72*(1-$B$70)^LOG(E56/E$55,2) -> 15.063513 | F73: =F$72*(1-$B$70)^LOG(F56/F$55,2) -> 40.675508 | G73: =G$72*(1-$B$70)^LOG(G56/G$55,2) -> 45.793224 | H73: =H$72*(1-$B$70)^LOG(H56/H$55,2) -> 44.108334 | I73: =I$72*(1-$B$70)^LOG(I56/I$55,2) -> 42.307892 | ... M73: =M$72*(1-$B$70)^LOG(M56/M$55,2) -> 51.816321
A74: 2024 | B74: =B$73*(1-$B$70)^LOG(B57/B$55,2) -> 28.947469 | C74: =C$73*(1-$B$70)^LOG(C57/C$55,2) -> 42.901266 | D74: =D$73*(1-$B$70)^LOG(D57/D$55,2) -> 26.420016 | E74: =E$73*(1-$B$70)^LOG(E57/E$55,2) -> 14.777869 | F74: =F$73*(1-$B$70)^LOG(F57/F$55,2) -> 38.590218 | G74: =G$73*(1-$B$70)^LOG(G57/G$55,2) -> 43.445568 | H74: =H$73*(1-$B$70)^LOG(H57/H$55,2) -> 41.847056 | I74: =I$73*(1-$B$70)^LOG(I57/I$55,2) -> 41.505623 | ... M74: =M$73*(1-$B$70)^LOG(M57/M$55,2) -> 51.202166 | P74: 30.158022
A75: 2025 | B75: =B$73*(1-$B$70)^LOG(B58/B$55,2) -> 28.554847 | C75: =C$73*(1-$B$70)^LOG(C58/C$55,2) -> 41.7871 | D75: =D$73*(1-$B$70)^LOG(D58/D$55,2) -> 26.240022 | E75: =E$73*(1-$B$70)^LOG(E58/E$55,2) -> 14.637085 | F75: =F$73*(1-$B$70)^LOG(F58/F$55,2) -> 37.588012 | G75: =G$73*(1-$B$70)^LOG(G58/G$55,2) -> 42.317266 | H75: =H$73*(1-$B$70)^LOG(H58/H$55,2) -> 40.760268 | I75: =I$73*(1-$B$70)^LOG(I58/I$55,2) -> 41.110211 | ... M75: =M$73*(1-$B$70)^LOG(M58/M$55,2) -> 50.897824 | P75: 46.425194
A76: 2026 | B76: =B$73*(1-$B$70)^LOG(B59/B$55,2) -> 28.167551 | C76: =C$73*(1-$B$70)^LOG(C59/C$55,2) -> 40.70187 | D76: =D$73*(1-$B$70)^LOG(D59/D$55,2) -> 26.061255 | E76: =E$73*(1-$B$70)^LOG(E59/E$55,2) -> 14.497642 | F76: =F$73*(1-$B$70)^LOG(F59/F$55,2) -> 36.611834 | G76: =G$73*(1-$B$70)^LOG(G59/G$55,2) -> 41.218267 | H76: =H$73*(1-$B$70)^LOG(H59/H$55,2) -> 39.701705 | I76: =I$73*(1-$B$70)^LOG(I59/I$55,2) -> 40.718567 | ... M76: =M$73*(1-$B$70)^LOG(M59/M$55,2) -> 50.59529 | P76: 26.967439
A77: 2027 | B77: =B$73*(1-$B$70)^LOG(B60/B$55,2) -> 27.785507 | C77: =C$73*(1-$B$70)^LOG(C60/C$55,2) -> 39.644823 | D77: =D$73*(1-$B$70)^LOG(D60/D$55,2) -> 25.883705 | E77: =E$73*(1-$B$70)^LOG(E60/E$55,2) -> 14.359527 | F77: =F$73*(1-$B$70)^LOG(F60/F$55,2) -> 35.661008 | G77: =G$73*(1-$B$70)^LOG(G60/G$55,2) -> 40.147809 | H77: =H$73*(1-$B$70)^LOG(H60/H$55,2) -> 38.670633 | I77: =I$73*(1-$B$70)^LOG(I60/I$55,2) -> 40.330654 | ... M77: =M$73*(1-$B$70)^LOG(M60/M$55,2) -> 50.294555 | P77: 15.208399
A78: 2028 | B78: =B$73*(1-$B$70)^LOG(B61/B$55,2) -> 27.408646 | C78: =C$73*(1-$B$70)^LOG(C61/C$55,2) -> 38.615229 | D78: =D$73*(1-$B$70)^LOG(D61/D$55,2) -> 25.707365 | E78: =E$73*(1-$B$70)^LOG(E61/E$55,2) -> 14.222728 | F78: =F$73*(1-$B$70)^LOG(F61/F$55,2) -> 34.734875 | G78: =G$73*(1-$B$70)^LOG(G61/G$55,2) -> 39.105152 | H78: =H$73*(1-$B$70)^LOG(H61/H$55,2) -> 37.666339 | I78: =I$73*(1-$B$70)^LOG(I61/I$55,2) -> 39.946436 | ... M78: =M$73*(1-$B$70)^LOG(M61/M$55,2) -> 49.995608 | P78: 41.760035
A79: 2029 | B79: =B$73*(1-$B$70)^LOG(B62/B$55,2) -> 27.036896 | C79: =C$73*(1-$B$70)^LOG(C62/C$55,2) -> 37.612373 | D79: =D$73*(1-$B$70)^LOG(D62/D$55,2) -> 25.532227 | E79: =E$73*(1-$B$70)^LOG(E62/E$55,2) -> 14.087233 | F79: =F$73*(1-$B$70)^LOG(F62/F$55,2) -> 33.832794 | G79: =G$73*(1-$B$70)^LOG(G62/G$55,2) -> 38.089573 | H79: =H$73*(1-$B$70)^LOG(H62/H$55,2) -> 36.688126 | I79: =I$73*(1-$B$70)^LOG(I62/I$55,2) -> 39.565878 | ... M79: =M$73*(1-$B$70)^LOG(M62/M$55,2) -> 49.698437 | P79: 47.014205
A80: 2030 | B80: =B$73*(1-$B$70)^LOG(B63/B$55,2) -> 26.670188 | C80: =C$73*(1-$B$70)^LOG(C63/C$55,2) -> 36.635562 | D80: =D$73*(1-$B$70)^LOG(D63/D$55,2) -> 25.358281 | E80: =E$73*(1-$B$70)^LOG(E63/E$55,2) -> 13.953028 | F80: =F$73*(1-$B$70)^LOG(F63/F$55,2) -> 32.95414 | G80: =G$73*(1-$B$70)^LOG(G63/G$55,2) -> 37.100369 | H80: =H$73*(1-$B$70)^LOG(H63/H$55,2) -> 35.735319 | I80: =I$73*(1-$B$70)^LOG(I63/I$55,2) -> 39.188946 | ... M80: =M$73*(1-$B$70)^LOG(M63/M$55,2) -> 49.403033 | P80: 45.284391
A81: 2031 | B81: =B$73*(1-$B$70)^LOG(B64/B$55,2) -> 26.308453 | C81: =C$73*(1-$B$70)^LOG(C64/C$55,2) -> 35.68412 | D81: =D$73*(1-$B$70)^LOG(D64/D$55,2) -> 25.185521 | E81: =E$73*(1-$B$70)^LOG(E64/E$55,2) -> 13.820102 | F81: =F$73*(1-$B$70)^LOG(F64/F$55,2) -> 32.098306 | G81: =G$73*(1-$B$70)^LOG(G64/G$55,2) -> 36.136855 | H81: =H$73*(1-$B$70)^LOG(H64/H$55,2) -> 34.807256 | I81: =I$73*(1-$B$70)^LOG(I64/I$55,2) -> 38.815605 | ... M81: =M$73*(1-$B$70)^LOG(M64/M$55,2) -> 49.109385 | P81: 42.714823
A82: 2032 | B82: =B$73*(1-$B$70)^LOG(B65/B$55,2) -> 25.951625 | C82: =C$73*(1-$B$70)^LOG(C65/C$55,2) -> 34.757386 | D82: =D$73*(1-$B$70)^LOG(D65/D$55,2) -> 25.013938 | E82: =E$73*(1-$B$70)^LOG(E65/E$55,2) -> 13.688442 | F82: =F$73*(1-$B$70)^LOG(F65/F$55,2) -> 31.264698 | G82: =G$73*(1-$B$70)^LOG(G65/G$55,2) -> 35.198364 | H82: =H$73*(1-$B$70)^LOG(H65/H$55,2) -> 33.903295 | I82: =I$73*(1-$B$70)^LOG(I65/I$55,2) -> 38.445821 | ... M82: =M$73*(1-$B$70)^LOG(M65/M$55,2) -> 48.817482 | P82: 28.551641
A83: 2033 | B83: =B$73*(1-$B$70)^LOG(B66/B$55,2) -> 25.599637 | C83: =C$73*(1-$B$70)^LOG(C66/C$55,2) -> 33.854721 | D83: =D$73*(1-$B$70)^LOG(D66/D$55,2) -> 24.843523 | E83: =E$73*(1-$B$70)^LOG(E66/E$55,2) -> 13.558036 | F83: =F$73*(1-$B$70)^LOG(F66/F$55,2) -> 30.452739 | G83: =G$73*(1-$B$70)^LOG(G66/G$55,2) -> 34.284246 | H83: =H$73*(1-$B$70)^LOG(H66/H$55,2) -> 33.022811 | I83: =I$73*(1-$B$70)^LOG(I66/I$55,2) -> 38.079559 | ... M83: =M$73*(1-$B$70)^LOG(M66/M$55,2) -> 48.527314 | P83: 41.792562
A84: 2034 | B84: =B$73*(1-$B$70)^LOG(B67/B$55,2) -> 25.252423 | C84: =C$73*(1-$B$70)^LOG(C67/C$55,2) -> 32.975498 | D84: =D$73*(1-$B$70)^LOG(D67/D$55,2) -> 24.67427 | E84: =E$73*(1-$B$70)^LOG(E67/E$55,2) -> 13.428873 | F84: =F$73*(1-$B$70)^LOG(F67/F$55,2) -> 29.661868 | G84: =G$73*(1-$B$70)^LOG(G67/G$55,2) -> 33.393868 | H84: =H$73*(1-$B$70)^LOG(H67/H$55,2) -> 32.165193 | I84: =I$73*(1-$B$70)^LOG(I67/I$55,2) -> 37.716787 | ... M84: =M$73*(1-$B$70)^LOG(M67/M$55,2) -> 48.238871 | P84: 29.027382
A85: 2035 | B85: =B$73*(1-$B$70)^LOG(B68/B$55,2) -> 24.909918 | C85: =C$73*(1-$B$70)^LOG(C68/C$55,2) -> 32.119109 | D85: =D$73*(1-$B$70)^LOG(D68/D$55,2) -> 24.50617 | E85: =E$73*(1-$B$70)^LOG(E68/E$55,2) -> 13.30094 | F85: =F$73*(1-$B$70)^LOG(F68/F$55,2) -> 28.891535 | G85: =G$73*(1-$B$70)^LOG(G68/G$55,2) -> 32.526614 | H85: =H$73*(1-$B$70)^LOG(H68/H$55,2) -> 31.329848 | I85: =I$73*(1-$B$70)^LOG(I68/I$55,2) -> 37.35747 | ... M85: =M$73*(1-$B$70)^LOG(M68/M$55,2) -> 47.952142 | P85: 52.126155

Sheet heat pump production
A1: Conversion | B1: (shamoushaki 2023) | G1: lifetime of heap tpumo around 18 yrr | H1: Source: energy perspective outllok
A2: Table S1. Inventory data for all phases of air-source heat pump
A3: Manufacturing
A4: Component | B4: Material | C4: Weight | E4: Unit | I4: Ref | K4: Explanation
A5: Evaporator and condenser | B5: Low-alloyed steel | C5: 32 | E5: kg | I5: Greening, Benjamin, and Adisa Azapagic. "Domestic heat pumps: Life cycle environmental impacts and potential implications for the UK." Energy 39, no. 1 (2012): 205-217.
A6: Housing and compressor | B6: Reinforcing steel | C6: 120 | E6: kg | I6: Sevindik, Selman, Catalina Spataru, Teresa Domenech Aparisi, and Raimund Bleischwitz. "A comparative environmental assessment of heat pumps and gas boilers towards a circular economy in the UK." Energies 14, no. 11 (2021): 3027.
A7: Wiring, piping and expansion valve | B7: Copper | C7: 35.2 | E7: kg | I7: " | K7: UK data
A8: Pipework insulation | B8: Elastomere | C8: 16 | E8: kg | I8: " | K8: Data for a 10 kW ASHP ?
A9: Wiring insulation | B9: Polyvinylchloride | C9: 1.6 | E9: kg | I9: "
A10: Lubricating oil | B10: Polyolester oil | C10: 2.7 | E10: kg | I10: "
A11: Air fan | B11: Copper | C11: 1.4 | E11: kg | I11: "
A12: " | B12: HDPE | C12: 0.5 | E12: kg | I12: "
A13: Refrigerant | B13: R-134a | C13: 4.9 | E13: kg | I13: "
A14: " | B14: Losses | C14: 3% (manufacture) & 6% (operation, annually)
A15: Energy | B15: Medium-voltage electricity | C15: 504 | E15: MJ | I15: Naumann, Gabriel, Elke Schropp, and Matthias Gaderer. "Life Cycle Assessment of an Air-Source Heat Pump and a Condensing Gas Boiler Using an Attributional and a Consequential Approach." Procedia CIRP 105 (2022): 351-356. | K15: Data for a 5 kW ASHP ?
A16: " | B16: Heat | C16: 1400 | E16: MJ | I16: Naumann, Gabriel, Elke Schropp, and Matthias Gaderer. "Life Cycle Assessment of an Air-Source Heat Pump and a Condensing Gas Boiler Using an Attributional and a Consequential Approach." Procedia CIRP 105 (2022): 351-356.
A17: Assembly & Installation
A18: Process | B18: Energy | C18: Weight | E18: Unit | I18: Ref
A19: Assembly | B19: Medium-voltage electricity (European mix) | C19: 504 | E19: MJ | I19: Greening, Benjamin, and Adisa Azapagic. "Domestic heat pumps: Life cycle environmental impacts and potential implications for the UK." Energy 39, no. 1 (2012): 205-217.
A20: " | B20: Natural gas | C20: 1400 | E20: MJ | I20: Sevindik, Selman, Catalina Spataru, Teresa Domenech Aparisi, and Raimund Bleischwitz. "A comparative environmental assessment of heat pumps and gas boilers towards a circular economy in the UK." Energies 14, no. 11 (2021): 3027. | K20: Explanation
A21: O & M
A22: Process/Item | B22: Weight | C22: Unit | E22: Ref
A23: UK electricity | B23: 0.357 | C23: kWh/kWh heat generated | E23: Greening, Benjamin, and Adisa Azapagic. "Domestic heat pumps: Life cycle environmental impacts and potential implications for the UK." Energy 39, no. 1 (2012): 205-217.
A24: Refrigerant | B24: 0.294 | C24: kg (annually) | E24: Sevindik, Selman, Catalina Spataru, Teresa Domenech Aparisi, and Raimund Bleischwitz. "A comparative environmental assessment of heat pumps and gas boilers towards a circular economy in the UK." Energies 14, no. 11 (2021): 3027.
A25: Air‐source heat pumps for residential applications contain around 15 to 20 kilogrammes of copper, predominantly in their pipes and valves, making up roughly 10% of the overall cost of the devic
A26: souzrce (the future of heat pumps, 2022
A28: Production installment duration | B28: 1-3 y | C28: y | E28: Source: https://www.iea.org/energy-system/buildings/heat-pumps#tracking | L28: Planned Investment
A30: Country | B30: Capacity installed | C30: unit | E30: year | G30: source | H30: if estimated on a 8kw HP | J30: Notes | K30: Capacity estimated 2030 | L30: unit | M30: Source | N30: CAPEX for heat pump facilites
A31: China | B31: 50 | C31: GW | E31: 2024 | G31: IEA, https://www.iea.org/data-and-statistics/charts/heat-pump-manufacturing-capacity-per-region-2022 | H31: =B31*10^6/8 -> 6250000 | I31: units HP | J31: 20 for Air-Air GW and 30 air to water (IEA; china heat pumps) | K31: =B31*1.2 -> 60 | L31: GW | N31: =60*0.84 -> 50.4 | O31: €/kW | P31: IEA clean technology outlook 2023
A32: US | B32: 34 | C32: GW | E32: 2024 | G32: IEA, https://www.iea.org/data-and-statistics/charts/heat-pump-manufacturing-capacity-per-region-2023 | H32: =B32*10^6/8 -> 4250000 | K32: =B32*1.2 -> 40.8 | L32: GW | N32: =175*0.84 -> 147 | O32: €/kW | P32: IEA clean technology outlook 2024
A33: Europe | B33: 25 | C33: GW | E33: 2024 | G33: IEA, https://www.iea.org/data-and-statistics/charts/heat-pump-manufacturing-capacity-per-region-2024 | H33: =B33*10^6/8 -> 3125000 | K33: =B33*1.2 -> 30 | L33: GW | N33: =170*0.84 -> 142.8 | O33: €/kW | P33: IEA clean technology outlook 2025
A34: Japan and Korea | B34: 16 | C34: GW | E34: 2024 | G34: IEA, https://www.iea.org/data-and-statistics/charts/heat-pump-manufacturing-capacity-per-region-2025 | H34: =B34*10^6/8 -> 2000000 | K34: =B34*1.2 -> 19.2 | L34: GW
A35: Japan | B35: =B34*Demand!I38/SUM(Demand!I38:J38) -> 9.1382105 | C35: GW | G35: allocation based on demand data as a rough estimate | H35: =B35*10^6/8 -> 1142276.3
A36: Korea | B36: =B34-B35 -> 6.8617895 | C36: GW | G36: allocation based on demand data as a rough estimate | H36: =B36*10^6/8 -> 857723.69
A37: ROW | B37: 14 | C37: GW | E37: 2024 | G37: IEA, https://www.iea.org/data-and-statistics/charts/heat-pump-manufacturing-capacity-per-region-2026 | H37: =B37*10^6/8 -> 1750000 | K37: =B37*1.2 -> 16.8 | L37: GW
A38: ROW w/o Australia | B38: =14-B45 -> 14 | H38: =H37-H45 -> 1486000
A39: Brazil | B39: 0 | C39: GW | E39: 2024 | G39: IEA Energy Technology Perspectives 2023, page 453 (annex) | H39: =B39*10^6/8 -> 0 | K39: =B39*1.2 -> 0 | L39: GW
A40: Germany | B40: =0.17*B33 -> 4.25 | C40: GW | H40: =B40*10^6/8 -> 531250
A41: Austria | B41: =0.06*B33 -> 1.5 | C41: GW | H41: =B41*10^6/8 -> 187500
A42: Italy | B42: =0.16*B33 -> 4 | C42: GW | H42: =B42*10^6/8 -> 500000
A43: Czech Republic | B43: =B33*0.05 -> 1.25 | C43: GW | H43: =B43*10^6/8 -> 156250
A44: Rest of Europe | B44: =B33-SUM(B40:B43) -> 14 | C44: GW | H44: =B44*10^6/8 -> 1750000
A45: Australia | H45: =Demand!B38*0.2 -> 264000 | I45: estimation, Australia covers less then 20% of demand by domestic production
A47: Country | B47: Cost of Manufacturing | C47: Unit | E47: year | F47: Source | K47: OPEX evolution -> see notes in notion
A48: Europe | B48: 200-250 | C48: €/Kw | E48: 2023 | F48: Advancing clean energy manufacturing, IEA 2023 | K48: https://www.sciencedirect.com/science/article/pii/S0306261924013977
A49: USA | B49: 200-250 | C49: €/Kw | E49: 2023 | F49: Advancing clean energy manufacturing, IEA 2024
A50: China | B50: 100-125 | C50: €/Kw | E50: 2023 | F50: Advancing clean energy manufacturing, IEA 2025
A52: Learning rate of HP per cumulative unit sold | B52: 0.1 | C52: https://reflex-project.eu/wp-content/uploads/2018/12/REFLEX_policy_brief_Experience_curves_12_2018.pdf
A54: Planned Capacity expansion
A55: Country | B55: CAPEX (total) (Mio. €) | C55: additional 1000 units | D55: capacity investment existing in MW | E55: OPEX (Mio. €/ 1000units) | G55: CAPEX( €/kW) | I55: Source | K55: Currently installed production | L55: unit | M55: year | N55: Source | O55: other values | P55: unit | Q55: Source
A56: France | B56: 199.3 | C56: 318 | D56: =C56*'cost estimate'!$B$31 -> 2544 | E56: 0.62 | G56: =E56*'cost estimate'!$B$31/1000*10^6 -> 4960 | I56: Lyons 2023, p. 34 | N56: Lyons 2023, p. 34
A57: Slovakia | B57: 180 | C57: 105 | D57: =C57*'cost estimate'!$B$31 -> 840 | E57: 1.7 | G57: =E57*'cost estimate'!$B$31/1000*10^6 -> 13600 | I57: Lyons 2023, p. 34 | N57: Lyons 2023, p. 35
A58: Italy | B58: 130 | C58: 153 | D58: =C58*'cost estimate'!$B$31 -> 1224 | E58: 0.84 | G58: =E58*'cost estimate'!$B$31/1000*10^6 -> 6720 | I58: Lyons 2023, p. 34 | N58: Lyons 2023, p. 36
A59: Netherlands | B59: 70 | C59: 53 | D59: =C59*'cost estimate'!$B$31 -> 424 | E59: 1.3 | G59: =E59*'cost estimate'!$B$31/1000*10^6 -> 10400 | I59: Lyons 2023, p. 34 | N59: Lyons 2023, p. 37
A60: Spain | B60: 70 | C60: 53 | D60: =C60*'cost estimate'!$B$31 -> 424 | E60: 1.3 | G60: =E60*'cost estimate'!$B$31/1000*10^6 -> 10400 | I60: Lyons 2023, p. 34 | N60: Lyons 2023, p. 38
A61: Poland | B61: 300 | C61: 220 | D61: =C61*'cost estimate'!$B$31 -> 1760 | E61: 1.4 | G61: =E61*'cost estimate'!$B$31/1000*10^6 -> 11200 | I61: Lyons 2023, p. 34 | N61: Lyons 2023, p. 39
A62: Germany | B62: 600 | C62: 240 | D62: =C62*'cost estimate'!$B$31 -> 1920 | E62: 2.5 | G62: =E62*'cost estimate'!$B$31/1000*10^6 -> 20000 | I62: Lyons 2023, p. 34 | K62: 884 | L62: mio. € | M62: 2022 | N62: Lyons 2023, p. 40 | O62: 250 000 | P62: units | Q62: https://www.dashboard-deutschland.de/indicator/tile_1663667563512?origin=dashboard&db=energie&category=energie
A63: Portugal | B63: 12 | C63: 150 | D63: =C63*'cost estimate'!$B$31 -> 1200 | E63: 0.1 | G63: =E63*'cost estimate'!$B$31/1000*10^6 -> 800 | I63: Lyons 2023, p. 34 | L63: mio. € | M63: 2022 | N63: Lyons 2023, p. 41
A64: Czech | B64: 145 | C64: 500 | D64: =C64*'cost estimate'!$B$31 -> 4000 | E64: 0.3 | G64: =E64*'cost estimate'!$B$31/1000*10^6 -> 2400 | I64: Lyons 2023, p. 34 | L64: mio. € | N64: Lyons 2023, p. 42
A65: Sweden | K65: 931 | L65: mio. € | M65: 2022 | N65: Lyons 2023, p. 43
A66: Austria | K66: 178.6 | L66: mio. € | M66: 2022 | N66: https://nachhaltigwirtschaften.at/resources/nw_pdf/events/20240619-energiewende-marktstatistik/schriftenreihe-2024-17i-Waermepumpen.pdf | O66: 26 954 | P66: units | Q66: https://nachhaltigwirtschaften.at/resources/nw_pdf/events/20240619-energiewende-marktstatistik/schriftenreihe-2024-17i-Waermepumpen.pdf
A67: RoE | D67: =SUM(D56:D66)-SUM(D58,D66,D64,D62) -> 7192
A68: China | B68: 45 | C68: 8% capacity growth in 2022 | I68: https://iea.blob.core.windows.net/assets/217e820f-3344-4144-9d2c-cc444e080421/FutureofHeatpumpsinChina.pdf, IEA
A69: Europe | C69: 17% groth rate necessary to meet demand | I69: https://www.ehpa.org/wp-content/uploads/2024/07/EHPA-Competitiveness-of-the-heat-pump-sector-in-Europe-Report.pdf
A70: USA | B70: =169*0.84 -> 141.96 | I70: https://cleantechnica.com/2023/11/17/169-million-to-accelerate-electric-heat-pump-manufacturing-in-usa/
A72: OPEX Cost in Countrx | B72: energy | C72: material | D72: Summe without labor | E72: unit | G72: labour (hourly compensation cost) | I72: Source: energy | J72: source labour | K72: source material
A73: Europe | B73: 6.4 | C73: 29 | D73: =SUM(B73:C73) -> 35.4 | E73: €/kW | G73: 27.6 | H73: USD/h | I73: https://mcusercontent.com/8dbf465d9a5cfe9f310f1464e/files/aefa3988-2475-e868-fb82-c5a0af13dbaa/EU_Hydronic_Heat_Pump_Manufacturing_Market_Assessment_Technical_Report.pdf | J73: https://www.conference-board.org/ilcprogram/index.cfm?id=38269 | K73: https://mcusercontent.com/8dbf465d9a5cfe9f310f1464e/files/aefa3988-2475-e868-fb82-c5a0af13dbaa/EU_Hydronic_Heat_Pump_Manufacturing_Market_Assessment_Technical_Report.pdf
A74: China | B74: 4.6 | C74: 29 | D74: =SUM(B74:C74) -> 33.6 | E74: €/kW | G74: =G75/3 -> 13.3 | H74: USD/h | I74: https://mcusercontent.com/8dbf465d9a5cfe9f310f1464e/files/aefa3988-2475-e868-fb82-c5a0af13dbaa/EU_Hydronic_Heat_Pump_Manufacturing_Market_Assessment_Technical_Report.pdf | J74: https://mcusercontent.com/8dbf465d9a5cfe9f310f1464e/files/aefa3988-2475-e868-fb82-c5a0af13dbaa/EU_Hydronic_Heat_Pump_Manufacturing_Market_Assessment_Technical_Report.pdf | K74: https://mcusercontent.com/8dbf465d9a5cfe9f310f1464e/files/aefa3988-2475-e868-fb82-c5a0af13dbaa/EU_Hydronic_Heat_Pump_Manufacturing_Market_Assessment_Technical_Report.pdf
A75: USA | B75: 2.7 | C75: 29 | D75: =SUM(B75:C75) -> 31.7 | E75: €/kW | G75: 39.9 | H75: USD/h | I75: https://mcusercontent.com/8dbf465d9a5cfe9f310f1464e/files/aefa3988-2475-e868-fb82-c5a0af13dbaa/EU_Hydronic_Heat_Pump_Manufacturing_Market_Assessment_Technical_Report.pdf | J75: https://www.conference-board.org/ilcprogram/index.cfm?id=38269 | K75: https://mcusercontent.com/8dbf465d9a5cfe9f310f1464e/files/aefa3988-2475-e868-fb82-c5a0af13dbaa/EU_Hydronic_Heat_Pump_Manufacturing_Market_Assessment_Technical_Report.pdf
A76: Germany | B76: 6.4 | C76: 29 | D76: =SUM(B76:C76) -> 35.4 | E76: €/kW | G76: 43.18 | H76: USD/h | J76: https://www.conference-board.org/ilcprogram/index.cfm?id=38269 | K76: https://mcusercontent.com/8dbf465d9a5cfe9f310f1464e/files/aefa3988-2475-e868-fb82-c5a0af13dbaa/EU_Hydronic_Heat_Pump_Manufacturing_Market_Assessment_Technical_Report.pdf
A77: Czech republic | B77: 6.4 | C77: 29 | D77: =SUM(B77:C77) -> 35.4 | E77: €/kW | G77: 10.71 | H77: USD/h | J77: https://www.conference-board.org/ilcprogram/index.cfm?id=38269 | K77: https://mcusercontent.com/8dbf465d9a5cfe9f310f1464e/files/aefa3988-2475-e868-fb82-c5a0af13dbaa/EU_Hydronic_Heat_Pump_Manufacturing_Market_Assessment_Technical_Report.pdf
A78: Austria | B78: 6.4 | C78: 29 | D78: =SUM(B78:C78) -> 35.4 | E78: €/kW | G78: 39.54 | H78: USD/h | J78: https://www.conference-board.org/ilcprogram/index.cfm?id=38269 | K78: https://mcusercontent.com/8dbf465d9a5cfe9f310f1464e/files/aefa3988-2475-e868-fb82-c5a0af13dbaa/EU_Hydronic_Heat_Pump_Manufacturing_Market_Assessment_Technical_Report.pdf
A79: Italy | B79: 6.4 | C79: 29 | D79: =SUM(B79:C79) -> 35.4 | E79: €/kW | G79: 32.49 | H79: USD/h | J79: https://www.conference-board.org/ilcprogram/index.cfm?id=38269 | K79: https://mcusercontent.com/8dbf465d9a5cfe9f310f1464e/files/aefa3988-2475-e868-fb82-c5a0af13dbaa/EU_Hydronic_Heat_Pump_Manufacturing_Market_Assessment_Technical_Report.pdf
A80: Austrlia | B80: =AVERAGE($B$73:$B$75) -> 4.5666667 | C80: 29 | D80: =SUM(B80:C80) -> 33.566667 | E80: €/kW | G80: 38.19 | H80: USD/h | J80: https://www.conference-board.org/ilcprogram/index.cfm?id=38269 | K80: https://mcusercontent.com/8dbf465d9a5cfe9f310f1464e/files/aefa3988-2475-e868-fb82-c5a0af13dbaa/EU_Hydronic_Heat_Pump_Manufacturing_Market_Assessment_Technical_Report.pdf
A81: South Korea | B81: =AVERAGE($B$73:$B$75) -> 4.5666667 | C81: 29 | D81: =SUM(B81:C81) -> 33.566667 | E81: €/kW | G81: 22.98 | H81: USD/h | J81: https://www.conference-board.org/ilcprogram/index.cfm?id=38269 | K81: https://mcusercontent.com/8dbf465d9a5cfe9f310f1464e/files/aefa3988-2475-e868-fb82-c5a0af13dbaa/EU_Hydronic_Heat_Pump_Manufacturing_Market_Assessment_Technical_Report.pdf
A82: Japan | B82: =AVERAGE($B$73:$B$75) -> 4.5666667 | C82: 29 | D82: =SUM(B82:C82) -> 33.566667 | E82: €/kW | G82: 26.46 | H82: USD/h | J82: https://www.conference-board.org/ilcprogram/index.cfm?id=38269 | K82: https://mcusercontent.com/8dbf465d9a5cfe9f310f1464e/files/aefa3988-2475-e868-fb82-c5a0af13dbaa/EU_Hydronic_Heat_Pump_Manufacturing_Market_Assessment_Technical_Report.pdf
A83: Brazil | B83: =AVERAGE($B$73:$B$75) -> 4.5666667 | C83: 29 | D83: =SUM(B83:C83) -> 33.566667 | E83: €/kW | G83: 7.98 | H83: USD/h | J83: https://www.conference-board.org/ilcprogram/index.cfm?id=38269 | K83: https://mcusercontent.com/8dbf465d9a5cfe9f310f1464e/files/aefa3988-2475-e868-fb82-c5a0af13dbaa/EU_Hydronic_Heat_Pump_Manufacturing_Market_Assessment_Technical_Report.pdf
A85: Cost per carrier | G85: Notes | H85: OPEX Cost in Countrx | J85: Adjust the cost | K85: Estimate total cost | L85: of whcih assumed labor cost | M85: Include labor cost somehow | N85: total cost
A86: Copper | B86: 16.7 | C86: USD/kW | D86: Enel 2023 | G86: use this is cost carriers | H86: Europe | I86: 27.6 | J86: =I86/$I$97 -> 1.0042007 | K86: =D73/0.8 -> 44.25 | L86: =K86-D73 -> 8.85 | M86: =L86*J86 -> 8.8871763 | N86: =M86+D73 -> 44.287176 | O86: €/kW
A87: Nickel | B87: 6.8 | C87: USD/kW | D87: Enel 2023 | G87: use this is cost carriers | H87: China | I87: =I88/3 -> 13.3 | J87: =I87/$I$97 -> 0.48390831 | K87: =D74/0.8 -> 42 | L87: =K87-D74 -> 8.4 | M87: =L87*J87 -> 4.0648298 | N87: =M87+D74 -> 37.66483 | O87: €/kW
A88: Steel | B88: 4.1 | C88: USD/kW | D88: Enel 2023 | G88: use this is cost carriers | H88: USA | I88: 39.9 | J88: =I88/$I$97 -> 1.4517249 | K88: =D75/0.8 -> 39.625 | L88: =K88-D75 -> 7.925 | M88: =L88*J88 -> 11.50492 | N88: =M88+D75 -> 43.20492 | O88: €/kW
A89: Aluminium | B89: 2.2 | C89: USD/kW | D89: Enel 2023 | G89: use this is cost carriers | H89: Germany | I89: 43.18 | J89: =I89/$I$97 -> 1.5710647 | K89: =D76/0.8 -> 44.25 | L89: =K89-D76 -> 8.85 | M89: =L89*J89 -> 13.903923 | N89: =M89+D76 -> 49.303923 | O89: €/kW
A90: Total for secondary material s | B90: =SUM(B86:B89) -> 29.8 | C90: USD/kW | D90: Enel 2023 | G90: use this is cost carriers | H90: Czech republic | I90: 10.71 | J90: =I90/$I$97 -> 0.38967354 | K90: =D77/0.8 -> 44.25 | L90: =K90-D77 -> 8.85 | M90: =L90*J90 -> 3.4486108 | N90: =M90+D77 -> 38.848611 | O90: €/kW
A91: refrigerant | B91: 22 - 108 | C91: € / kg ?? | H91: Austria | I91: 39.54 | J91: =I91/$I$97 -> 1.4386267 | K91: =D78/0.8 -> 44.25 | L91: =K91-D78 -> 8.85 | M91: =L91*J91 -> 12.731846 | N91: =M91+D78 -> 48.131846 | O91: €/kW
H92: Italy | I92: 32.49 | J92: =I92/$I$97 -> 1.1821189 | K92: =D79/0.8 -> 44.25 | L92: =K92-D79 -> 8.85 | M92: =L92*J92 -> 10.461752 | N92: =M92+D79 -> 45.861752 | O92: €/kW
H93: Austrlia | I93: 38.19 | J93: =I93/$I$97 -> 1.3895082 | K93: =D80/0.8 -> 41.958333 | L93: =K93-D80 -> 8.3916667 | M93: =L93*J93 -> 11.660289 | N93: =M93+D80 -> 45.226956 | O93: €/kW
A94: Node | B94: Year | C94: capacity_existing in units | D94: capacity_existing in GW | E94: Carbon footprint | G94: source carbon footprint | H94: South Korea | I94: 22.98 | J94: =I94/$I$97 -> 0.83610624 | K94: =D81/0.8 -> 41.958333 | L94: =K94-D81 -> 8.3916667 | M94: =L94*J94 -> 7.0163249 | N94: =M94+D81 -> 40.582992 | O94: €/kW
A95: AUS | B95: 2022 | C95: 264000 | D95: =Demand!B55/10^6*0.2 -> 2.112 | H95: Japan | I95: 26.46 | J95: =I95/$I$97 -> 0.96272285 | K95: =D82/0.8 -> 41.958333 | L95: =K95-D82 -> 8.3916667 | M95: =L95*J95 -> 8.0788493 | N95: =M95+D82 -> 41.645516 | O95: €/kW
A96: AUT | B96: 2022 | C96: 187500 | D96: =B41 -> 1.5 | H96: Brazil | I96: 7.98 | J96: =I96/$I$97 -> 0.29034499 | K96: =D83/0.8 -> 41.958333 | L96: =K96-D83 -> 8.3916667 | M96: =L96*J96 -> 2.4364784 | N96: =M96+D83 -> 36.003145 | O96: €/kW
A97: BRA | B97: 2022 | C97: 0 | D97: 0.01 | I97: =AVERAGE(I86:I96) -> 27.484545 | J97: =I97/$I$97 -> 1 | K97: =D84/2*3 -> 0 | M97: =K97*J97 -> 0 | N97: =AVERAGE(N86:N96) -> 42.796515 | O97: €/kW
A98: CHN | B98: 2022 | C98: 6250000 | D98: =B31 -> 50
A99: CZE | B99: 2022 | C99: 156250 | D99: =B43 -> 1.25 | O99: https://iea.blob.core.windows.net/assets/7e7f4b17-1bb2-48e4-8a92-fb9355b1d1bd/CleanTechnologyManufacturingRoadmap.pdf
A100: DEU | B100: 2022 | C100: 531250 | D100: =B40 -> 4.25
A101: ITA | B101: 2022 | C101: 500000 | D101: =B42 -> 4
A102: JPN | B102: 2022 | C102: 1142276.3 | D102: =B35 -> 9.1382105
A103: KOR | B103: 2022 | C103: 857723.69 | D103: =B36 -> 6.8617895
A104: ROE | B104: 2022 | C104: 625000 | D104: =B44 -> 14 | E104: 1640 | G104: ecoinvent | H104: Data for CH
A105: ROW | B105: 2022 | C105: 1486000 | D105: =B37-D95 -> 11.888 | E105: 1740 | G105: ecoonvent | H105: includes upstrea
A106: USA | B106: 2022 | C106: 4250000 | D106: =B32 -> 34
D107: =SUM(D95:D106) -> 139.01
...

Sheet conversion
A1: conversion factors | U1: Lifecycle inventories of heating
A3: Conversion | B3: (shamoushaki 2023) | E3: probably for a 10 kW output
A4: Table S1. Inventory data for all phases of air-source heat pump
A5: Manufacturing
A6: Component | B6: Material | C6: Weight | D6: Unit | F6: Conversion of compressor prodcution | G6: Source: Rewlay-ngoen, 2020
A7: Evaporator and condenser | B7: Low-alloyed steel | C7: 32 | D7: kg | E7: assume half aluminium and half copper?? Mentioned in EC JRC 2023 | F7: Material type | G7: Component | H7: Weight | I7: Ratio
A8: Housing and compressor | B8: Reinforcing steel | C8: 120 | D8: kg | H8: (kg) | I8: (%)
A9: Wiring, piping and expansion valve | B9: Copper | C9: 35.2 | D9: kg | F9: Cast iron | G9: Cylinder, shaft, rotor | H9: 4.8 | I9: 20.24
A10: Pipework insulation | B10: Elastomere | C10: 16 | D10: kg | F10: Steel sheet | G10: upper / lower housing, Accumulator | H10: 5.13 | I10: 21.64
A11: Wiring insulation | B11: Polyvinylchloride | C11: 1.6 | D11: kg | F11: High grade steel | G11: Rolling piston | H11: 0.56 | I11: 2.36
A12: Lubricating oil | B12: Polyolester oil | C12: 2.7 | D12: kg | F12: Sintering steel | G12: Upper / lower bearing | H12: 0.19 | I12: 0.8
A13: Air fan | B13: Copper | C13: 1.4 | D13: kg | F13: Silicon steel | G13: Stator, rotor | H13: 7.8 | I13: 32.9
A14: " | B14: HDPE | C14: 0.5 | D14: kg | F14: Copper | G14: Copper wire | H14: 2.26 | I14: 9.53
A15: Refrigerant | B15: R-134a | C15: 4.9 | D15: kg | G15: copper tube | H15: 0.44 | I15: 1.86
A16: " | B16: Losses | C16: 3% (manufacture) & 6% (operation, annually) | F16: Aluminum ingot | G16: Rotor core | H16: 0.37 | I16: 1.56
A17: Energy | B17: Medium-voltage electricity | C17: 504 | D17: MJ | F17: HCFC-22 (R22) | G17: Refrigerant | H17: 1.5 | I17: 6.33
A18: " | B18: Heat | C18: 1400 | D18: MJ | F18: Mineral oil | G18: Lubricant oil | H18: 0.653 | I18: 2.75
A19: Assembly & Installation | F19: Paint | G19: Compressor coating | H19: 0.008 | I19: 0.03
A20: Process | B20: Energy | C20: Weight | D20: Unit | F20: Total | H20: 23.711 | I20: 100
A21: Assembly | B21: Medium-voltage electricity (European mix) | C21: 504 | D21: MJ | F21: Steel total | H21: =(H10+H11+H13+H12)/H20 -> 0.57694741 | I21: =I10+I11+I13+I12 -> 57.7 | J21: kg Steel/kg compressor
A22: " | B22: Natural gas | C22: 1400 | D22: MJ | F22: Copper total | H22: =SUM(H14:H15)/H20 -> 0.1138712 | I22: =SUM(I14:I15) -> 11.39 | J22: kg Copper/kg compressor
A23: O & M
A24: Process/Item | B24: Weight | C24: Unit | D24: Ref
A25: UK electricity | B25: 0.357 | C25: kWh/kWh heat generated | D25: Greening, Benjamin, and Adisa Azapagic. "Domestic heat pumps: Life cycle environmental impacts and potential implications for the UK." Energy 39, no. 1 (2012): 205-217.
A26: Refrigerant | B26: 0.294 | C26: kg (annually) | D26: Sevindik, Selman, Catalina Spataru, Teresa Domenech Aparisi, and Raimund Bleischwitz. "A comparative environmental assessment of heat pumps and gas boilers towards a circular economy in the UK." Energies 14, no. 11 (2021): 3027.
A27: Air‐source heat pumps for residential applications contain around 15 to 20 kilogrammes of copper, predominantly in their pipes and valves, making up roughly 10% of the overall cost of the devic
A30: Average HP | C30: unit | D30: per Fu of 8 W | G30: Demand 2035 | I30: demand 2022 | J30: Bauxite
A31: Aluminum | B31: 32.3 | C31: kg/HP | D31: =B31/'cost estimate'!B31 -> 4.0375 | E31: kg/kW | F31: https://21255462.fs1.hubspotusercontent-na1.net/hubfs/21255462/Reports%20-%20Research/BZE%202024%20-%20Heat%20Pumps%20Supply%20Chain%20Briefing%20Paper.pdf?utm_medium=email&_hsenc=p2ANqtz-9dM8q358vgTGkDybe5e7jgnidtYeyNJEe5lIx4vgFMrCjajGmjMZRA6pWnNwM3C8x8xaJyVpqTPY3p2QLWycjpnTHNBw&_hsmi=295770870&utm_content=295770870&utm_source=hs_automation | G31: =D31*Demand!$N$68/10^6 -> 1519.4847 | H31: kt/a | I31: =D31*SUM(Demand!$B$55:$M$55)/10^6 -> 448.1625 | J31: =I31*4 -> 1792.65 | K31: =G31*1500 -> 2279227
A32: Steel | B32: =AVERAGE(C7+C8,146.9) -> 149.45 | C32: kg/HP | D32: =B32/'cost estimate'!$B$31 -> 18.68125 | E32: kg/kW | G32: =D32*Demand!$N$68/10^6 -> 7030.5569 | H32: kt/a | I32: =D32*SUM(Demand!$B$55:$M$55)/10^6 -> 2073.6187 | K32: =G32*400 -> 2812222.8 | L32: =K31/K32 -> 0.81047173
A33: Copper | B33: =AVERAGE(C9+C13,36.6,59.2) -> 44.133333 | C33: kg/HP | D33: =B33/'cost estimate'!$B$31 -> 5.5166667 | E33: kg/kW | G33: =D33*Demand!$N$68/10^6 -> 2076.1587 | H33: kt/a | I33: =D33*SUM(Demand!$B$55:$M$55)/10^6 -> 612.35 | K33: =G33*1500 -> 3114238
A34: Nickel | B34: =B31*0.15 -> 4.845 | C34: kg/HP | D34: =B34/'cost estimate'!$B$31 -> 0.605625 | E34: kg/kW | F34: Assume nickel in alloyed steel | G34: =D34*Demand!$N$68/10^6 -> 227.9227 | H34: kt/a | I34: =D34*SUM(Demand!$B$55:$M$55)/10^6 -> 67.224375 | K34: =G34*1500 -> 341884.06
A35: copper of which are in compressor | B35: =I22 -> 11.39 | C35: kg/HP | D35: =B35/'cost estimate'!$B$31 -> 1.42375 | E35: kg/kW
A36: copper in rest of hp | B36: =B33-B35 -> 32.743333 | C36: kg/HP | D36: =B36/'cost estimate'!$B$31 -> 4.0929167 | E36: kg/kW
A37: steel in compressot | B37: =I21 -> 57.7 | C37: kg/HP | D37: =B37/'cost estimate'!$B$31 -> 7.2125 | E37: kg/kW
A38: Steel rest in HP | B38: =B32-B37 -> 91.75 | C38: kg/HP | D38: =B38/'cost estimate'!$B$31 -> 11.46875 | E38: kg/kW | G38: =1351959+135185+942882 -> 2430026
A39: Refrigerant | B39: =AVERAGE(C15,4.9,4.9,3.5) -> 4.55 | C39: kg/HP | D39: =B39/'cost estimate'!$B$31 -> 0.56875 | E39: kg/kW | G39: =2794175+27982 -> 2822157
M49: From EC JRC Report (page 43):

Sheet cost estimate
A3: cost of heat pump 8Kw | C3: to estimate market value | D3: in €/kW
A4: UK example | B4: 3760 | C4: Punds | E4: https://www.sciencedirect.com/science/article/pii/S2211467X2400227X
B5: =B4/O46 -> 4498.6839 | C5: Euros/HP
A6: Share compressor | B6: =B5*0.25 -> 1124.671 | C6: Euros/HP or Euros /8kW | D6: =B6/8 -> 140.58387 | E6: Heat Pump Supply Chains and Manufacturing Competitiveness Considerations
A7: sahre HX | B7: =B5*0.16 -> 719.78942 | C7: Euros/HP or Euros /8kW | D7: =B7/8 -> 89.973678 | E7: Heat Pump Supply Chains and Manufacturing Competitiveness Considerations (Margaret Mann, 2016)
A8: sahre refrigerant | B8: =0.02*B5/conversion!B39 -> 19.774435 | C8: Euro/kg refrigerant | D8: =B8/8 -> 2.4718043 | E8: Heat Pump Supply Chains and Manufacturing Competitiveness Considerations (Margaret Mann, 2016)
A10: year | B10: price_shed_demand
A11: 2022 | B11: "inf"
A12: 2023 | B12: "inf"
A13: 2024 | B13: "inf"
A14: 2025 | B14: "inf"
A15: 2026 | B15: "inf"
A16: 2027 | B16: "inf"
A17: 2028 | B17: "inf"
A18: 2029 | B18: "inf"
A19: 2030 | B19: "inf"
A20: 2031 | B20: "inf"
A21: 2032 | B21: "inf"
A22: 2033 | B22: =140*11.5 -> 1610 | C22: €/kW
A23: 2034 | B23: =140*11.5 -> 1610 | C23: €/kW
A24: 2035 | B24: =140*11.5 -> 1610 | C24: €/kW
A29: Assumption for conversino
A30: HP | B30: kW
A31: 1 | B31: 8
A33: Regionalized cost factors
A34: For Labour | B34: €/h | C34: Labour adjusment factor
A35: Australia | B35: 38.19 | C35: =B35/$B$46 -> 1.3895082
A36: Austria | B36: 39.54 | C36: =B36/$B$46 -> 1.4386267
A37: Brazil | B37: 7.98 | C37: =B37/$B$46 -> 0.29034499
A38: China | B38: =B45/3 -> 13.3 | C38: =B38/$B$46 -> 0.48390831
A39: Czech republic | B39: 10.71 | C39: =B39/$B$46 -> 0.38967354
A40: Germany | B40: 43.18 | C40: =B40/$B$46 -> 1.5710647
A41: Italy | B41: 32.49 | C41: =B41/$B$46 -> 1.1821189 | E41: =AVERAGE(C35,C49) -> 1.2264618
A42: Japan | B42: 26.46 | C42: =B42/$B$46 -> 0.96272285 | E42: =AVERAGE(C36,C50) -> 1.4204663
A43: Korea | B43: 22.98 | C43: =B43/$B$46 -> 0.83610624 | E43: =AVERAGE(C37,C51) -> 0.44511017
A44: Rest of Europe | B44: 27.6 | C44: =B44/$B$46 -> 1.0042007 | E44: =AVERAGE(C38,C52) -> 0.39387064 | N44: converison factor
A45: USA | B45: 39.9 | C45: =B45/$B$46 -> 1.4517249 | E45: =AVERAGE(C39,C53) -> 0.89404213 | N45: euro | O45: 1 | Q45: https://www.currency.me.uk/convert/eur/gbp#:~:text=Latest%20Currency%20Exchange%20Rates%3A%201%20Euro%20%3D%200.8358%20British%20Pound
B46: =AVERAGE(B35:B45) -> 27.484545 | E46: =AVERAGE(C40,C54) -> 1.4964236 | N46: pound | O46: 0.8358
E47: =AVERAGE(C41,C55) -> 1.4811342
A48: For Energy Cost | B48: USD/kWh | C48: Energy adjusment factor | E48: =AVERAGE(C42,C56) -> 0.91179147
A49: Australia | B49: 0.273 | C49: =B49/$B$60 -> 1.0634154 | E49: =AVERAGE(C43,C57) -> 0.67319491
A50: Austria | B50: 0.36 | C50: =B50/$B$60 -> 1.402306 | E50: =AVERAGE(C44,C58) -> 1.0049829
A51: Brazil | B51: 0.154 | C51: =B51/$B$60 -> 0.59987535 | E51: =AVERAGE(C45,C59) -> 1.0842296
A52: China | B52: 0.078 | C52: =B52/$B$60 -> 0.30383297
A53: Czech republic | B53: 0.359 | C53: =B53/$B$60 -> 1.3984107
A54: Germany | B54: 0.365 | C54: =B54/$B$60 -> 1.4217825
A55: Italy | B55: 0.457 | C55: =B55/$B$60 -> 1.7801496
A56: Japan | B56: 0.221 | C56: =B56/$B$60 -> 0.86086008
A57: Korea | B57: 0.131 | C57: =B57/$B$60 -> 0.51028358
A58: Rest of Europe | B58: =AVERAGE(B49:B57,B59) -> 0.2582 | C58: =B58/$B$60 -> 1.005765
A59: USA | B59: 0.184 | C59: =B59/$B$60 -> 0.71673419
B60: =AVERAGE(B50:B59) -> 0.25672

Sheet Jobs
A1: Country | B1: Jobs | C1: Type | D1: Year | E1: Source | F1: Projected workforce 2030 | G1: Notes | H1: Source
A2: Europe | B2: 44000 | C2: heat pump manufacturing | D2: 2022 | E2: EHPA 2022
A3: Europe | B3: 22000 | C3: component manufacturing | D3: 2022 | E3: EHPA 2022
A4: China | B4: 100000 | C4: Manufacturing | D4: 2022 | E4: IEA, Outlook Heat pump china | F4: 200000 | G4: extra workers in the sector | H4: IEA, HP in China
A6: Global | B6: 810000 | C6: in HP supply chain | D6: 2022 | E6: IEA, Outlook Heat pump china
A8: australia | B8: 7000 | C8: in HP manufacturing | D8: 2030 | E8: https://21255462.fs1.hubspotusercontent-na1.net/hubfs/21255462/Reports%20-%20Research/BZE%202024%20-%20Make%20it%20Here%20Building%20Australias%20Clean%20Industrial%20Future%20.pdf?utm_medium=email&_hsenc=p2ANqtz-830lZIoJiepzUI-y6CKlT2VKway4PaFo_35Km9xKs-JjEI34UFgSiLcYE4S5qALQvqTJZSZ2a2d6oBJgafaoQ4Rw4QzA&_hsmi=305939647&utm_content=305939647&utm_source=hs_automation
A12: Steel | B12: 6 | C12: Mio. Jobs
A13: in europe | B13: 330000 | C13: jobs
A14: australoa | B14: 100000 | C14: jobs
I22: lbaor prodoctivity | J22: https://mcusercontent.com/8dbf465d9a5cfe9f310f1464e/files/aefa3988-2475-e868-fb82-c5a0af13dbaa/EU_Hydronic_Heat_Pump_Manufacturing_Market_Assessment_Technical_Report.pdf

Sheet Demand
A2: Country | B2: Sales of heating heat pumps 2022 | C2: Growth in sales 2021 to 2022 (% of additional heat pumps units sold) | D2: Growth in sales 2021 to 2022 (no. of additional heat pumps units sold) | E2: Source | F2: https://www.ehpa.org/wp-content/uploads/2023/06/Heat-Pump-Key-Facts-May-2023_compressed.pdf | G2: Country | H2: Sales/value | I2: Unit | J2: year | K2: Source | L2: Annual grth rate IEA | M2: CAGR | N2: Sales in ASHP | O2: Sales in GSHP | P2: Source | Q2: Projected Value in 2030 | R2: Pojected sales in 2050 | S2: Source
A3: Austria | B3: 49204 | C3: 0.59 | D3: 18227 | E3: EHPA, 2023 | G3: Japan | H3: 746000 | I3: units | J3: 2021 | K3: https://heatpumpingtechnologies.org/wp-content/uploads/2023/03/mcr-iea-hpt-presentation-japan-20230314.pdf | L3: A
G4: South Korea | H4: =3*10^9 -> 3000000000 | I4: USD, value | J4: 2022 | K4: https://heatpumpingtechnologies.org/wp-content/uploads/2022/08/iea-hpt-tcp-member-country-report-korea-2022minsung-kim.pdf | L4: A
A5: Belgium | B5: 32965 | C5: 0.66 | D5: 13121 | E5: EHPA, 2023 | G5: USA | H5: =4.33*10^6 -> 4330000 | I5: units | J5: 2022 | K5: https://heatpumpingtechnologies.org/wp-content/uploads/2023/06/us-country-report-2023.pdf | L5: A
G6: USA | H6: 30 | I6: GW | J6: 2022 | K6: IEA, 2024 | L6: A | Q6: =H7*2 -> 62 | S6: https://iea.blob.core.windows.net/assets/217e820f-3344-4144-9d2c-cc444e080421/FutureofHeatpumpsinChina.pdf
A7: Czechia | B7: 60065 | C7: 0.99 | D7: 29886 | E7: EHPA, 2023 | G7: China | H7: 31 | I7: GW | J7: 2022 | K7: https://www.iea.org/reports/the-future-of-heat-pumps-in-china/executive-summary | L7: A | M7: 0.04
G8: China | H8: 1000000 | I8: units | J8: 2022 | K8: https://www.heatpumps.london/blog/everything-you-need-to-know-about-heat-pumps | L8: A
G9: China | H9: =31*10^9 -> 31000000000 | I9: RMB | J9: 2022 | K9: http://www.chinaiol.com/download/Global%20Heat%20Pump%20Market%20Report%202024.pdf | L9: this includes HP and AC split systems
A10: Denmark | B10: 88833 | C10: 0.2 | D10: 14892 | E10: EHPA, 2023 | G10: Australia | H10: =1.32*10^6 -> 1320000 | I10: units | J10: 2022 | K10: https://iifiir.org/en/news/main-figures-for-the-australian-heat-pump-market#:~:text=Single%20split%20system%20sales%20were,commercial%20heat%20pumps%20is%20small. | L10: 50% in Aitr to water and 20 percent in air to air | N10: =1800*10^3 -> 1800000 | P10: http://www.chinaiol.com/download/Global%20Heat%20Pump%20Market%20Report%202024.pdf | Q10: =7*10^6 -> 7000000 | S10: https://mcusercontent.com/8dbf465d9a5cfe9f310f1464e/files/aefa3988-2475-e868-fb82-c5a0af13dbaa/EU_Hydronic_Heat_Pump_Manufacturing_Market_Assessment_Technical_Report.pdf
G11: Europe | H11: =3*10^6 -> 3000000 | I11: units | J11: 2022 | K11: https://mcusercontent.com/8dbf465d9a5cfe9f310f1464e/files/aefa3988-2475-e868-fb82-c5a0af13dbaa/EU_Hydronic_Heat_Pump_Manufacturing_Market_Assessment_Technical_Report.pdf | L11: 24 air to water and 8% in ata; 1000 GW in cumulative capacity | Q11: 25000 | R11: 60000 | S11: https://mcusercontent.com/8dbf465d9a5cfe9f310f1464e/files/aefa3988-2475-e868-fb82-c5a0af13dbaa/EU_Hydronic_Heat_Pump_Manufacturing_Market_Assessment_Technical_Report.pdf
A12: Finland | B12: 196359 | C12: 0.52 | D12: 66984 | E12: EHPA, 2023 | G12: global cumulative | H12: 1000 | I12: GW | J12: 2021 | K12: https://mcusercontent.com/8dbf465d9a5cfe9f310f1464e/files/aefa3988-2475-e868-fb82-c5a0af13dbaa/EU_Hydronic_Heat_Pump_Manufacturing_Market_Assessment_Technical_Report.pdf
G13: global yearly | H13: 111 | I13: GW | K13: IEA
A14: France | B14: 462672 | C14: 0.2 | D14: 76176 | E14: EHPA, 2023 | G14: calculated: | H14: =H13*10^6/8 -> 13875000 | I14: units sold | K14: validation in https://21255462.fs1.hubspotusercontent-na1.net/hubfs/21255462/Reports%20-%20Research/BZE%202024%20-%20Heat%20Pumps%20Supply%20Chain%20Briefing%20Paper.pdf?utm_medium=email&_hsenc=p2ANqtz-9dM8q358vgTGkDybe5e7jgnidtYeyNJEe5lIx4vgFMrCjajGmjMZRA6pWnNwM3C8x8xaJyVpqTPY3p2QLWycjpnTHNBw&_hsmi=295770870&utm_content=295770870&utm_source=hs_automation
G15: global | H15: =8*10^6 -> 8000000 | I15: units sold | J15: 2020 | K15: lyons 2023
A16: Germany | B16: 236000 | C16: 0.53 | D16: 82000 | E16: EHPA, 2023
A18: Italy | B18: 502349 | C18: 0.37 | D18: 134429 | E18: EHPA, 2023
H19: Growth Rate | K19: europe is fastes growing HP market
A20: Netherlands | B20: 123208 | C20: 0.8 | D20: 54796 | E20: EHPA, 2023 | G20: Europe | H20: 0.17 | I20: CAGR | J20: ( https://eur-lex.europa.eu/legal-content/EN/TXT/?uri=CELEX%3A52022DC0643&qid=1669913060946)
G21: Oceania | H21: 0.04 | I21: CAGR | J21: https://iifiir.org/en/news/main-figures-for-the-australian-heat-pump-market#:~:text=Single%20split%20system%20sales%20were,commercial%20heat%20pumps%20is%20small.
A22: Norway | B22: 156295 | C22: 0.25 | D22: 31267 | E22: EHPA, 2023 | G22: North America | H22: 0.088 | I22: CAGR | J22: https://www.news.market.us/heat-pump-statistics/
G23: Asia | H23: 0.125 | I23: YoY | J23: http://www.chinaiol.com/download/Global%20Heat%20Pump%20Market%20Report%202024.pdf
A24: Poland | B24: 195480 | C24: 1.02 | D24: 98540 | E24: EHPA, 2023 | G24: Global | H24: 0.11 | I24: YoY | J24: https://www.iea.org/commentaries/global-heat-pump-sales-continue-double-digit-growth
G25: China | H25: =(35/31)^(1/4)-1 -> 0.030805169 | I25: CAGR | J25: calulated from data from iEA https://www.iea.org/reports/the-future-of-heat-pumps-in-china/executive-summary
A26: Portugal | B26: 29969 | C26: 0.17 | D26: 4357 | E26: EHPA, 2023 | G26: Global | H26: =(111/84)^(1/4)-1 -> 0.072163265 | I26: CAGR | J26: calulated from data from iEA https://www.iea.org/reports/the-future-of-heat-pumps-in-china/executive-summary | U26: https://iea.blob.core.windows.net/assets/217e820f-3344-4144-9d2c-cc444e080421/FutureofHeatpumpsinChina.pdf
U27: http://www.chinaiol.com/download/Global%20Heat%20Pump%20Market%20Report%202024.pdf
A28: Sweden*** | B28: 215373 | C28: 0.6 | D28: 81875 | E28: EHPA, 2023
A30: Switzerland | B30: 41209 | C30: 0.22 | D30: 7505 | E30: EHPA, 2023
A32: Spain | B32: 161800 | C32: 0.21 | D32: 28129 | E32: EHPA, 2023
A34: UK**** | B34: 59862 | C34: 0.4 | D34: 17103 | E34: EHPA, 2023
A36: Scenario 1: continue with current growth rate in unit pcs.
A37: year | B37: AUS | C37: AUT | D37: BRA | E37: CHN | F37: CZE | G37: DEU | H37: ITA | I37: JPN | J37: KOR | K37: ROE | L37: ROW | M37: USA | N37: unit
A38: 2022 | B38: =1.32*10^6 -> 1320000 | C38: 49204 | D38: 0 | E38: 1000000 | F38: 60065 | G38: 236000 | H38: 502349 | I38: 746000 | J38: =H4/'cost estimate'!B5*0.84 -> 560163.83 | K38: =H11-SUM(F38:H38,C38) -> 2152382 | L38: =H14-SUM(B38:K38,M38) -> 2918836.2 | M38: =4.33*10^6 -> 4330000 | N38: pcs
A39: 2023 | B39: =$B$38*($H$21+1)^(A39-$A$38) -> 1372800 | C39: =$C$38*(1+$H$20)^(A39-$A$38) -> 57568.68 | D39: 0 | E39: =$E$38*(1+$H$23)^(A39-$A$38) -> 1125000 | F39: =$F$38*(1+$H$20)^(A39-$A$38) -> 70276.05 | G39: =$G$38*(1+$H$20)^(A39-$A$38) -> 276120 | H39: =$H$38*(1+$H$20)^(A39-$A$38) -> 587748.33 | I39: =$I$38*(1+$H$23)^((A39-$A$38)) -> 839250 | J39: =$J$38*(1+$H$23)^((A39-$A$38)) -> 630184.31 | K39: =$K$38*(1+$H$20)^(A39-$A$38) -> 2518286.9 | L39: =$L$38*(1+$H$24)^(A39-$A$38) -> 3239908.1 | M39: =$M$38*(1+$H$22)^((A39-$A$38)) -> 4711040 | N39: pcs
A40: 2024 | B40: =$B$38*($H$21+1)^(A40-$A$38) -> 1427712 | C40: =$C$38*(1+$H$20)^(A40-$A$38) -> 67355.356 | D40: 0 | E40: =$E$38*(1+$H$23)^(A40-$A$38) -> 1265625 | F40: =$F$38*(1+$H$20)^(A40-$A$38) -> 82222.978 | G40: =$G$38*(1+$H$20)^(A40-$A$38) -> 323060.4 | H40: =$H$38*(1+$H$20)^(A40-$A$38) -> 687665.55 | I40: =$I$38*(1+$H$23)^((A40-$A$38)) -> 944156.25 | J40: =$J$38*(1+$H$23)^((A40-$A$38)) -> 708957.35 | K40: =$K$38*(1+$H$20)^(A40-$A$38) -> 2946395.7 | L40: =$L$38*(1+$H$24)^(A40-$A$38) -> 3596298 | M40: =$M$38*(1+$H$22)^((A40-$A$38)) -> 5125611.5 | N40: pcs
A41: 2025 | B41: =$B$38*($H$21+1)^(A41-$A$38) -> 1484820.5 | C41: =$C$38*(1+$H$20)^(A41-$A$38) -> 78805.766 | D41: 0 | E41: =$E$38*(1+$H$23)^(A41-$A$38) -> 1423828.1 | F41: =$F$38*(1+$H$20)^(A41-$A$38) -> 96200.885 | G41: =$G$38*(1+$H$20)^(A41-$A$38) -> 377980.67 | H41: =$H$38*(1+$H$20)^(A41-$A$38) -> 804568.69 | I41: =$I$38*(1+$H$23)^((A41-$A$38)) -> 1062175.8 | J41: =$J$38*(1+$H$23)^((A41-$A$38)) -> 797577.02 | K41: =$K$38*(1+$H$20)^(A41-$A$38) -> 3447283 | L41: =$L$38*(1+$H$24)^(A41-$A$38) -> 3991890.8 | M41: =$M$38*(1+$H$22)^((A41-$A$38)) -> 5576665.3 | N41: pcs
A42: 2026 | B42: =$B$38*($H$21+1)^(A42-$A$38) -> 1544213.3 | C42: =$C$38*(1+$H$20)^(A42-$A$38) -> 92202.746 | D42: 0 | E42: =$E$38*(1+$H$23)^(A42-$A$38) -> 1601806.6 | F42: =$F$38*(1+$H$20)^(A42-$A$38) -> 112555.04 | G42: =$G$38*(1+$H$20)^(A42-$A$38) -> 442237.38 | H42: =$H$38*(1+$H$20)^(A42-$A$38) -> 941345.37 | I42: =$I$38*(1+$H$23)^((A42-$A$38)) -> 1194947.8 | J42: =$J$38*(1+$H$23)^((A42-$A$38)) -> 897274.14 | K42: =$K$38*(1+$H$20)^(A42-$A$38) -> 4033321.1 | L42: =$L$38*(1+$H$24)^(A42-$A$38) -> 4430998.8 | M42: =$M$38*(1+$H$22)^((A42-$A$38)) -> 6067411.9 | N42: pcs
A43: 2027 | B43: =$B$38*($H$21+1)^(A43-$A$38) -> 1605981.8 | C43: =$C$38*(1+$H$20)^(A43-$A$38) -> 107877.21 | D43: 0 | E43: =$E$38*(1+$H$23)^(A43-$A$38) -> 1802032.5 | F43: =$F$38*(1+$H$20)^(A43-$A$38) -> 131689.39 | G43: =$G$38*(1+$H$20)^(A43-$A$38) -> 517417.74 | H43: =$H$38*(1+$H$20)^(A43-$A$38) -> 1101374.1 | I43: =$I$38*(1+$H$23)^((A43-$A$38)) -> 1344316.2 | J43: =$J$38*(1+$H$23)^((A43-$A$38)) -> 1009433.4 | K43: =$K$38*(1+$H$20)^(A43-$A$38) -> 4718985.7 | L43: =$L$38*(1+$H$24)^(A43-$A$38) -> 4918408.7 | M43: =$M$38*(1+$H$22)^((A43-$A$38)) -> 6601344.1 | N43: pcs
A44: 2028 | B44: =$B$38*($H$21+1)^(A44-$A$38) -> 1670221.1 | C44: =$C$38*(1+$H$20)^(A44-$A$38) -> 126216.34 | D44: 0 | E44: =$E$38*(1+$H$23)^(A44-$A$38) -> 2027286.5 | F44: =$F$38*(1+$H$20)^(A44-$A$38) -> 154076.59 | G44: =$G$38*(1+$H$20)^(A44-$A$38) -> 605378.75 | H44: =$H$38*(1+$H$20)^(A44-$A$38) -> 1288607.7 | I44: =$I$38*(1+$H$23)^((A44-$A$38)) -> 1512355.8 | J44: =$J$38*(1+$H$23)^((A44-$A$38)) -> 1135612.6 | K44: =$K$38*(1+$H$20)^(A44-$A$38) -> 5521213.3 | L44: =$L$38*(1+$H$24)^(A44-$A$38) -> 5459433.6 | M44: =$M$38*(1+$H$22)^((A44-$A$38)) -> 7182262.4 | N44: pcs
A45: 2029 | B45: =$B$38*($H$21+1)^(A45-$A$38) -> 1737029.9 | C45: =$C$38*(1+$H$20)^(A45-$A$38) -> 147673.12 | D45: 0 | E45: =$E$38*(1+$H$23)^(A45-$A$38) -> 2280697.3 | F45: =$F$38*(1+$H$20)^(A45-$A$38) -> 180269.61 | G45: =$G$38*(1+$H$20)^(A45-$A$38) -> 708293.14 | H45: =$H$38*(1+$H$20)^(A45-$A$38) -> 1507671 | I45: =$I$38*(1+$H$23)^((A45-$A$38)) -> 1701400.2 | J45: =$J$38*(1+$H$23)^((A45-$A$38)) -> 1277564.2 | K45: =$K$38*(1+$H$20)^(A45-$A$38) -> 6459819.5 | L45: =$L$38*(1+$H$24)^(A45-$A$38) -> 6059971.3 | M45: =$M$38*(1+$H$22)^((A45-$A$38)) -> 7814301.5 | N45: pcs
A46: 2030 | B46: =$B$38*($H$21+1)^(A46-$A$38) -> 1806511.1 | C46: =$C$38*(1+$H$20)^(A46-$A$38) -> 172777.55 | D46: 0 | E46: =$E$38*(1+$H$23)^(A46-$A$38) -> 2565784.5 | F46: =$F$38*(1+$H$20)^(A46-$A$38) -> 210915.44 | G46: =$G$38*(1+$H$20)^(A46-$A$38) -> 828702.97 | H46: =$H$38*(1+$H$20)^(A46-$A$38) -> 1763975 | I46: =$I$38*(1+$H$23)^((A46-$A$38)) -> 1914075.2 | J46: =$J$38*(1+$H$23)^((A46-$A$38)) -> 1437259.7 | K46: =$K$38*(1+$H$20)^(A46-$A$38) -> 7557988.8 | L46: =$L$38*(1+$H$24)^(A46-$A$38) -> 6726568.2 | M46: =$M$38*(1+$H$22)^((A46-$A$38)) -> 8501960 | N46: pcs
A47: 2031 | B47: =$B$38*($H$21+1)^(A47-$A$38) -> 1878771.6 | C47: =$C$38*(1+$H$20)^(A47-$A$38) -> 202149.73 | D47: 0 | E47: =$E$38*(1+$H$23)^(A47-$A$38) -> 2886507.6 | F47: =$F$38*(1+$H$20)^(A47-$A$38) -> 246771.07 | G47: =$G$38*(1+$H$20)^(A47-$A$38) -> 969582.48 | H47: =$H$38*(1+$H$20)^(A47-$A$38) -> 2063850.8 | I47: =$I$38*(1+$H$23)^((A47-$A$38)) -> 2153334.7 | J47: =$J$38*(1+$H$23)^((A47-$A$38)) -> 1616917.1 | K47: =$K$38*(1+$H$20)^(A47-$A$38) -> 8842846.9 | L47: =$L$38*(1+$H$24)^(A47-$A$38) -> 7466490.7 | M47: =$M$38*(1+$H$22)^((A47-$A$38)) -> 9250132.5 | N47: pcs
A48: 2032 | B48: =$B$38*($H$21+1)^(A48-$A$38) -> 1953922.5 | C48: =$C$38*(1+$H$20)^(A48-$A$38) -> 236515.18 | D48: 0 | E48: =$E$38*(1+$H$23)^(A48-$A$38) -> 3247321 | F48: =$F$38*(1+$H$20)^(A48-$A$38) -> 288722.15 | G48: =$G$38*(1+$H$20)^(A48-$A$38) -> 1134411.5 | H48: =$H$38*(1+$H$20)^(A48-$A$38) -> 2414705.4 | I48: =$I$38*(1+$H$23)^((A48-$A$38)) -> 2422501.5 | J48: =$J$38*(1+$H$23)^((A48-$A$38)) -> 1819031.8 | K48: =$K$38*(1+$H$20)^(A48-$A$38) -> 10346131 | L48: =$L$38*(1+$H$24)^(A48-$A$38) -> 8287804.7 | M48: =$M$38*(1+$H$22)^((A48-$A$38)) -> 10064144 | N48: pcs
A49: 2033 | B49: =$B$38*($H$21+1)^(A49-$A$38) -> 2032079.4 | C49: =$C$38*(1+$H$20)^(A49-$A$38) -> 276722.77 | D49: 0 | E49: =$E$38*(1+$H$23)^(A49-$A$38) -> 3653236.2 | F49: =$F$38*(1+$H$20)^(A49-$A$38) -> 337804.91 | G49: =$G$38*(1+$H$20)^(A49-$A$38) -> 1327261.5 | H49: =$H$38*(1+$H$20)^(A49-$A$38) -> 2825205.4 | I49: =$I$38*(1+$H$23)^((A49-$A$38)) -> 2725314.2 | J49: =$J$38*(1+$H$23)^((A49-$A$38)) -> 2046410.8 | K49: =$K$38*(1+$H$20)^(A49-$A$38) -> 12104973 | L49: =$L$38*(1+$H$24)^(A49-$A$38) -> 9199463.2 | M49: =$M$38*(1+$H$22)^((A49-$A$38)) -> 10949789 | N49: pcs
A50: 2034 | B50: =$B$38*($H$21+1)^(A50-$A$38) -> 2113362.5 | C50: =$C$38*(1+$H$20)^(A50-$A$38) -> 323765.64 | D50: 0 | E50: =$E$38*(1+$H$23)^(A50-$A$38) -> 4109890.7 | F50: =$F$38*(1+$H$20)^(A50-$A$38) -> 395231.75 | G50: =$G$38*(1+$H$20)^(A50-$A$38) -> 1552895.9 | H50: =$H$38*(1+$H$20)^(A50-$A$38) -> 3305490.3 | I50: =$I$38*(1+$H$23)^((A50-$A$38)) -> 3065978.4 | J50: =$J$38*(1+$H$23)^((A50-$A$38)) -> 2302212.1 | K50: =$K$38*(1+$H$20)^(A50-$A$38) -> 14162819 | L50: =$L$38*(1+$H$24)^(A50-$A$38) -> 10211404 | M50: =$M$38*(1+$H$22)^((A50-$A$38)) -> 11913370 | N50: pcs
A51: 2035 | B51: =$B$38*($H$21+1)^(A51-$A$38) -> 2197897 | C51: =$C$38*(1+$H$20)^(A51-$A$38) -> 378805.79 | D51: 0 | E51: =$E$38*(1+$H$23)^(A51-$A$38) -> 4623627 | F51: =$F$38*(1+$H$20)^(A51-$A$38) -> 462421.14 | G51: =$G$38*(1+$H$20)^(A51-$A$38) -> 1816888.2 | H51: =$H$38*(1+$H$20)^(A51-$A$38) -> 3867423.6 | I51: =$I$38*(1+$H$23)^((A51-$A$38)) -> 3449225.7 | J51: =$J$38*(1+$H$23)^((A51-$A$38)) -> 2589988.6 | K51: =$K$38*(1+$H$20)^(A51-$A$38) -> 16570498 | L51: =$L$38*(1+$H$24)^(A51-$A$38) -> 11334659 | M51: =$M$38*(1+$H$22)^((A51-$A$38)) -> 12961747 | N51: =SUM(B51:M51) -> 60253180
A53: year | B53: AUS | C53: AUT | D53: BRA | E53: CHN | F53: CZE | G53: DEU | H53: ITA | I53: JPN | J53: KOR | K53: ROE | L53: ROW | M53: USA
N54: kW
A55: 2022 | B55: =1.32*10^6*8 -> 10560000 | C55: =49204*'cost estimate'!B31 -> 393632 | D55: 0 | E55: =H7*10^6 -> 31000000 | F55: =60065*'cost estimate'!B31 -> 480520 | G55: =236000*'cost estimate'!B31 -> 1888000 | H55: =502349*'cost estimate'!B31 -> 4018792 | I55: =746000*'cost estimate'!B31 -> 5968000 | J55: =H4/'cost estimate'!B5*0.84*'cost estimate'!B31 -> 4481310.6 | K55: =H11*8-SUM(F55:H55,C55) -> 17219056 | L55: =H13*10^6-SUM(B55:K55,M55) -> 4990689.4 | M55: =H6*10^6 -> 30000000 | N55: kW
A56: 2023 | B56: =$B$55*($H$21+1)^(A56-$A$55) -> 10982400 | C56: =$C$55*(1+$H$20)^(A56-$A$55) -> 460549.44 | D56: 0 | E56: =$E$55*(1+$H$25)^(A56-$A$38) -> 31954960 | F56: =$F$55*(1+$H$20)^(A56-$A$38) -> 562208.4 | G56: =$G$55*(1+$H$20)^(A56-$A$38) -> 2208960 | H56: =$H$55*(1+$H$20)^(A56-$A$38) -> 4701986.6 | I56: =$I$55*(1+$H$26)^((A56-$A$38)) -> 6398670.4 | J56: =$J$55*(1+$H$26)^((A56-$A$38)) -> 4804696.6 | K56: =$K$55*(1+$H$20)^(A56-$A$38) -> 20146296 | L56: =$L$55*(1+$H$26)^(A56-$A$38) -> 5350833.8 | M56: =$M$55*(1+$H$22)^((A56-$A$38)) -> 32640000 | N56: kW
A57: 2024 | B57: =$B$55*($H$21+1)^(A57-$A$55) -> 11421696 | C57: =$C$55*(1+$H$20)^(A57-$A$55) -> 538842.84 | D57: 0 | E57: =$E$55*(1+$H$25)^(A57-$A$38) -> 32939338 | F57: =$F$55*(1+$H$20)^(A57-$A$38) -> 657783.83 | G57: =$G$55*(1+$H$20)^(A57-$A$38) -> 2584483.2 | H57: =$H$55*(1+$H$20)^(A57-$A$38) -> 5501324.4 | I57: =$I$55*(1+$H$26)^((A57-$A$38)) -> 6860419.3 | J57: =$J$55*(1+$H$26)^((A57-$A$38)) -> 5151419.2 | K57: =$K$55*(1+$H$20)^(A57-$A$38) -> 23571166 | L57: =$L$55*(1+$H$26)^(A57-$A$38) -> 5736967.4 | M57: =$M$55*(1+$H$22)^((A57-$A$38)) -> 35512320 | N57: kW
A58: 2025 | B58: =$B$55*($H$21+1)^(A58-$A$55) -> 11878564 | C58: =$C$55*(1+$H$20)^(A58-$A$55) -> 630446.13 | D58: 0 | E58: =$E$55*(1+$H$25)^(A58-$A$38) -> 33954040 | F58: =$F$55*(1+$H$20)^(A58-$A$38) -> 769607.08 | G58: =$G$55*(1+$H$20)^(A58-$A$38) -> 3023845.3 | H58: =$H$55*(1+$H$20)^(A58-$A$38) -> 6436549.5 | I58: =$I$55*(1+$H$26)^((A58-$A$38)) -> 7355489.6 | J58: =$J$55*(1+$H$26)^((A58-$A$38)) -> 5523162.5 | K58: =$K$55*(1+$H$20)^(A58-$A$38) -> 27578264 | L58: =$L$55*(1+$H$26)^(A58-$A$38) -> 6150965.7 | M58: =$M$55*(1+$H$22)^((A58-$A$38)) -> 38637404 | N58: kW
A59: 2026 | B59: =$B$55*($H$21+1)^(A59-$A$55) -> 12353706 | C59: =$C$55*(1+$H$20)^(A59-$A$55) -> 737621.97 | D59: 0 | E59: =$E$55*(1+$H$25)^(A59-$A$38) -> 35000000 | F59: =$F$55*(1+$H$20)^(A59-$A$38) -> 900440.28 | G59: =$G$55*(1+$H$20)^(A59-$A$38) -> 3537899.1 | H59: =$H$55*(1+$H$20)^(A59-$A$38) -> 7530762.9 | I59: =$I$55*(1+$H$26)^((A59-$A$38)) -> 7886285.7 | J59: =$J$55*(1+$H$26)^((A59-$A$38)) -> 5921731.9 | K59: =$K$55*(1+$H$20)^(A59-$A$38) -> 32266569 | L59: =$L$55*(1+$H$26)^(A59-$A$38) -> 6594839.5 | M59: =$M$55*(1+$H$22)^((A59-$A$38)) -> 42037496 | N59: kW
A60: 2027 | B60: =$B$55*($H$21+1)^(A60-$A$55) -> 12847855 | C60: =$C$55*(1+$H$20)^(A60-$A$55) -> 863017.71 | D60: 0 | E60: =$E$55*(1+$H$25)^(A60-$A$38) -> 36078181 | F60: =$F$55*(1+$H$20)^(A60-$A$38) -> 1053515.1 | G60: =$G$55*(1+$H$20)^(A60-$A$38) -> 4139341.9 | H60: =$H$55*(1+$H$20)^(A60-$A$38) -> 8810992.6 | I60: =$I$55*(1+$H$26)^((A60-$A$38)) -> 8455385.8 | J60: =$J$55*(1+$H$26)^((A60-$A$38)) -> 6349063.4 | K60: =$K$55*(1+$H$20)^(A60-$A$38) -> 37751886 | L60: =$L$55*(1+$H$26)^(A60-$A$38) -> 7070744.7 | M60: =$M$55*(1+$H$22)^((A60-$A$38)) -> 45736795 | N60: kW
A61: 2028 | B61: =$B$55*($H$21+1)^(A61-$A$55) -> 13361769 | C61: =$C$55*(1+$H$20)^(A61-$A$55) -> 1009730.7 | D61: 0 | E61: =$E$55*(1+$H$25)^(A61-$A$38) -> 37189575 | F61: =$F$55*(1+$H$20)^(A61-$A$38) -> 1232612.7 | G61: =$G$55*(1+$H$20)^(A61-$A$38) -> 4843030 | H61: =$H$55*(1+$H$20)^(A61-$A$38) -> 10308861 | I61: =$I$55*(1+$H$26)^((A61-$A$38)) -> 9065554.1 | J61: =$J$55*(1+$H$26)^((A61-$A$38)) -> 6807232.6 | K61: =$K$55*(1+$H$20)^(A61-$A$38) -> 44169706 | L61: =$L$55*(1+$H$26)^(A61-$A$38) -> 7580992.7 | M61: =$M$55*(1+$H$22)^((A61-$A$38)) -> 49761633 | N61: kW
A62: 2029 | B62: =$B$55*($H$21+1)^(A62-$A$55) -> 13896240 | C62: =$C$55*(1+$H$20)^(A62-$A$55) -> 1181384.9 | D62: 0 | E62: =$E$55*(1+$H$25)^(A62-$A$38) -> 38335207 | F62: =$F$55*(1+$H$20)^(A62-$A$38) -> 1442156.9 | G62: =$G$55*(1+$H$20)^(A62-$A$38) -> 5666345.1 | H62: =$H$55*(1+$H$20)^(A62-$A$38) -> 12061368 | I62: =$I$55*(1+$H$26)^((A62-$A$38)) -> 9719754.1 | J62: =$J$55*(1+$H$26)^((A62-$A$38)) -> 7298464.7 | K62: =$K$55*(1+$H$20)^(A62-$A$38) -> 51678556 | L62: =$L$55*(1+$H$26)^(A62-$A$38) -> 8128061.9 | M62: =$M$55*(1+$H$22)^((A62-$A$38)) -> 54140657 | N62: kW
A63: 2030 | B63: =$B$55*($H$21+1)^(A63-$A$55) -> 14452089 | C63: =$C$55*(1+$H$20)^(A63-$A$55) -> 1382220.4 | D63: 0 | E63: =$E$55*(1+$H$25)^(A63-$A$38) -> 39516129 | F63: =$F$55*(1+$H$20)^(A63-$A$38) -> 1687323.5 | G63: =$G$55*(1+$H$20)^(A63-$A$38) -> 6629623.8 | H63: =$H$55*(1+$H$20)^(A63-$A$38) -> 14111800 | I63: =$I$55*(1+$H$26)^((A63-$A$38)) -> 10421163 | J63: =$J$55*(1+$H$26)^((A63-$A$38)) -> 7825145.7 | K63: =$K$55*(1+$H$20)^(A63-$A$38) -> 60463911 | L63: =$L$55*(1+$H$26)^(A63-$A$38) -> 8714609.4 | M63: =$M$55*(1+$H$22)^((A63-$A$38)) -> 58905035 | N63: kW
A64: 2031 | B64: =$B$55*($H$21+1)^(A64-$A$55) -> 15030173 | C64: =$C$55*(1+$H$20)^(A64-$A$55) -> 1617197.8 | D64: 0 | E64: =$E$55*(1+$H$25)^(A64-$A$38) -> 40733430 | F64: =$F$55*(1+$H$20)^(A64-$A$38) -> 1974168.5 | G64: =$G$55*(1+$H$20)^(A64-$A$38) -> 7756659.8 | H64: =$H$55*(1+$H$20)^(A64-$A$38) -> 16510806 | I64: =$I$55*(1+$H$26)^((A64-$A$38)) -> 11173188 | J64: =$J$55*(1+$H$26)^((A64-$A$38)) -> 8389833.8 | K64: =$K$55*(1+$H$20)^(A64-$A$38) -> 70742775 | L64: =$L$55*(1+$H$26)^(A64-$A$38) -> 9343484 | M64: =$M$55*(1+$H$22)^((A64-$A$38)) -> 64088678 | N64: kW
A65: 2032 | B65: =$B$55*($H$21+1)^(A65-$A$55) -> 15631380 | C65: =$C$55*(1+$H$20)^(A65-$A$55) -> 1892121.5 | D65: 0 | E65: =$E$55*(1+$H$25)^(A65-$A$38) -> 41988230 | F65: =$F$55*(1+$H$20)^(A65-$A$38) -> 2309777.2 | G65: =$G$55*(1+$H$20)^(A65-$A$38) -> 9075292 | H65: =$H$55*(1+$H$20)^(A65-$A$38) -> 19317643 | I65: =$I$55*(1+$H$26)^((A65-$A$38)) -> 11979482 | J65: =$J$55*(1+$H$26)^((A65-$A$38)) -> 8995271.6 | K65: =$K$55*(1+$H$20)^(A65-$A$38) -> 82769047 | L65: =$L$55*(1+$H$26)^(A65-$A$38) -> 10017740 | M65: =$M$55*(1+$H$22)^((A65-$A$38)) -> 69728482 | N65: kW
A66: 2033 | B66: =$B$55*($H$21+1)^(A66-$A$55) -> 16256635 | C66: =$C$55*(1+$H$20)^(A66-$A$55) -> 2213782.1 | D66: 0 | E66: =$E$55*(1+$H$25)^(A66-$A$38) -> 43281685 | F66: =$F$55*(1+$H$20)^(A66-$A$38) -> 2702439.3 | G66: =$G$55*(1+$H$20)^(A66-$A$38) -> 10618092 | H66: =$H$55*(1+$H$20)^(A66-$A$38) -> 22601643 | I66: =$I$55*(1+$H$26)^((A66-$A$38)) -> 12843961 | J66: =$J$55*(1+$H$26)^((A66-$A$38)) -> 9644399.8 | K66: =$K$55*(1+$H$20)^(A66-$A$38) -> 96839785 | L66: =$L$55*(1+$H$26)^(A66-$A$38) -> 10740653 | M66: =$M$55*(1+$H$22)^((A66-$A$38)) -> 75864588 | N66: kW
A67: 2034 | B67: =$B$55*($H$21+1)^(A67-$A$55) -> 16906900 | C67: =$C$55*(1+$H$20)^(A67-$A$55) -> 2590125.1 | D67: 0 | E67: =$E$55*(1+$H$25)^(A67-$A$38) -> 44614984 | F67: =$F$55*(1+$H$20)^(A67-$A$38) -> 3161854 | G67: =$G$55*(1+$H$20)^(A67-$A$38) -> 12423167 | H67: =$H$55*(1+$H$20)^(A67-$A$38) -> 26443922 | I67: =$I$55*(1+$H$26)^((A67-$A$38)) -> 13770823 | J67: =$J$55*(1+$H$26)^((A67-$A$38)) -> 10340371 | K67: =$K$55*(1+$H$20)^(A67-$A$38) -> 1.1330255e+08 | L67: =$L$55*(1+$H$26)^(A67-$A$38) -> 11515734 | M67: =$M$55*(1+$H$22)^((A67-$A$38)) -> 82540672
A68: 2035 | B68: =$B$55*($H$21+1)^(A68-$A$55) -> 17583176 | C68: =$C$55*(1+$H$20)^(A68-$A$55) -> 3030446.3 | D68: 0 | E68: =$E$55*(1+$H$25)^(A68-$A$38) -> 45989357 | F68: =$F$55*(1+$H$20)^(A68-$A$38) -> 3699369.2 | G68: =$G$55*(1+$H$20)^(A68-$A$38) -> 14535106 | H68: =$H$55*(1+$H$20)^(A68-$A$38) -> 30939389 | I68: =$I$55*(1+$H$26)^((A68-$A$38)) -> 14764570 | J68: =$J$55*(1+$H$26)^((A68-$A$38)) -> 11086566 | K68: =$K$55*(1+$H$20)^(A68-$A$38) -> 1.3256398e+08 | L68: =$L$55*(1+$H$26)^(A68-$A$38) -> 12346747 | M68: =$M$55*(1+$H$22)^((A68-$A$38)) -> 89804251 | N68: =SUM(B68:M68) -> 3.7634296e+08 | O68: validated with IEA
A69: 2036 | B69: =$B$55*($H$21+1)^(A69-$A$55) -> 18286503 | C69: =$C$55*(1+$H$20)^(A69-$A$55) -> 3545622.2 | D69: 1 | E69: =$E$55*(1+$H$25)^(A69-$A$38) -> 47406066 | F69: =$F$55*(1+$H$20)^(A69-$A$38) -> 4328261.9 | G69: =$G$55*(1+$H$20)^(A69-$A$38) -> 17006074 | H69: =$H$55*(1+$H$20)^(A69-$A$38) -> 36199085 | I69: =$I$55*(1+$H$26)^((A69-$A$38)) -> 15830030 | J69: =$J$55*(1+$H$26)^((A69-$A$38)) -> 11886609 | K69: =$K$55*(1+$H$20)^(A69-$A$38) -> 1.5509986e+08 | L69: =$L$55*(1+$H$26)^(A69-$A$38) -> 13237728 | M69: =$M$55*(1+$H$22)^((A69-$A$38)) -> 97707025
B70: HEX | C70: Com | E70: HP | N70: share us | O70: sahre in prodcution usa currently
B71: 164.40808 | C71: 135.99284 | D71: 139 | E71: =SUM(B55:M55)/10^6 -> 111 | F71: =IF(OR(B71<E71,C71<E71,D71<E71),"problem", "good") -> good | N71: =M68/N68 -> 0.23862344 | O71: =34/100 -> 0.34
B72: 177.11144 | C72: 150.30156 | D72: 147.66088 | E72: =SUM(B56:M56)/10^6 -> 120.21156 | F72: =IF(OR(B72<E72,C72<E72,D72<E72),"problem", "good") -> good | J72: =G55/10^6 -> 1.888 | N72: need 1400 GW in 2050 in APS scnarion in china
B73: 190.96784 | C73: 166.39187 | D73: 167.25204 | E73: =SUM(B57:M57)/10^6 -> 130.47576 | F73: =IF(OR(B73<E73,C73<E73,D73<E73),"problem", "good") -> good | I73: =4/37 -> 0.10810811
B74: 206.10541 | C74: 184.51452 | D74: 177.70631 | E74: =SUM(B58:M58)/10^6 -> 141.93834 | F74: =IF(OR(B74<E74,C74<E74,D74<E74),"problem", "good") -> good
B75: 222.66978 | C75: 204.95851 | D75: 189.1256 | E75: =SUM(B59:M59)/10^6 -> 154.76735 | F75: =IF(OR(B75<E75,C75<E75,D75<E75),"problem", "good") -> good
B76: 240.82684 | C76: 228.05717 | D76: 201.57293 | E76: =SUM(B60:M60)/10^6 -> 169.15678 | F76: =IF(OR(B76<E76,C76<E76,D76<E76),"problem", "good") -> good
B77: 260.76604 | C77: 254.19532 | D77: 215.11762 | E77: =SUM(B61:M61)/10^6 -> 185.3307 | F77: =IF(OR(B77<E77,C77<E77,D77<E77),"problem", "good") -> good
B78: 282.70421 | C78: 283.81758 | D78: 229.83563 | E78: =SUM(B62:M62)/10^6 -> 203.54819 | F78: =IF(OR(B78<E78,C78<E78,D78<E78),"problem", "good") -> good
B79: 306.89013 | C79: 317.43802 | D79: 245.81007 | E79: =SUM(B63:M63)/10^6 -> 224.10905 | F79: =IF(OR(B79<E79,C79<E79,D79<E79),"problem", "good") -> good | J79: AUS | K79: AUT | L79: BRA | M79: CHN | N79: CZE | O79: DEU | P79: ITA | Q79: JPN | R79: KOR | S79: ROE | T79: ROW | U79: USA
B80: 333.60982 | C80: 355.65146 | D80: 263.13162 | E80: =SUM(B64:M64)/10^6 -> 247.3604 | F80: =IF(OR(B80<E80,C80<E80,D80<E80),"problem", "good") -> good | J80: =B55/10^6 -> 10.56 | K80: =C55/10^6 -> 0.393632 | L80: =D55/10^6 -> 0 | M80: =E55/10^6 -> 31 | N80: =F55/10^6 -> 0.48052 | O80: =G55/10^6 -> 1.888 | P80: =H55/10^6 -> 4.018792 | Q80: =I55/10^6 -> 5.968 | ... U80: =M55/10^6 -> 30
B81: 363.19284 | C81: 399.14666 | D81: 281.89912 | E81: =SUM(B65:M65)/10^6 -> 273.70447 | F81: =IF(OR(B81<E81,C81<E81,D81<E81),"problem", "good") -> good | J81: =B56/10^6 -> 10.9824 | K81: =C56/10^6 -> 0.46054944 | L81: =D56/10^6 -> 0 | M81: =E56/10^6 -> 31.95496 | N81: =F56/10^6 -> 0.5622084 | O81: =G56/10^6 -> 2.20896 | P81: =H56/10^6 -> 4.7019866 | Q81: =I56/10^6 -> 6.3986704 | ... U81: =M56/10^6 -> 32.64
B82: 396.01969 | C82: 448.72167 | D82: 302.22008 | E82: =SUM(B66:M66)/10^6 -> 303.60766 | F82: =IF(OR(B82<E82,C82<E82,D82<E82),"problem", "good") -> problem | J82: =B57/10^6 -> 11.421696 | K82: =C57/10^6 -> 0.53884284 | L82: =D57/10^6 -> 0 | M82: =E57/10^6 -> 32.939338 | N82: =F57/10^6 -> 0.65778383 | O82: =G57/10^6 -> 2.5844832 | P82: =H57/10^6 -> 5.5013244 | Q82: =I57/10^6 -> 6.8604193 | ... U82: =M57/10^6 -> 35.51232
B83: 432.53059 | C83: 505.30173 | D83: 324.2114 | E83: =SUM(B67:M67)/10^6 -> 337.6111 | F83: =IF(OR(B83<E83,C83<E83,D83<E83),"problem", "good") -> problem | J83: =B58/10^6 -> 11.878564 | K83: =C58/10^6 -> 0.63044613 | L83: =D58/10^6 -> 0 | M83: =E58/10^6 -> 33.95404 | N83: =F58/10^6 -> 0.76960708 | O83: =G58/10^6 -> 3.0238453 | P83: =H58/10^6 -> 6.4365495 | Q83: =I58/10^6 -> 7.3554896 | ... U83: =M58/10^6 -> 38.637404
B84: 473.23578 | C84: 569.96027 | D84: 348 | E84: =SUM(B68:M68)/10^6 -> 376.34296 | F84: =IF(OR(B84<E84,C84<E84,D84<E84),"problem", "good") -> problem | J84: =B59/10^6 -> 12.353706 | K84: =C59/10^6 -> 0.73762197 | L84: =D59/10^6 -> 0 | M84: =E59/10^6 -> 35 | N84: =F59/10^6 -> 0.90044028 | O84: =G59/10^6 -> 3.5378991 | P84: =H59/10^6 -> 7.5307629 | Q84: =I59/10^6 -> 7.8862857 | ... U84: =M59/10^6 -> 42.037496
J85: =B60/10^6 -> 12.847855 | K85: =C60/10^6 -> 0.86301771 | L85: =D60/10^6 -> 0 | M85: =E60/10^6 -> 36.078181 | N85: =F60/10^6 -> 1.0535151 | O85: =G60/10^6 -> 4.1393419 | P85: =H60/10^6 -> 8.8109926 | Q85: =I60/10^6 -> 8.4553858 | ... U85: =M60/10^6 -> 45.736795
J86: =B61/10^6 -> 13.361769 | K86: =C61/10^6 -> 1.0097307 | L86: =D61/10^6 -> 0 | M86: =E61/10^6 -> 37.189575 | N86: =F61/10^6 -> 1.2326127 | O86: =G61/10^6 -> 4.84303 | P86: =H61/10^6 -> 10.308861 | Q86: =I61/10^6 -> 9.0655541 | ... U86: =M61/10^6 -> 49.761633
J87: =B62/10^6 -> 13.89624 | K87: =C62/10^6 -> 1.1813849 | L87: =D62/10^6 -> 0 | M87: =E62/10^6 -> 38.335207 | N87: =F62/10^6 -> 1.4421569 | O87: =G62/10^6 -> 5.6663451 | P87: =H62/10^6 -> 12.061368 | Q87: =I62/10^6 -> 9.7197541 | ... U87: =M62/10^6 -> 54.140657
J88: =B63/10^6 -> 14.452089 | K88: =C63/10^6 -> 1.3822204 | L88: =D63/10^6 -> 0 | M88: =E63/10^6 -> 39.516129 | N88: =F63/10^6 -> 1.6873235 | O88: =G63/10^6 -> 6.6296238 | P88: =H63/10^6 -> 14.1118 | Q88: =I63/10^6 -> 10.421163 | ... U88: =M63/10^6 -> 58.905035
B89: European demand | C89: Europea productio | E89: Pacifi cemdan | F89: Pacific production | J89: =B64/10^6 -> 15.030173 | K89: =C64/10^6 -> 1.6171978 | L89: =D64/10^6 -> 0 | M89: =E64/10^6 -> 40.73343 | N89: =F64/10^6 -> 1.9741685 | O89: =G64/10^6 -> 7.7566598 | P89: =H64/10^6 -> 16.510806 | Q89: =I64/10^6 -> 11.173188 | ... U89: =M64/10^6 -> 64.088678
B90: =SUM(C55,F55:H55,K55)/10^6 -> 24 | C90: =SUM('heat pump production'!C140,'heat pump production'!F140:H140,'heat pump production'!K140) -> 25 | D90: =B90*0.4 -> 9.6 | E90: =SUM(I55:J55,B55)/10^6 -> 21.009311 | F90: =SUM('heat pump production'!B140,'heat pump production'!I140:J140) -> 18.112 | J90: =B65/10^6 -> 15.63138 | K90: =C65/10^6 -> 1.8921215 | L90: =D65/10^6 -> 0 | M90: =E65/10^6 -> 41.98823 | N90: =F65/10^6 -> 2.3097772 | O90: =G65/10^6 -> 9.075292 | P90: =H65/10^6 -> 19.317643 | Q90: =I65/10^6 -> 11.979482 | ... U90: =M65/10^6 -> 69.728482
B91: =SUM(C56,F56:H56,K56)/10^6 -> 28.08 | C91: =SUM('heat pump production'!C141,'heat pump production'!F141:H141,'heat pump production'!K141) -> 26.456638 | D91: =B91*0.4 -> 11.232 | E91: =SUM(I56:J56,B56)/10^6 -> 22.185767 | F91: =SUM('heat pump production'!B141,'heat pump production'!I141:J141) -> 19.421877 | J91: =B66/10^6 -> 16.256635 | K91: =C66/10^6 -> 2.2137821 | L91: =D66/10^6 -> 0 | M91: =E66/10^6 -> 43.281685 | N91: =F66/10^6 -> 2.7024393 | O91: =G66/10^6 -> 10.618092 | P91: =H66/10^6 -> 22.601643 | Q91: =I66/10^6 -> 12.843961 | ... U91: =M66/10^6 -> 75.864588
B92: =SUM(C57,F57:H57,K57)/10^6 -> 32.8536 | C92: =SUM('heat pump production'!C142,'heat pump production'!F142:H142,'heat pump production'!K142) -> 27.998149 | D92: =B92*0.4 -> 13.14144 | E92: =SUM(I57:J57,B57)/10^6 -> 23.433535 | F92: =SUM('heat pump production'!B142,'heat pump production'!I142:J142) -> 20.828984 | J92: =B67/10^6 -> 16.9069 | K92: =C67/10^6 -> 2.5901251 | L92: =D67/10^6 -> 0 | M92: =E67/10^6 -> 44.614984 | N92: =F67/10^6 -> 3.161854 | O92: =G67/10^6 -> 12.423167 | P92: =H67/10^6 -> 26.443922 | Q92: =I67/10^6 -> 13.770823 | ... U92: =M67/10^6 -> 82.540672
B93: =SUM(C58,F58:H58,K58)/10^6 -> 38.438712 | C93: =SUM('heat pump production'!C143,'heat pump production'!F143:H143,'heat pump production'!K143) -> 29.629476 | D93: =B93*0.4 -> 15.375485 | E93: =SUM(I58:J58,B58)/10^6 -> 24.757216 | F93: =SUM('heat pump production'!B143,'heat pump production'!I143:J143) -> 22.340643 | J93: =B68/10^6 -> 17.583176 | K93: =C68/10^6 -> 3.0304463 | L93: =D68/10^6 -> 0 | M93: =E68/10^6 -> 45.989357 | N93: =F68/10^6 -> 3.6993692 | O93: =G68/10^6 -> 14.535106 | P93: =H68/10^6 -> 30.939389 | Q93: =I68/10^6 -> 14.76457 | ... U93: =M68/10^6 -> 89.804251
B94: =SUM(C59,F59:H59,K59)/10^6 -> 44.973293 | C94: =SUM('heat pump production'!C144,'heat pump production'!F144:H144,'heat pump production'!K144) -> 31.355853 | D94: =B94*0.4 -> 17.989317 | E94: =SUM(I59:J59,B59)/10^6 -> 26.161724 | F94: =SUM('heat pump production'!B144,'heat pump production'!I144:J144) -> 23.964732
B95: =SUM(C60,F60:H60,K60)/10^6 -> 52.618753 | C95: =SUM('heat pump production'!C145,'heat pump production'!F145:H145,'heat pump production'!K145) -> 33.182819 | D95: =B95*0.4 -> 21.047501 | E95: =SUM(I60:J60,B60)/10^6 -> 27.652304 | F95: =SUM('heat pump production'!B145,'heat pump production'!I145:J145) -> 25.70973
B96: =SUM(C61,F61:H61,K61)/10^6 -> 61.563941 | C96: =SUM('heat pump production'!C146,'heat pump production'!F146:H146,'heat pump production'!K146) -> 35.116234 | D96: =B96*0.4 -> 24.625576 | E96: =SUM(I61:J61,B61)/10^6 -> 29.234555 | F96: =SUM('heat pump production'!B146,'heat pump production'!I146:J146) -> 27.584756
B97: =SUM(C62,F62:H62,K62)/10^6 -> 72.029811 | C97: =SUM('heat pump production'!C147,'heat pump production'!F147:H147,'heat pump production'!K147) -> 37.1623 | D97: =B97*0.4 -> 28.811924 | E97: =SUM(I62:J62,B62)/10^6 -> 30.914458 | F97: =SUM('heat pump production'!B147,'heat pump production'!I147:J147) -> 29.599624
B98: =SUM(C63,F63:H63,K63)/10^6 -> 84.274879 | C98: =SUM('heat pump production'!C148,'heat pump production'!F148:H148,'heat pump production'!K148) -> 39.327581 | D98: =B98*0.4 -> 33.709951 | E98: =SUM(I63:J63,B63)/10^6 -> 32.698398 | F98: =SUM('heat pump production'!B148,'heat pump production'!I148:J148) -> 31.764896
B99: =SUM(C64,F64:H64,K64)/10^6 -> 98.601608 | C99: =SUM('heat pump production'!C149,'heat pump production'!F149:H149,'heat pump production'!K149) -> 41.619024 | D99: =B99*0.4 -> 39.440643 | E99: =SUM(I64:J64,B64)/10^6 -> 34.593195 | F99: =SUM('heat pump production'!B149,'heat pump production'!I149:J149) -> 34.091932
B100: =SUM(C65,F65:H65,K65)/10^6 -> 115.36388 | C100: =SUM('heat pump production'!C150,'heat pump production'!F150:H150,'heat pump production'!K150) -> 44.043979 | D100: =B100*0.4 -> 46.145553 | E100: =SUM(I65:J65,B65)/10^6 -> 36.606133 | F100: =SUM('heat pump production'!B150,'heat pump production'!I150:J150) -> 36.59296
B101: =SUM(C66,F66:H66,K66)/10^6 -> 134.97574 | C101: =SUM('heat pump production'!C151,'heat pump production'!F151:H151,'heat pump production'!K151) -> 46.610225 | D101: =B101*0.4 -> 53.990296 | E101: =SUM(I66:J66,B66)/10^6 -> 38.744995 | F101: =SUM('heat pump production'!B151,'heat pump production'!I151:J151) -> 39.281135
B102: =SUM(C67,F67:H67,K67)/10^6 -> 157.92162 | C102: =SUM('heat pump production'!C152,'heat pump production'!F152:H152,'heat pump production'!K152) -> 49.325994 | D102: =B102*0.4 -> 63.168647 | E102: =SUM(I67:J67,B67)/10^6 -> 41.018094 | F102: =SUM('heat pump production'!B152,'heat pump production'!I152:J152) -> 42.170616 | H102: =F102*0.4 -> 16.868246
B103: =SUM(C68,F68:H68,K68)/10^6 -> 184.76829 | C103: =SUM('heat pump production'!C153,'heat pump production'!F153:H153,'heat pump production'!K153) -> 52.2 | D103: =B103*0.4 -> 73.907317 | E103: =SUM(I68:J68,B68)/10^6 -> 43.434313 | F103: =SUM('heat pump production'!B153,'heat pump production'!I153:J153) -> 45.276635 | H103: =F103*0.4 -> 18.110654

Sheet Material demand scenarion
A1: Region | B1: Technology | C1: Material | D1: Scenario | E1: Unit | F1: 2020 | G1: 2030 | H1: 2050 | I1: Source | J1: for validation | K1: share on current production (2022) | M1: CO2 - reduction scneario
A2: EU | B2: Heat pumps | C2: Cu | D2: LDS | E2: t/yr | F2: 59658 | G2: 154180.03 | H2: 233490.3 | I2: Source Carrara et al. 2024 | M2: Country | N2: Copper emissions reudction
A3: EU | B3: Heat pumps | C3: Cu | D3: HDS | E3: t/yr | F3: 59658 | G3: 369093.99 | H3: 584188.6 | I3: Source Carrara et al. 2025 | N3: 2030 | O3: 2050
A4: EU | B4: Heat pumps | C4: Plastic | D4: LDS | E4: t/yr | F4: 0.003779 | G4: 0.9138384 | H4: 1.7557812 | I4: Source Carrara et al. 2026 | M4: Europe | N4: 30-40% | O4: 90 - 97$% | P4: https://internationalcopper.org/wp-content/uploads/2023/03/Copper_The-Pathway-to-Net-Zero_Focus-on-Europe_final.pdf
A5: EU | B5: Heat pumps | C5: Plastic | D5: HDS | E5: t/yr | F5: 0.003779 | G5: 2.1826816 | H5: 6.7155031 | I5: Source Carrara et al. 2027 | P5: https://internationalcopper.org/wp-content/uploads/2023/02/ICA-GlobalDecarbonization-202301-Final-singlepgs.pdf
A6: EU | B6: Heat pumps | C6: Steel | D6: LDS | E6: t/yr | F6: 0.019222 | G6: 0.9138384 | H6: 1.7557812 | I6: Source Carrara et al. 2028
A7: EU | B7: Heat pumps | C7: Steel | D7: HDS | E7: t/yr | F7: 0.019222 | G7: 2.1826816 | H7: 6.7155031 | I7: Source Carrara et al. 2029
A8: USA | B8: Heat pumps | C8: Cu | D8: LDS | E8: t/yr | F8: 125172 | G8: 133658.84 | H8: 151841.65 | I8: Source Carrara et al. 2030
A9: USA | B9: Heat pumps | C9: Cu | D9: HDS | E9: t/yr | F9: 125172 | G9: 232583.43 | H9: 312724.66 | I9: Source Carrara et al. 2031
A10: USA | B10: Heat pumps | C10: Plastic | D10: LDS | E10: t/yr | F10: 61902 | G10: 66099.042 | H10: 75091.089 | I10: Source Carrara et al. 2032
A11: USA | B11: Heat pumps | C11: Plastic | D11: HDS | E11: t/yr | F11: 61902 | G11: 115020.77 | H11: 154653.45 | I11: Source Carrara et al. 2033
A12: USA | B12: Heat pumps | C12: Steel | D12: LDS | E12: t/yr | F12: 536940 | G12: 573345.28 | H12: 651342.6 | I12: Source Carrara et al. 2034
A13: USA | B13: Heat pumps | C13: Steel | D13: HDS | E13: t/yr | F13: 536940 | G13: 997693.96 | H13: 1341469.2 | I13: Source Carrara et al. 2035
A14: China | B14: Heat pumps | C14: Cu | D14: LDS | E14: t/yr | F14: 71004 | G14: 81768.074 | H14: 85804.319 | I14: Source Carrara et al. 2036
A15: China | B15: Heat pumps | C15: Cu | D15: HDS | E15: t/yr | F15: 71004 | G15: 136862.39 | H15: 199519.86 | I15: Source Carrara et al. 2037
A16: China | B16: Heat pumps | C16: Plastic | D16: LDS | E16: t/yr | F16: 35114 | G16: 40437.217 | H16: 42433.284 | I16: Source Carrara et al. 2038
A17: China | B17: Heat pumps | C17: Plastic | D17: HDS | E17: t/yr | F17: 35114 | G17: 67683.315 | H17: 98669.658 | I17: Source Carrara et al. 2039
... A25: World | B25: Heat pumps | C25: Steel | D25: HDS | E25: t/yr | F25: 1411430 | G25: 3496762.4 | H25: 5062190.8 | I25: Source Carrara et al. 2047
A27: World | B27: 2020 | C27: 2030 | D27: max_laod
A28: Copper | B28: =F21/SUM('Refinement (material production'!L35:L46)/1000 -> 0.012647663 | C28: =conversion!G33/SUM('Refinement (material production'!L35:L46) -> 0.079804987 | D28: =C28*1.1 -> 0.087785486
A29: Steel | B29: =F19/SUM('Refinement (material production'!AB34:AB45)/10^6 -> 0.00016030526 | C29: =SUM(conversion!G32)/SUM('Refinement (material production'!$AB$34:$AB$45)/10^3 -> 0.0037002931 | D29: =C29*1.1 -> 0.0040703224
A30: Iron | C30: ='Material demand scenarion'!G25*1.6/SUM(mining!K63:K74)/10^6 -> 0.0021518538 | D30: =C30*1.1 -> 0.0023670392
A31: Nickel | C31: =conversion!G34/SUM(mining!K45:K56)*10^3 -> 0.069067486 | D31: =C31*1.1 -> 0.075974235
A32: Aluminium | C32: =conversion!G31/SUM('Refinement (material production'!B35:B46) -> 0.022214689 | D32: =C32*1.1 -> 0.024436157
A33: Bauxite | C33: =conversion!G31*4/SUM(mining!J3:J14) -> 0.015994576 | D33: =C33*1.1 -> 0.017594033

Sheet Allocation OPEX CAPEX
A1: Allocation OPEX HX and Compressor
A3: Material cost | F3: OPEX variable for Compressor and HEX manufacturing | J3: Assumptions | O3: Allocation based on weight principle | P3: kg/kW | Q3: %
A4: air - air CHN | B4: 77.765283 | C4: USD/kW | D4: IEA 2024 | J4: share material on total cost | K4: 0.9 | L4: see ENEL 2023 | O4: total weight input Hx | P4: =conversion!D31+conversion!D34 -> 4.643125 | Q4: =P4/$P$6 -> 0.34964936
A5: air - water CHN | B5: 90.624118 | C5: USD/kW | D5: IEA 2024 | J5: Allocation factor HX | K5: 0.34964936 | L5: based on weight | O5: total weight input compressor | P5: =conversion!D35+conversion!D37 -> 8.63625 | Q5: =P5/$P$6 -> 0.65035064
A6: air - air home EU | B6: 111.51972 | C6: USD/kW | D6: IEA 2024 | J6: Allocation Factor Compresso r | K6: 0.65035064 | L6: based on weight | O6: total weight input materials | P6: =SUM(P4:P5) -> 13.279375
A7: air - water EU | B7: 195.10215 | C7: USD/kW | D7: IEA 2024
A8: air - air JPN | B8: 68.121157 | C8: USD/kW | D8: IEA 2024 | J8: Regionalized cost factors | O8: Share Copper in Component/HP | P8: =conversion!B35/conversion!B33 -> 0.25808157 | U8: Australia | V8: 1.3895082 | W8: 1.0573199
A9: air - water JPN | B9: 195.10215 | C9: USD/kW | D9: IEA 2024 | J9: For Labour | K9: €/h | L9: Labour adjusment factor | M9: For countries in EU | O9: Share Steel in Component/HP | P9: =conversion!B37/conversion!B32 -> 0.3860823 | U9: Austria | V9: 1.4386267 | W9: 1.394268
A10: air air CHN | B10: 54.927706 | C10: USD/kW | D10: IEA 2024 | J10: Australia | K10: 38.19 | L10: =K10/$K$20 -> 1.3895082 | U10: Brazil | V10: 0.29034499 | W10: 0.59643687
A11: air air USA | B11: 178.12634 | C11: USD/kW | D11: IEA 2024 | J11: Austria | K11: 39.54 | L11: =K11/$K$20 -> 1.4386267 | M11: =K11/$K$19 -> 1.4326087 | O11: Cost Copper in HP total | P11: =16.7*0.84 -> 14.028 | Q11: €/kW | R11: ENEL | U11: China | V11: 0.48390831 | W11: 0.3020914
A12: air air India | B12: 56.947355 | C12: USD/kW | D12: IEA 2024 | J12: Brazil | K12: 7.98 | L12: =K12/$K$20 -> 0.29034499 | O12: Cost Steel in HP total | P12: =8.6*0.84 -> 7.224 | Q12: €/kW | R12: ENEL | U12: Czech republic | V12: 0.38967354 | W12: 1.390395
J13: China | K13: =K21/3 -> 13.3 | L13: =K13/$K$20 -> 0.48390831 | U13: Germany | V13: 1.5710647 | W13: 1.4136328
A14: average value for technologies | B14: Material Cost | C14: Only Component cost minus steel and copper | D14: share affected by labor | E14: total cost with adjusted labor cost | F14: Assumed allocation to Compressor | G14: Assumed allocation to HEX | J14: Czech republic | K14: 10.71 | L14: =K14/$K$20 -> 0.38967354 | M14: =K14/$K$19 -> 0.38804348 | U14: Italy | V14: 1.1821189 | W14: 1.7699458
A15: AUS | B15: =114.248442448875*0.84 -> 95.968692 | C15: =B15-$P$11-$P$12 -> 74.716692 | D15: =C15/$K$4-C15 -> 8.3018546 | E15: =D15*L10+C15 -> 86.252186 | F15: =E15*$K$6 -> 56.094164 | G15: =E15*$K$5 -> 30.158022 | H15: €/kW | J15: Germany | K15: 43.18 | L15: =K15/$K$20 -> 1.5710647 | M15: =K15/$K$19 -> 1.5644928 | O15: average enrgy cost per kW | U15: Japan | V15: 0.96272285 | W15: 0.85592564
A16: AUT | B16: =161.582737600832*0.84 -> 135.7295 | C16: =B16-$P$11-$P$12 -> 114.4775 | D16: =C16/$K$4-C16 -> 12.719722 | E16: =D16*L11+C16 -> 132.77643 | F16: =E16*$K$6 -> 86.351237 | G16: =E16*$K$5 -> 46.425194 | H16: €/kW | J16: Italy | K16: 32.49 | L16: =K16/$K$20 -> 1.1821189 | M16: =K16/$K$19 -> 1.1771739 | O16: eu | P16: 6.4 | Q16: €/kW | R16: EU Hydronic report | U16: Korea | V16: 0.83610624 | W16: 0.50735864
A17: BRA | B17: =114.248442448875*0.84 -> 95.968692 | C17: =B17-$P$11-$P$12 -> 74.716692 | D17: =C17/$K$4-C17 -> 8.3018546 | E17: =D17*L12+C17 -> 77.127094 | F17: =E17*$K$6 -> 50.159654 | G17: =E17*$K$5 -> 26.967439 | H17: €/kW | J17: Japan | K17: 26.46 | L17: =K17/$K$20 -> 0.96272285 | O17: china | P17: 4.6 | Q17: €/kW | R17: EU Hydronic report | U17: Rest of Europe | V17: 1.0042007 | W17: 1
A18: CHN | B18: =AVERAGE(B4:B5,B10)*0.84 -> 62.52879 | C18: =B18-$P$11-$P$12 -> 41.27679 | D18: =C18/$K$4-C18 -> 4.58631 | E18: =D18*L13+C18 -> 43.496143 | F18: =E18*$K$6 -> 28.287745 | G18: =E18*$K$5 -> 15.208399 | H18: €/kW | J18: Korea | K18: 22.98 | L18: =K18/$K$20 -> 0.83610624 | O18: usa | P18: 2.7 | Q18: €/kW | R18: EU Hydronic report | U18: Rest of World | V18: 1 | W18: 1
A19: CZE | B19: =161.582737600832*0.84 -> 135.7295 | C19: =B19-$P$11-$P$12 -> 114.4775 | D19: =C19/$K$4-C19 -> 12.719722 | E19: =D19*L14+C19 -> 119.43404 | F19: =E19*$K$6 -> 77.674003 | G19: =E19*$K$5 -> 41.760035 | H19: €/kW | J19: Rest of Europe | K19: 27.6 | L19: =K19/$K$20 -> 1.0042007 | P19: =AVERAGE(P16:P18) -> 4.5666667 | U19: USA | V19: 1.4517249 | W19: 0.71262587
A20: DEU | B20: =161.582737600832*0.84 -> 135.7295 | C20: =B20-$P$11-$P$12 -> 114.4775 | D20: =C20/$K$4-C20 -> 12.719722 | E20: =D20*L15+C20 -> 134.46101 | F20: =E20*$K$6 -> 87.446801 | G20: =E20*$K$5 -> 47.014205 | H20: €/kW | J20: Rest of World | K20: =AVERAGE(K10:K19,K21) -> 27.484545 | L20: =K20/$K$20 -> 1
A21: ITA | B21: =161.582737600832*0.84 -> 135.7295 | C21: =B21-$P$11-$P$12 -> 114.4775 | D21: =C21/$K$4-C21 -> 12.719722 | E21: =D21*L16+C21 -> 129.51372 | F21: =E21*$K$6 -> 84.229333 | G21: =E21*$K$5 -> 45.284391 | H21: €/kW | J21: USA | K21: 39.9 | L21: =K21/$K$20 -> 1.4517249
A22: JPN | B22: =AVERAGE(B8:B9) -> 131.61165 | C22: =B22-$P$11-$P$12 -> 110.35965 | D22: =C22/$K$4-C22 -> 12.262184 | E22: =D22*L17+C22 -> 122.16474 | F22: =E22*$K$6 -> 79.449915 | G22: =E22*$K$5 -> 42.714823 | H22: €/kW | L22: =MIN(L10:L21) -> 0.29034499 | M22: Brazil
A23: KOR | B23: =114.248442448875*0.84 -> 95.968692 | C23: =B23-$P$11-$P$12 -> 74.716692 | D23: =C23/$K$4-C23 -> 8.3018546 | E23: =D23*L18+C23 -> 81.657924 | F23: =E23*$K$6 -> 53.106283 | G23: =E23*$K$5 -> 28.551641 | H23: €/kW | L23: =MAX(L10:L22) -> 1.5710647 | M23: Germany | O23: Allocation for CAPEX
A24: ROE | B24: =AVERAGE((B6:B7))*0.84 -> 128.78119 | C24: =B24-$P$11-$P$12 -> 107.52919 | D24: =C24/$K$4-C24 -> 11.947688 | E24: =D24*L19+C24 -> 119.52706 | F24: =E24*$K$6 -> 77.734502 | G24: =E24*$K$5 -> 41.792562 | H24: €/kW | J24: For Energy Cost | K24: USD/kWh | L24: Energy adjusment factor | O24: Total OPEX | P24: Part of HP | Q24: Share compressor | R24: Share HEX
A25: ROW | B25: =AVERAGE(B4:B12)*0.84 -> 95.968692 | C25: =B25-$P$11-$P$12 -> 74.716692 | D25: =C25/$K$4-C25 -> 8.3018546 | E25: =D25*L20+C25 -> 83.018546 | F25: =E25*$K$6 -> 53.991165 | G25: =E25*$K$5 -> 29.027382 | H25: €/kW | J25: Australia | K25: 0.273 | L25: =K25/$K$35 -> 1.0573199 | O25: =E15+E54+B40 -> 143.56132 | P25: =(E54+B40)/O25 -> 0.39919621 | Q25: =F15/O25 -> 0.39073313 | R25: =G15/O25 -> 0.21007066
A26: USA | B26: =B11*0.84 -> 149.62612 | C26: =B26-$P$11-$P$12 -> 128.37412 | D26: =C26/$K$4-C26 -> 14.263792 | E26: =D26*L21+C26 -> 149.08123 | F26: =E26*$K$6 -> 96.95507 | G26: =E26*$K$5 -> 52.126155 | H26: €/kW | J26: Austria | K26: 0.36 | L26: =K26/$K$35 -> 1.394268 | O26: =E16+E55+B41 -> 218.57146 | P26: =(E55+B41)/O26 -> 0.39252621 | Q26: =F16/O26 -> 0.39507097 | R26: =G16/O26 -> 0.21240282
J27: Brazil | K27: 0.154 | L27: =K27/$K$35 -> 0.59643687 | O27: =E17+E56+B42 -> 129.07845 | P27: =(E56+B42)/O27 -> 0.40247892 | Q27: =F17/O27 -> 0.38859821 | R27: =G17/O27 -> 0.20892286
A28: FIXED OPEX | B28: only OPEX FIXED | C28: OPEX and labor cost | F28: OPEX fixed and variable For Heat Pump Assemble | J28: China | K28: 0.078 | L28: =K28/$K$35 -> 0.3020914 | O28: =E18+E57+B43 -> 78.923834 | P28: =(E57+B43)/O28 -> 0.44888456 | Q28: =F18/O28 -> 0.35841828 | R28: =G18/O28 -> 0.19269716
A29: air air CHN | B29: 13.784876 | C29: 29.539021 | D29: USD/kW | E29: IEA 2024 | F29: =C29-B29 -> 15.754144 | J29: Czech republic | K29: 0.359 | L29: =K29/$K$35 -> 1.390395 | O29: =E19+E58+B44 -> 201.99159 | P29: =(E58+B44)/O29 -> 0.40871776 | Q29: =F19/O29 -> 0.38454078 | R29: =G19/O29 -> 0.20674146
A30: air air CHN | B30: 11.815608 | C30: 11.815608 | D30: USD/kW | E30: IEA 2024 | F30: =C30-B30 -> 0 | J30: Germany | K30: 0.365 | L30: =K30/$K$35 -> 1.4136328 | O30: =E20+E59+B45 -> 220.76633 | P30: =(E59+B45)/O30 -> 0.39093517 | Q30: =F20/O30 -> 0.3961057 | R30: =G20/O30 -> 0.21295913
A31: air water CHN | B31: 15.754144 | C31: 29.539021 | D31: USD/kW | E31: IEA 2024 | F31: =C31-B31 -> 13.784876 | J31: Italy | K31: 0.457 | L31: =K31/$K$35 -> 1.7699458 | O31: =E21+E60+B46 -> 216.46251 | P31: =(E60+B46)/O31 -> 0.40168059 | Q31: =F21/O31 -> 0.38911741 | R31: =G21/O31 -> 0.209202
A32: air air EU | B32: 51.200969 | C32: 76.801454 | D32: USD/kW | E32: IEA 2024 | F32: =C32-B32 -> 25.600485 | J32: Japan | K32: 0.221 | L32: =K32/$K$35 -> 0.85592564 | O32: =E22+E61+B47 -> 182.2735 | P32: =(E61+B47)/O32 -> 0.32977235 | Q32: =F22/O32 -> 0.43588298 | R32: =G22/O32 -> 0.23434467
A33: air water EU | B33: 76.801454 | C33: 131.94096 | D33: USD/kW | E33: IEA 2024 | F33: =C33-B33 -> 55.139506 | J33: Korea | K33: 0.131 | L33: =K33/$K$35 -> 0.50735864 | O33: =E23+E62+B48 -> 134.61859 | P33: =(E62+B48)/O33 -> 0.39341272 | Q33: =F23/O33 -> 0.39449443 | R33: =G23/O33 -> 0.21209286
A34: air air USA | B34: 33.477557 | C34: 70.89365 | D34: USD/kW | E34: IEA 2024 | F34: =C34-B34 -> 37.416093 | J34: Rest of Europe | K34: =AVERAGE(K25:K33,K36) -> 0.2582 | L34: =K34/$K$35 -> 1 | O34: =E24+E63+B49 -> 201.98754 | P34: =(E63+B49)/O34 -> 0.40824536 | Q34: =F24/O34 -> 0.38484801 | R34: =G24/O34 -> 0.20690663
A35: air air JPN | B35: 17.723413 | C35: 37.416093 | D35: USD/kW | E35: IEA 2024 | F35: =C35-B35 -> 19.692681 | J35: Rest of World | K35: =AVERAGE(K25:K34,K36) -> 0.2582 | L35: =K35/$K$35 -> 1 | O35: =E25+E64+B50 -> 138.90811 | P35: =(E64+B50)/O35 -> 0.40234918 | Q35: =F25/O35 -> 0.38868259 | R35: =G25/O35 -> 0.20896823
A36: air water Jon | B36: 59.078042 | C36: 86.647794 | D36: USD/kW | E36: IEA 2024 | F36: =C36-B36 -> 27.569753 | J36: USA | K36: 0.184 | L36: =K36/$K$35 -> 0.71262587 | O36: =E26+E65+B51 -> 205.66164 | P36: =(E65+B51)/O36 -> 0.27511407 | Q36: =F26/O36 -> 0.47143002 | R36: =G26/O36 -> 0.2534559
A37: air air India | B37: 11.815608 | C37: 21.661949 | D37: USD/kW | E37: IEA 2024 | F37: =C37-B37 -> 9.8463403 | L37: 1 | M37: =MAX(L25:L36) -> 1.7699458
A39: average value for technologies | B39: FIXED OPEX | D39: total | G39: =G15/8760 -> 0.0034426966
A40: AUS | B40: =$B$50 -> 27.202156 | C40: €/kW | D40: =B40+E54 -> 57.309136 | E40: 57.309136 | G40: =G16/8760 -> 0.0052996797
A41: AUT | B41: =$B$49 -> 53.761018 | C41: €/kW | D41: =B41+E55 -> 85.795026 | E41: 85.795026 | G41: =G17/8760 -> 0.0030784748
A42: BRA | B42: =$B$50 -> 27.202156 | C42: €/kW | D42: =B42+E56 -> 51.951355 | E42: 51.951355 | G42: =G18/8760 -> 0.0017361186
A43: CHN | B43: =AVERAGE(B29:B31)*0.84 -> 11.579296 | C43: €/kW | D43: =B43+E57 -> 35.427691 | E43: 35.427691 | G43: =G19/8760 -> 0.0047671273
A44: CZE | B44: =$B$49 -> 53.761018 | C44: €/kW | D44: =B44+E58 -> 82.557551 | E44: 82.557551 | G44: =G20/8760 -> 0.0053669184 | K44: Bar4 | L44: 33.827893
A45: DEU | B45: =$B$49 -> 53.761018 | C45: €/kW | D45: =B45+E59 -> 86.305321 | E45: 86.305321 | G45: =G21/8760 -> 0.005169451 | K45: Bar5 | L45: 179.82196
A46: ITA | B46: =$B$49 -> 53.761018 | C46: €/kW | D46: =B46+E60 -> 86.948789 | E46: 86.948789 | G46: =G22/8760 -> 0.0048761213 | K46: Bar2 | L46: 8.9020772
A47: JPN | B47: =AVERAGE(B35:B36)*0.84 -> 32.256611 | C47: €/kW | D47: =B47+E61 -> 60.108761 | E47: 60.108761 | G47: =G23/8760 -> 0.0032593198 | K47: Bar3 | L47: 16.023739
A48: KOR | B48: =$B$50 -> 27.202156 | C48: €/kW | D48: =B48+E62 -> 52.960665 | E48: 52.960665 | G48: =G24/8760 -> 0.0047708404 | K48: CAPEX | L48: =L46 -> 8.9020772
A49: ROE | B49: =AVERAGE(B32:B33)*0.84 -> 53.761018 | C49: €/kW | D49: =B49+E63 -> 82.460476 | E49: 82.460476 | G49: =G25/8760 -> 0.0033136281 | K49: fixed OPEX | L49: =L47-L46 -> 7.1216617
A50: ROW | B50: =AVERAGE(B29:B37)*0.84 -> 27.202156 | C50: €/kW | D50: =B50+E64 -> 55.889563 | E50: 55.889563 | G50: =G26/8760 -> 0.0059504744 | K50: Labor cost | L50: =L44-L46 -> 24.925816
A51: USA | B51: =B34*0.84 -> 28.121148 | C51: €/kW | D51: =B51+E65 -> 56.580411 | E51: 56.580411 | K51: Material Cost | L51: =L45-L44 -> 145.99407
G52: 30.106979
A53: Variable OPEX | B53: total cost with adjusted labor cost | C53: Cost Electricty (adjusted) | D53: Include labor cost | E53: total cost with adjusted labor cost | G53: 32.034008
A54: AUS | B54: =SUM($P$11:$P$12) -> 21.252 | C54: =$P$19*L25 -> 4.8284276 | D54: =SUM(B54:C54)/$K$4-SUM(B54:C54) -> 2.8978253 | E54: =SUM(B54:C54)+D54*L10 -> 30.106979 | F54: €/kW | G54: 24.749199
A55: AUT | B55: =SUM($P$11:$P$12) -> 21.252 | C55: =$P$19*L26 -> 6.3671572 | D55: =SUM(B55:C55)/$K$4-SUM(B55:C55) -> 3.0687952 | E55: =SUM(B55:C55)+D55*L11 -> 32.034008 | F55: €/kW | G55: 23.848395
A56: BRA | B56: =SUM($P$11:$P$12) -> 21.252 | C56: =$P$19*L27 -> 2.7237284 | D56: =SUM(B56:C56)/$K$4-SUM(B56:C56) -> 2.6639698 | E56: =SUM(B56:C56)+D56*L12 -> 24.749199 | F56: €/kW | G56: 28.796533
A57: CHN | B57: =SUM($P$11:$P$12) -> 21.252 | C57: =$P$19*L28 -> 1.3795507 | D57: =SUM(B57:C57)/$K$4-SUM(B57:C57) -> 2.5146167 | E57: =SUM(B57:C57)+D57*L13 -> 23.848395 | F57: €/kW | G57: 32.544303
A58: CZE | B58: =SUM($P$11:$P$12) -> 21.252 | C58: =$P$19*L29 -> 6.3494707 | D58: =SUM(B58:C58)/$K$4-SUM(B58:C58) -> 3.0668301 | E58: =SUM(B58:C58)+D58*L14 -> 28.796533 | F58: €/kW | G58: 33.187771
A59: DEU | B59: =SUM($P$11:$P$12) -> 21.252 | C59: =$P$19*L30 -> 6.45559 | D59: =SUM(B59:C59)/$K$4-SUM(B59:C59) -> 3.0786211 | E59: =SUM(B59:C59)+D59*L15 -> 32.544303 | F59: €/kW | G59: 27.85215
A60: ITA | B60: =SUM($P$11:$P$12) -> 21.252 | C60: =$P$19*L31 -> 8.0827524 | D60: =SUM(B60:C60)/$K$4-SUM(B60:C60) -> 3.2594169 | E60: =SUM(B60:C60)+D60*L16 -> 33.187771 | F60: €/kW | G60: 25.758508
A61: JPN | B61: =SUM($P$11:$P$12) -> 21.252 | C61: =$P$19*L32 -> 3.9087271 | D61: =SUM(B61:C61)/$K$4-SUM(B61:C61) -> 2.7956363 | E61: =SUM(B61:C61)+D61*L17 -> 27.85215 | F61: €/kW | G61: 28.699458
A62: KOR | B62: =SUM($P$11:$P$12) -> 21.252 | C62: =$P$19*L33 -> 2.3169378 | D62: =SUM(B62:C62)/$K$4-SUM(B62:C62) -> 2.6187709 | E62: =SUM(B62:C62)+D62*L18 -> 25.758508 | F62: €/kW | G62: 28.687407
A63: ROE | B63: =SUM($P$11:$P$12) -> 21.252 | C63: =$P$19*L34 -> 4.5666667 | D63: =SUM(B63:C63)/$K$4-SUM(B63:C63) -> 2.8687407 | E63: =SUM(B63:C63)+D63*L19 -> 28.699458 | F63: €/kW | G63: 28.459263
A64: ROW | B64: =SUM($P$11:$P$12) -> 21.252 | C64: =$P$19*L35 -> 4.5666667 | D64: =SUM(B64:C64)/$K$4-SUM(B64:C64) -> 2.8687407 | E64: =SUM(B64:C64)+D64*L20 -> 28.687407 | F64: €/kW
A65: USA | B65: =SUM($P$11:$P$12) -> 21.252 | C65: =$P$19*L36 -> 3.2543248 | D65: =SUM(B65:C65)/$K$4-SUM(B65:C65) -> 2.722925 | E65: =SUM(B65:C65)+D65*L21 -> 28.459263 | F65: €/kW
A67: CAPEX | B67: CAPEX HP | D67: Share OPEX to CAPEX | E67: Compressor | F67: HEX | G67: Assumption use the same ratio OPEX/CAPEX from HP to HEX and compressor s
A68: AUS | B68: 113.4 | C68: €/kW | D68: =(E54+B40)/B68 -> 0.50537157 | E68: =F15/$D68 -> 110.99589 | F68: =G15/$D68 -> 59.674948
A69: AUT | B69: 142.8 | C69: €/kW | D69: =(E55+B41)/B69 -> 0.6008055 | E69: =F16/$D69 -> 143.72578 | F69: =G16/$D69 -> 77.271587
A70: BRA | B70: 113.4 | C70: €/kW | D70: =(E56+B42)/B70 -> 0.45812482 | E70: =F17/$D70 -> 109.48906 | F70: =G17/$D70 -> 58.864829
A71: CHN | B71: 50.4 | C71: €/kW | D71: =(E57+B43)/B71 -> 0.70293037 | E71: =F18/$D71 -> 40.242598 | F71: =G18/$D71 -> 21.635711
A72: CZE | B72: 142.8 | C72: €/kW | D72: =(E58+B44)/B72 -> 0.57813411 | E72: =F19/$D72 -> 134.35292 | F72: =G19/$D72 -> 72.232436
A73: DEU | B73: 142.8 | C73: €/kW | D73: =(E59+B45)/B73 -> 0.604379 | E73: =F20/$D73 -> 144.68868 | F73: =G20/$D73 -> 77.789277
A74: ITA | B74: 142.8 | C74: €/kW | D74: =(E60+B46)/B74 -> 0.60888507 | E74: =F21/$D74 -> 138.33371 | F74: =G21/$D74 -> 74.372641
A75: JPN | B75: 113.4 | C75: €/kW | D75: =(E61+B47)/B75 -> 0.53005962 | E75: =F22/$D75 -> 149.88864 | F75: =G22/$D75 -> 80.58494
A76: KOR | B76: 113.4 | C76: €/kW | D76: =(E62+B48)/B76 -> 0.46702526 | E76: =F23/$D76 -> 113.7118 | F76: =G23/$D76 -> 61.135111
A77: ROE | B77: 142.8 | C77: €/kW | D77: =(E63+B49)/B77 -> 0.57745431 | E77: =F24/$D77 -> 134.61585 | F77: =G24/$D77 -> 72.373798
A78: ROW | B78: 113.4 | C78: €/kW | D78: =(E64+B50)/B78 -> 0.49285329 | E78: =F25/$D78 -> 109.54815 | F78: =G25/$D78 -> 58.896597
A79: USA | B79: 147 | C79: €/kW | D79: =(E65+B51)/B79 -> 0.38490075 | E79: =F26/$D79 -> 251.89629 | F79: =G26/$D79 -> 135.42752
B82: =B68/12.94 -> 8.763524 | E82: =0.5*10^6*E78 -> 54774073
E83: =(225+242+170)*1000 -> 637000 | F83: =E82/8760 -> 6252.7481

Sheet refrigerants
A1: Refrigerant type | B1: GWP | C1: unit | D1: import limit | F1: year | G1: source | H1: notes
A2: HFC-134a | B2: 1430 | C2: kgCo2-eq /kg | F2: 2030 | G2: https://eur-lex.europa.eu/legal-content/EN/TXT/?uri=uriserv:OJ.L_.2014.150.01.0195.01.ENG | H2: global phase ot of HFC ubntil 2030 (montreal protocol), he phase-down is being managed through an annual import quota that will gradually reduce over 18 years. The end point of the phase-down, 15% of the baseline level, will be reached on 1 January 2036.
A3: R410A | B3: 2088 | C3: kgCo2-eq /kg | G3: https://www.infraserv.com/de/leistungen/facility-management/expertenwissen/f-gase/kaeltemittel/spezifische-kaeltemittel/r-410a.html
A4: R 32 | B4: 675 | C4: kgCo2-eq /kg | G4: https://www.infraserv.com/de/leistungen/facility-management/expertenwissen/f-gase/kaeltemittel/spezifische-kaeltemittel/r-410a.html
A5: R 290 | B5: 3 | C5: kgCo2-eq /kg | G5: https://www.infraserv.com/de/leistungen/facility-management/expertenwissen/f-gase/kaeltemittel/spezifische-kaeltemittel/r-410a.html | H5: Propane
A6: CO2 | B6: 1 | C6: kgCo2-eq /kg
A8: Mittelwert between most common types | B8: =AVERAGE(B2:B4) -> 1397.6667
A9: Country | B9: Production | C9: Capacity | D9: Units | E9: converted to t | F9: type | G9: year | H9: source | I9: note | M9: 2022 Calculated HFC Production | O9: Source | P9: https://www.epa.gov/climate-hfcs-reduction/2022-hfc-data-hub/expanded-hfc-data#2022%20Calc%20Prod
A10: China | B10: 811000 | C10: =1683*10^6 -> 1683000000 | D10: t | E10: =B10 -> 811000 | F10: HFC | G10: 2020 | H10: https://chineseclimatepolicy.oxfordenergy.org/book-content/domestic-policies/hfcs/#:~:text=Capacity%20utilization%20in%20the%20Chinese,actual%20production%20of%20811%2C000%20tonnes. | I10: global share 70% | M10: USA: | N10: Chemical | O10: Total Production (MT) | P10: Production for Feedstock (MT) | Q10: Destruction (MT) | R10: Calculated Production (MT) | S10: Calculated Production (MTCO2e)
A11: China | B11: 1581392661 | D11: tCO2-eq | E11: =B11/$T$23 -> 1178727.7 | G11: 2023 | H11: https://ozone.unep.org/countries/profile/chn
A12: Australia | B12: 0 | C12: 0 | F12: HFC | G12: 2023 | H12: https://ozone.unep.org/countries/profile/aus | I12: negative production??? | N12: HFC-32 | O12: 17762 | P12: 0 | Q12: 17.7 | R12: 17744.3 | S12: 11977388
A13: USA | B13: =R16/1.103 -> 55645.422 | D13: t | F13: HFC-134a | G13: 2022 | H13: https://www.epa.gov/climate-hfcs-reduction/2022-hfc-data-hub/expanded-hfc-data#2022%20Calc%20Prod | N13: HFC-41 | O13: 25.4 | P13: 1.6 | Q13: 1.8 | R13: 22 | S13: 2027.6
A14: USA | B14: =R23 -> 133907.2 | D14: t | E14: 133907.2 | F14: HFC | G14: 2022 | H14: https://www.epa.gov/climate-hfcs-reduction/2022-hfc-data-hub/expanded-hfc-data#2022%20Calc%20Prod | N14: HFC-125 | O14: 19223.1 | P14: 0 | Q14: 47.4 | R14: 19175.7 | S14: 67115021
A15: France | B15: 15518000 | D15: MT CO2-eq | E15: =B15/$T$23 -> 11566.702 | F15: HFC | G15: 2022 | H15: Global Overview of HCFC, HFC, and HFO/HCFO Production, 2022 | N15: HFC-134 | O15: 516.1 | P15: 0 | Q15: 1.8 | R15: 514.3 | S15: 565688.2
A16: Germany | B16: 6950000 | D16: MT CO2-eq | E16: =B16/$T$23 -> 5180.3439 | F16: HFC | G16: 2022 | H16: Global Overview of HCFC, HFC, and HFO/HCFO Production, 2023 | N16: HFC-134a | O16: 61397.7 | P16: 0 | Q16: 20.8 | R16: 61376.9 | S16: 87768927 | V16: https://wedocs.unep.org/bitstream/handle/20.500.11822/33094/CoolRep.pdf?sequence=1&isAllowed=y
A17: Japan | B17: 28965000 | D17: MT CO2-eq | E17: =B17/$T$23 -> 21589.735 | F17: HFC | G17: 2022 | H17: Global Overview of HCFC, HFC, and HFO/HCFO Production, 2024 | N17: HFC-143a | O17: 42.8 | P17: 0 | Q17: 48.8 | R17: -6.1 | S17: -27136.9
A18: South Korea | B18: 2769080 | D18: MT CO2-eq | E18: =B18/$T$23 -> 2063.9981 | F18: HFC | G18: 2023 | H18: https://ozone.unep.org/countries/profile/kor | N18: HFC-152a | O18: 33453.6 | P18: 3797.9 | Q18: 0.8 | R18: 29654.9 | S18: 3677202.6
A19: Brazil | B19: 0 | E19: =B19/$T$23 -> 0 | F19: HFC | G19: 2023 | H19: https://ozone.unep.org/countries/profile/kor | N19: HFC-227ea | O19: 1365.3 | P19: 0 | Q19: 40.6 | R19: 1324.7 | S19: 4265637.5
A20: Italy | B20: 0 | E20: 0 | F20: HFC | G20: 2023 | H20: https://ozone.unep.org/countries/profile/ita | N20: HFC-236ea | O20: 32.6 | P20: 0 | Q20: 0 | R20: 32.6 | S20: 44673.4
A21: Czech Republic | B21: 0 | E21: 0 | F21: HFC | G21: 2023 | H21: https://ozone.unep.org/countries/profile/cze | N21: HFC-245fa | O21: 17416.2 | P21: 13350.2 | Q21: 3.3 | R21: 4062.7 | S21: 4184584.1
A22: Austria | B22: 0 | E22: 0 | F22: HFC | G22: 2024 | H22: https://ozone.unep.org/countries/profile/aut | M22: Data current as of: | N22: HFC-23 | O22: 745.2 | P22: 0 | Q22: 740 | R22: 5.2 | S22: 77196.8 | T22: converison rat
A23: Gobal | B23: =461*10^6 -> 461000000 | D23: MT CO2-eq | E23: =B23/$T$23 -> 343617.05 | F23: HFC | G23: 2019 | M23: 45441 | N23: Total | O23: =SUM(O12:O22) -> 151980 | P23: =SUM(P12:P22) -> 17149.7 | Q23: =SUM(Q12:Q22) -> 923 | R23: =SUM(R12:R22) -> 133907.2 | S23: =SUM(S12:S22) -> 1.7965121e+08 | T23: =S23/R23 -> 1341.6098
A24: Scenario high GWP refrigerant | E24: =E10/0.7 -> 1158571.4
B25: import availability | L25: https://www.dcceew.gov.au/sites/default/files/documents/heat-pumps-emerging-trends-in-australian-market.pdf
A26: AUS | B26: 0 | C26: t
A27: AUT | B27: 0 | C27: t
A28: BRA | B28: 0 | C28: t
A29: CHN | B29: =E10 -> 811000 | C29: t
A30: CZE | B30: 0 | C30: t
A31: DEU | B31: =E16 -> 5180.3439 | C31: t
A32: ITA | B32: 0 | C32: t
A33: JPN | B33: =E17 -> 21589.735 | C33: t
A34: KOR | B34: =E18 -> 2063.9981 | C34: t
A35: ROE | B35: =E15 -> 11566.702 | C35: t
A36: ROW | B36: =E24 -> 1158571.4 | C36: t
A37: USA | B37: =E14 -> 133907.2 | C37: t
A39: Productio | B39: Carbon foortprint | C39: source
A40: Europe | B40: 1.85 | C40: Ecoinvent
A41: World | B41: 1.89 | C41: Ecoinvent

Sheet mining
A1: Bauxite | B1: year | C1: Production | D1: Reserve | E1: unit | F1: Source
A2: United States | B2: 2021 and 2022 | C2: 96 | D2: 20000 | E2: kt | F2: USGS, 2023 and https://www.statista.com/statistics/1038450/us-bauxite-production/ | I2: Bauxite | J2: Production | K2: Reserves | L2: unit | M2: Source | N2: year | O2: Carbon Footprint | R2: time until new mine openinng | T2: 17 | U2: y | V2: IEA, Technology Perspective 2023
A3: Australia | B3: 2022 | C3: 100000 | D3: 5100000 | E3: kt | F3: USGS, 2023 | I3: United States | J3: 96 | K3: 20000 | L3: kt | M3: USGS, 2023 | N3: 2022 | R3: Global Copper investemnt | S3: =AVERAGE(360,450)*2/3 -> 270 | T3: Bio USD | U3: Technology perpsective, 2023
A4: Brazil | B4: 2022 | C4: 33000 | D4: 2700000 | E4: kt | F4: USGS, 2023 | I4: Australia | J4: 100000 | K4: 5100000 | L4: kt | M4: USGS, 2023 | N4: 2022 | R4: Global nickel investment | S4: =AVERAGE(360,450)*1/3 -> 135 | T4: Bio USD | U4: Technology perpsective, 2024
A5: Canada | B5: 2022 | E5: kt | F5: USGS, 2023 | I5: Brazil | J5: 33000 | K5: 2700000 | L5: kt | M5: USGS, 2023 | N5: 2022 | R5: Anticipated investemnt | S5: 180 - 220 | T5: Bio USD | U5: Technology perpsective, 2025
A6: China | B6: 2022 | C6: 90000 | D6: 710000 | E6: kt | F6: USGS, 2023 | I6: China | J6: 90000 | K6: 710000 | L6: kt
A7: Germany | B7: 2022 | E7: kt | F7: USGS, 2023 | I7: Germany | J7: 0 | K7: 0 | L7: kt
A8: Guinea | B8: 2022 | C8: 86000 | D8: 7400000 | E8: kt | F8: USGS, 2023 | I8: Austria | J8: 0 | K8: 0 | L8: kt
A9: India | B9: 2022 | C9: 17000 | D9: 660000 | E9: kt | F9: USGS, 2023 | I9: Italy | J9: 0 | K9: 0 | L9: kt
A10: Indonesia | B10: 2022 | C10: 21000 | D10: 1000000 | E10: kt | F10: USGS, 2023 | I10: Czech Republic | J10: 0 | K10: 0 | L10: kt
A11: Ireland | B11: 2022 | E11: kt | F11: USGS, 2023 | I11: Japan | J11: 0 | K11: 0 | L11: kt
A12: Jamaica | B12: 2022 | C12: 3900 | D12: 2000000 | E12: kt | F12: USGS, 2023 | I12: South Korea | J12: 0 | K12: 0 | L12: kt
A13: Kazakhstan | B13: 2022 | C13: 4400 | D13: 160000 | E13: kt | F13: USGS, 2023 | I13: RoE and central eurasia | J13: =C21-SUM(J7:J10) -> 13283 | K13: =D21-SUM(K7:K10) -> 250000 | L13: kt
A14: Russia | B14: 2022 | C14: 5000 | D14: 500000 | E14: kt | F14: USGS, 2023 | I14: ROW | J14: =C20-SUM(J3:J13) -> 143621 | K14: =D20-SUM(K3:K13) -> 22220000 | L14: kt | O14: 4.9 | P14: https://www.iea.org/data-and-statistics/charts/average-ghg-emissions-intensity-for-production-of-selected-commodities
A15: Saudi Arabia | B15: 2022 | C15: 4800 | D15: 180000 | E15: kt | F15: USGS, 2023
A16: Spain | B16: 2022 | E16: kt | F16: USGS, 2023 | I16: conversion
A17: Ukraine | B17: 2022 | E17: kt | F17: USGS, 2023 | I17: grade depostits | J17: 0.5 | K17: https://www.ga.gov.au/scientific-topics/minerals/mineral-resources-and-advice/australian-resource-reviews/bauxite
A18: Vietnam | B18: 2022 | C18: 3800 | D18: 5800000 | E18: kt | F18: USGS, 2023 | I18: CO2 | J18: 0.1 | K18: t Co2 / t Bauxite | L18: https://bauxite.world-aluminium.org/mining/responsible-sourcing/#:~:text=Bauxite%20mining%20emits%2C%20on%20average,2%20per%20tonne%20of%20bauxite.
A19: Other countries | B19: 2022 | C19: 8900 | D19: 5100000 | E19: kt | F19: USGS, 2023 | I19: price | J19: 47 | K19: €/t | L19: https://scrreen.eu/wp-content/uploads/2023/01/ALUMINIUM-AND-BAUXITE_CRM_2020_Factsheets_critical_Final.pdf
A20: world total | B20: 2022 | C20: 380000 | D20: 31000000 | E20: kt | F20: USGS, 2023 | I20: Or assume: Buaxite reserves are the total reserves of Bauxite and thus the conversion factor is 1
A21: europe total | B21: 2019 | C21: 13283 | D21: 250000 | E21: kt | F21: USGS, 2020 and 2018
A23: Copper | B23: year | C23: Production | D23: Reserve | E23: unit | F23: Source | G23: Note | I23: copper ore | J23: Production | K23: Reserves | L23: unit | M23: Source | N23: year | O23: Carbon Footprint | P23: unit | Q23: Source | R23: CAPEX | T23: Source | U23: Share of energ | V23: Sahre of labor on total cost | W23: Ajusted OPEX with labor and energy cost
A24: United States | B24: 2022 | C24: 1300 | D24: 44000 | E24: kt | F24: USGS, 2023 | G24: recoverable copper content | I24: Australia | J24: 830 | K24: 97000 | L24: kt | M24: USGS | N24: 2022 | O24: 1.34 | Q24: Ecoinvent 3.10 | U24: 0.3 | V24: 0.33 | W24: =$J$37*V24*'Allocation OPEX CAPEX'!L10 +'Allocation OPEX CAPEX'!L25*mining!U24*$J$37+(1-SUM(mining!U24:V24))*mining!$J$37 -> 3.497899 | X24: =W24/8760 -> 0.00039930354
A25: Australia | B25: 2022 | C25: 830 | D25: 97000 | E25: kt | F25: USGS, 2023 | G25: recoverable copper content | I25: Austria | J25: 0 | K25: 0 | L25: kt | M25: USGS | N25: 2022 | O25: 1.2 | P25: t CO2 / t Cu | U25: 0.3 | V25: =$V$33 -> 0.2975 | W25: =$J$37*V25*'Allocation OPEX CAPEX'!L11 +'Allocation OPEX CAPEX'!L26*mining!U25*$J$37+(1-SUM(mining!U25:V25))*mining!$J$37 -> 3.8124722 | X25: =W25/8760 -> 0.00043521372
A26: Canada | B26: 2022 | C26: 530 | D26: 7600 | E26: kt | F26: USGS, 2023 | G26: recoverable copper content | I26: Brazil | J26: 381 | K26: 0 | L26: kt | M26: USGS | N26: 2022 | O26: 1.2 | P26: t CO2 / t Cu | R26: 13500 | S26: USD/t | U26: 0.3 | V26: 0.27 | W26: =$J$37*V26*'Allocation OPEX CAPEX'!L12 +'Allocation OPEX CAPEX'!L27*mining!U26*$J$37+(1-SUM(mining!U26:V26))*mining!$J$37 -> 2.0983853 | X26: =W26/8760 -> 0.0002395417
A27: Chile | B27: 2022 | C27: 5200 | D27: 190000 | E27: kt | F27: USGS, 2023 | G27: recoverable copper content | I27: China | J27: 1900 | K27: 27000 | L27: kt | M27: USGS | N27: 2022 | O27: 2.12 | P27: t CO2 / t Cu | Q27: https://www.sciencedirect.com/science/article/pii/S0921344922001859#:~:text=According%20to%20our%20calculation%2C%20from,carbon%20emissions%20in%20those%20years. | U27: 0.3 | V27: 0.32 | W27: =$J$37*V27*'Allocation OPEX CAPEX'!L13 +'Allocation OPEX CAPEX'!L28*mining!U27*$J$37+(1-SUM(mining!U27:V27))*mining!$J$37 -> 1.9095705 | X27: =W27/8760 -> 0.00021798749
A28: China | B28: 2022 | C28: 1900 | D28: 27000 | E28: kt | F28: USGS, 2023 | G28: recoverable copper content | I28: Czech Republic | J28: 0 | K28: 0 | L28: kt | M28: USGS | N28: 2022 | O28: 1.2 | P28: t CO2 / t Cu | R28: 12500 | S28: EUR/t Cu | T28: https://internationalcopper.org/wp-content/uploads/2023/03/Copper_The-Pathway-to-Net-Zero_Focus-on-Europe_final.pdf | U28: 0.3 | V28: =$V$33 -> 0.2975 | W28: =$J$37*V28*'Allocation OPEX CAPEX'!L14 +'Allocation OPEX CAPEX'!L29*mining!U28*$J$37+(1-SUM(mining!U28:V28))*mining!$J$37 -> 2.856202 | X28: =W28/8760 -> 0.00032605046
A29: Congo (Kinshasa) | B29: 2022 | C29: 2200 | D29: 31000 | E29: kt | F29: USGS, 2023 | G29: recoverable copper content | I29: Germany | J29: 0.06 | K29: 0 | L29: kt | M29: USGS | N29: 2022 | O29: 1.2 | P29: t CO2 / t Cu | R29: 12500 | S29: EUR/t Cu | T29: https://internationalcopper.org/wp-content/uploads/2023/03/Copper_The-Pathway-to-Net-Zero_Focus-on-Europe_final.pdf | U29: 0.3 | V29: =$V$33 -> 0.2975 | W29: =$J$37*V29*'Allocation OPEX CAPEX'!L15 +'Allocation OPEX CAPEX'!L30*mining!U29*$J$37+(1-SUM(mining!U29:V29))*mining!$J$37 -> 3.9504966 | X29: =W29/8760 -> 0.00045096993
A30: Germany | B30: 2022 | C30: 0 | D30: 0 | E30: kt | F30: USGS, 2023 | G30: recoverable copper content | I30: Italy | J30: 0 | K30: 0 | L30: kt | M30: USGS | N30: 2022 | O30: 1.2 | P30: t CO2 / t Cu | R30: 12500 | S30: EUR/t Cu | T30: https://internationalcopper.org/wp-content/uploads/2023/03/Copper_The-Pathway-to-Net-Zero_Focus-on-Europe_final.pdf | U30: 0.3 | V30: =$V$33 -> 0.2975 | W30: =$J$37*V30*'Allocation OPEX CAPEX'!L16 +'Allocation OPEX CAPEX'!L31*mining!U30*$J$37+(1-SUM(mining!U30:V30))*mining!$J$37 -> 3.923577 | X30: =W30/8760 -> 0.00044789691
A31: Indonesia | B31: 2022 | C31: 920 | D31: 24000 | E31: kt | F31: USGS, 2023 | G31: recoverable copper content | I31: Japan | J31: 0 | K31: 0 | L31: kt | M31: USGS | N31: 2022 | O31: 2.5 | P31: t CO2 / t Cu | Q31: https://www.sciencedirect.com/science/article/pii/S2352550922003037 | R31: 12500 | S31: EUR/t Cu | T31: https://internationalcopper.org/wp-content/uploads/2023/03/Copper_The-Pathway-to-Net-Zero_Focus-on-Europe_final.pdf | U31: 0.3 | V31: =$V$33 -> 0.2975 | W31: =$J$37*V31*'Allocation OPEX CAPEX'!L17 +'Allocation OPEX CAPEX'!L32*mining!U31*$J$37+(1-SUM(mining!U31:V31))*mining!$J$37 -> 2.8871633 | X31: =W31/8760 -> 0.00032958485
A32: Japan | B32: 2022 | C32: 0 | D32: 0 | E32: kt | F32: USGS, 2023 | G32: recoverable copper content | I32: Korea | J32: 0 | K32: 0 | L32: kt | M32: USGS | N32: 2022 | O32: 1.2 | P32: t CO2 / t Cu | S32: EUR/t Cu | U32: 0.3 | V32: =$V$33 -> 0.2975 | W32: =$J$37*V32*'Allocation OPEX CAPEX'!L18 +'Allocation OPEX CAPEX'!L33*mining!U32*$J$37+(1-SUM(mining!U32:V32))*mining!$J$37 -> 2.4529123 | X32: =W32/8760 -> 0.00028001281
A33: Kazakhstan | B33: 2022 | C33: 580 | D33: 20000 | E33: kt | F33: USGS, 2023 | G33: recoverable copper content | I33: RoE | J33: 3431 | K33: 27590 | L33: kt | M33: USGS | N33: 2022 | O33: 1.2 | P33: t CO2 / t Cu | S33: EUR/t Cu | U33: 0.3 | V33: =AVERAGE(V27,V26,V24,V34) -> 0.2975 | W33: =$J$37*V33*'Allocation OPEX CAPEX'!L19 +'Allocation OPEX CAPEX'!L34*mining!U33*$J$37+(1-SUM(mining!U33:V33))*mining!$J$37 -> 3.0567928 | X33: =W33/8760 -> 0.00034894894
A34: Korea, Republic of | B34: 2022 | C34: 0 | D34: 0 | E34: kt | F34: USGS, 2023 | G34: recoverable copper content | I34: ROW | J34: =C41-SUM(J24:J33,J35) -> 14157.94 | K34: =D41-SUM(K24:K33,K35) -> 694410 | L34: kt | M34: USGS | N34: 2022 | O34: 1.2 | P34: t CO2 / t Cu | R34: 12500 | S34: EUR/t Cu | T34: https://internationalcopper.org/wp-content/uploads/2023/03/Copper_The-Pathway-to-Net-Zero_Focus-on-Europe_final.pdf | U34: 0.3 | V34: 0.27 | W34: =$J$37*V34*'Allocation OPEX CAPEX'!L20 +'Allocation OPEX CAPEX'!L35*mining!U34*$J$37+(1-SUM(mining!U34:V34))*mining!$J$37 -> 3.0529774 | X34: =W34/8760 -> 0.0003485134
A35: Mexico | B35: 2022 | C35: 740 | D35: 53000 | E35: kt | F35: USGS, 2023 | G35: recoverable copper content | I35: United States | J35: 1300 | K35: 44000 | L35: kt | M35: USGS | N35: 2022 | O35: 1.2 | P35: t CO2 / t Cu | Q35: Ecoinvent 3.10
A36: Peru | B36: 2022 | C36: 2200 | D36: 81000 | E36: kt | F36: USGS, 2023 | G36: recoverable copper content
A37: Poland | B37: 2022 | C37: 390 | D37: 30000 | E37: kt | F37: USGS, 2023 | G37: recoverable copper content | I37: OPEX | J37: =(2.12-0.35)/0.487*0.84 -> 3.0529774 | K37: €/kg | L37: https://www.spglobal.com/market-intelligence/en/news-insights/research/copper-all-in-sustaining-cost-jumps-16-percent-yoy-in-2021-margins-double
A38: Russia | B38: 2022 | C38: 1000 | D38: 62000 | E38: kt | F38: USGS, 2023 | G38: recoverable copper content
A39: Zambia | B39: 2022 | C39: 770 | D39: 19000 | E39: kt | F39: USGS, 2023 | G39: recoverable copper content
A40: Other countries | B40: 2022 | C40: 3400 | D40: 200000 | E40: kt | F40: USGS, 2023 | G40: recoverable copper content
A41: world total | B41: 2022 | C41: 22000 | D41: 890000 | E41: kt | F41: USGS, 2023 | G41: recoverable copper content
A42: europe | B42: 2019 | C42: 3431 | D42: =0.031*D41 -> 27590 | E42: kt | F42: USGS 2019 | G42: and https://rmis.jrc.ec.europa.eu/rmp/Copper
A43: brazil | B43: 2021 | C43: 381 | E43: kt | F43: USGS, 2021
A44: Nickel | B44: year | C44: Production | D44: Reserve | E44: unit | F44: Source | G44: Note | K44: Production | L44: Reserves | M44: unit | N44: Source | O44: year | P44: Carbon Footprint | Q44: unit | U44: Share of energ | V44: Sahre of labor on total cost | W44: Ajusted OPEX with labor and energy cost
A45: United States | B45: 2022 | C45: 18000 | D45: 370000 | E45: t | F45: USGS, 2023 | G45: Mine production - nickel, metric tons contained | J45: Australia | K45: 160000 | L45: 21000000 | M45: t | N45: USGS | R45: AUS | U45: 0.3 | V45: 0.33 | W45: =$K$59*(U45*'Allocation OPEX CAPEX'!L25+'Allocation OPEX CAPEX'!L10*mining!V45 + (1-mining!U45-mining!V45)) -> 9.5856661 | X45: =W45/8760 -> 0.0010942541
A46: Australia | B46: 2022 | C46: 160000 | D46: 21000000 | E46: t | F46: USGS, 2023 | G46: Mine production - nickel, metric tons contained | J46: Austria | K46: 700 | L46: 0 | M46: t | N46: https://rmis.jrc.ec.europa.eu/rmp/Nickel | R46: AUT | U46: 0.3 | V46: =$V$33 -> 0.2975 | W46: =$K$59*(U46*'Allocation OPEX CAPEX'!L26+'Allocation OPEX CAPEX'!L11*mining!V46 + (1-mining!U46-mining!V46)) -> 10.447725 | X46: =W46/8760 -> 0.0011926626
A47: Brazil | B47: 2022 | C47: 83000 | D47: 16000000 | E47: t | F47: USGS, 2023 | G47: Mine production - nickel, metric tons contained | J47: Brazil | K47: 83000 | L47: 16000000 | M47: t | N47: USGS | R47: BRA | U47: 0.3 | V47: 0.27 | W47: =$K$59*(U47*'Allocation OPEX CAPEX'!L27+'Allocation OPEX CAPEX'!L12*mining!V47 + (1-mining!U47-mining!V47)) -> 5.7504293 | X47: =W47/8760 -> 0.0006564417
A48: Canada | B48: 2022 | C48: 130000 | D48: 2200000 | E48: t | F48: USGS, 2023 | G48: Mine production - nickel, metric tons contained | J48: China | K48: 110000 | L48: 2100000 | M48: t | N48: USGS | P48: 8.3 | Q48: https://www.sciencedirect.com/science/article/pii/S0301420721004414 | R48: CHN | S48: 9.3 | T48: ecoinvent | U48: 0.3 | V48: 0.32 | W48: =$K$59*(U48*'Allocation OPEX CAPEX'!L28+'Allocation OPEX CAPEX'!L13*mining!V48 + (1-mining!U48-mining!V48)) -> 5.2329998 | X48: =W48/8760 -> 0.00059737441
A49: China | B49: 2022 | C49: 110000 | D49: 2100000 | E49: t | F49: USGS, 2023 | G49: Mine production - nickel, metric tons contained | J49: Czech Republic | K49: 0 | L49: 0 | M49: t | N49: USGS | R49: CZE | U49: 0.3 | V49: =$V$33 -> 0.2975 | W49: =$K$59*(U49*'Allocation OPEX CAPEX'!L29+'Allocation OPEX CAPEX'!L14*mining!V49 + (1-mining!U49-mining!V49)) -> 7.8271553 | X49: =W49/8760 -> 0.00089351088
A50: Indonesia | B50: 2022 | C50: 1600000 | D50: 21000000 | E50: t | F50: USGS, 2023 | G50: Mine production - nickel, metric tons contained | J50: Germany | K50: 0 | L50: 0 | M50: t | N50: USGS | R50: DEU | U50: 0.3 | V50: =$V$33 -> 0.2975 | W50: =$K$59*(U50*'Allocation OPEX CAPEX'!L30+'Allocation OPEX CAPEX'!L15*mining!V50 + (1-mining!U50-mining!V50)) -> 10.825968 | X50: =W50/8760 -> 0.0012358411
A51: New Caledonia | B51: 2022 | C51: 190000 | D51: 7100000 | E51: t | F51: USGS, 2023 | G51: Mine production - nickel, metric tons contained | J51: Italy | K51: 0 | L51: 0 | M51: t | N51: USGS | R51: ITA | U51: 0.3 | V51: =$V$33 -> 0.2975 | W51: =$K$59*(U51*'Allocation OPEX CAPEX'!L31+'Allocation OPEX CAPEX'!L16*mining!V51 + (1-mining!U51-mining!V51)) -> 10.752197 | X51: =W51/8760 -> 0.0012274197
A52: Philippines | B52: 2022 | C52: 330000 | D52: 4800000 | E52: t | F52: USGS, 2023 | G52: Mine production - nickel, metric tons contained | J52: Japan | K52: 56000 | L52: 0 | M52: t | N52: USGS | R52: JPN | U52: 0.3 | V52: =$V$33 -> 0.2975 | W52: =$K$59*(U52*'Allocation OPEX CAPEX'!L32+'Allocation OPEX CAPEX'!L17*mining!V52 + (1-mining!U52-mining!V52)) -> 7.9120019 | X52: =W52/8760 -> 0.00090319657
A53: Russia | B53: 2022 | C53: 220000 | D53: 7500000 | E53: t | F53: USGS, 2023 | G53: Mine production - nickel, metric tons contained | J53: Korea | K53: 0 | L53: 0 | M53: t | N53: USGS | R53: KOR | U53: 0.3 | V53: =$V$33 -> 0.2975 | W53: =$K$59*(U53*'Allocation OPEX CAPEX'!L33+'Allocation OPEX CAPEX'!L18*mining!V53 + (1-mining!U53-mining!V53)) -> 6.7219774 | X53: =W53/8760 -> 0.00076734901
A54: Europe tot | B54: 2019 | C54: 355000 | F54: USGS 2021 | G54: reserves europe: https://rmis.jrc.ec.europa.eu/rmp/Nickel | J54: RoE | K54: 355000 | L54: =0.055*D56 -> 5500000 | M54: t | N54: USGS | R54: ROE | U54: 0.3 | V54: =AVERAGE(V48,V47,V45,V55) -> 0.2975 | W54: =$K$59*(U54*'Allocation OPEX CAPEX'!L34+'Allocation OPEX CAPEX'!L19*mining!V54 + (1-mining!U54-mining!V54)) -> 8.3768556 | X54: =W54/8760 -> 0.00095626205
A55: Other countries | B55: 2022 | C55: 440000 | D55: 20000000 | E55: t | F55: USGS, 2023 | G55: Mine production - nickel, metric tons contained | J55: ROW | K55: =C56-SUM((K45:K54,K56)) -> 2517300 | L55: =D56-SUM(L45:L54,L56) -> 55030000 | M55: t | N55: USGS | R55: ROW | S55: 8.41 | T55: ecoinvent | U55: 0.3 | V55: 0.27 | W55: =$K$59*(U55*'Allocation OPEX CAPEX'!L35+'Allocation OPEX CAPEX'!L20*mining!V55 + (1-mining!U55-mining!V55)) -> 8.3664 | X55: =W55/8760 -> 0.00095506849
A56: World total (rounded) | B56: 2022 | C56: 3300000 | D56: 100000000 | E56: t | F56: USGS, 2023 | G56: Mine production - nickel, metric tons contained | J56: United States | K56: 18000 | L56: 370000 | M56: t | N56: USGS | P56: 13 | Q56: kg Co2 /kg Ni | R56: USA | T56: kg Co2 /kg Ni | U56: 0.3 | V56: 0.27 | W56: =$K$59*(U56*'Allocation OPEX CAPEX'!L36+'Allocation OPEX CAPEX'!L21*mining!V56 + (1-mining!U56-mining!V56)) -> 8.665528 | X56: =W56/8760 -> 0.00098921553
A57: Japan | B57: 2021 | C57: 56000 | E57: 7 | F57: USGS, 2021
J58: Price | K58: =15.92*0.84 -> 13.3728 | L58: €/kg | M58: https://markets.businessinsider.com/commodities/nickel-price
J59: OPEX | K59: =0.84*9.96 -> 8.3664 | L59: €/kg | M59: https://www.spglobal.com/market-intelligence/en/news-insights/research/nickel-industry-margins-surged-in-2021-amid-stronger-nickel-prices
A62: Iron ore | B62: Year | C62: Production usable ore | D62: Production iron content | E62: Unit | F62: Reserves usable ore | G62: Reserves iron content | H62: Unit | I62: Source | J62: Iron ore | K62: Production | L62: Reserves | M62: unit | N62: Source | O62: year | P62: Carbon Footprint | Q62: unit | R62: conversion factor | U62: OPEX values found | W62: Share Energy | X62: Sahre of labor on total cost | Y62: Ajusted OPEX with labor and energy cost
A63: United States | B63: 2022 | C63: 46000 | E63: kt | F63: 3000 | G63: 1000 | H63: Mt | I63: USGS, 2023 | J63: Australia | K63: 880 | L63: =F64 -> 51000 | M63: Mt | N63: USGS | R63: =D63/C63 -> 0 | U63: 10.88 | W63: 0.165 | X63: 0.33 | Y63: =$U$70*(W63*'Allocation OPEX CAPEX'!L25+'Allocation OPEX CAPEX'!L10*mining!X63 + (1-mining!W63-mining!X63)) -> 35.170888 | Z63: =Y63/8760 -> 0.0040149416
A64: Australia | B64: 2022 | C64: 880000 | D64: 540000 | E64: kt | F64: 51000 | G64: 27000 | H64: Mt | I64: USGS, 2023 | J64: Austria | K64: 3.311 | L64: =F79 -> 35 | M64: Mt | N64: USGS | R64: =D64/C64 -> 0.61363636 | U64: 59.17 | W64: 0.165 | X64: =$V$33 -> 0.2975 | Y64: =$U$70*(W64*'Allocation OPEX CAPEX'!L26+'Allocation OPEX CAPEX'!L11*mining!X64 + (1-mining!W64-mining!X64)) -> 36.949534 | Z64: =Y64/8760 -> 0.0042179833
A65: Brazil | B65: 2022 | C65: 410000 | D65: 260000 | E65: kt | F65: 34000 | G65: 15000 | H65: Mt | I65: USGS, 2023 | J65: Brazil | K65: 410 | L65: =F65 -> 34000 | M65: Mt | N65: USGS | R65: =D65/C65 -> 0.63414634 | U65: 49.85 | W65: 0.165 | X65: 0.27 | Y65: =$U$70*(W65*'Allocation OPEX CAPEX'!L27+'Allocation OPEX CAPEX'!L12*mining!X65 + (1-mining!W65-mining!X65)) -> 22.926232 | Z65: =Y65/8760 -> 0.0026171498
A66: Canada | B66: 2022 | C66: 58000 | D66: 35000 | E66: kt | F66: 6000 | G66: 2300 | H66: Mt | I66: USGS, 2023 | J66: China | K66: 380 | L66: =F68 -> 20000 | M66: Mt | N66: USGS | R66: =D66/C66 -> 0.60344828 | U66: 31.87 | W66: 0.165 | X66: 0.32 | Y66: =$U$70*(W66*'Allocation OPEX CAPEX'!L28+'Allocation OPEX CAPEX'!L13*mining!X66 + (1-mining!W66-mining!X66)) -> 22.242917 | Z66: =Y66/8760 -> 0.0025391457
A67: Chile | B67: 2022 | C67: 16000 | D67: 10000 | E67: kt | F67: NA | G67: NA | H67: Mt | I67: USGS, 2023 | J67: Czech Republic | K67: 0 | L67: =D86 -> 0 | M67: Mt | N67: USGS | R67: =D67/C67 -> 0.625 | U67: 17.54 | W67: 0.165 | X67: =$V$33 -> 0.2975 | Y67: =$U$70*(W67*'Allocation OPEX CAPEX'!L29+'Allocation OPEX CAPEX'!L14*mining!X67 + (1-mining!W67-mining!X67)) -> 27.285148 | Z67: =Y67/8760 -> 0.0031147429
A68: China | B68: 2022 | C68: 380000 | D68: 240000 | E68: kt | F68: 20000 | G68: 6900 | H68: Mt | I68: USGS, 2023 | J68: Germany | K68: 0.468 | L68: =D83 -> 0 | M68: Mt | N68: USGS | R68: =D68/C68 -> 0.63157895 | U68: 30.48 | W68: 0.165 | X68: =$V$33 -> 0.2975 | Y68: =$U$70*(W68*'Allocation OPEX CAPEX'!L30+'Allocation OPEX CAPEX'!L15*mining!X68 + (1-mining!W68-mining!X68)) -> 38.265991 | Z68: =Y68/8760 -> 0.0043682638
A69: India | B69: 2022 | C69: 290000 | D69: 180000 | E69: kt | F69: 5500 | G69: 3400 | H69: Mt | I69: USGS, 2023 | J69: Italy | K69: 0 | L69: =D88 -> 0 | M69: Mt | N69: USGS | R69: =D69/C69 -> 0.62068966 | U69: 57.76 | W69: 0.165 | X69: =$V$33 -> 0.2975 | Y69: =$U$70*(W69*'Allocation OPEX CAPEX'!L31+'Allocation OPEX CAPEX'!L16*mining!X69 + (1-mining!W69-mining!X69)) -> 36.506829 | Z69: =Y69/8760 -> 0.0041674463
A70: Iran | B70: 2022 | C70: 75000 | D70: 49000 | E70: kt | F70: 2700 | G70: 1500 | H70: Mt | I70: USGS, 2023 | J70: Japan | K70: 0 | L70: =D87 -> 0 | M70: Mt | N70: USGS | R70: =D70/C70 -> 0.65333333 | T70: Average | U70: =AVERAGE(U63:U69)*0.84 -> 30.906 | V70: €/t | W70: 0.165 | X70: =$V$33 -> 0.2975 | Y70: =$U$70*(W70*'Allocation OPEX CAPEX'!L32+'Allocation OPEX CAPEX'!L17*mining!X70 + (1-mining!W70-mining!X70)) -> 29.828548 | Z70: =Y70/8760 -> 0.0034050854
A71: Kazakhstan | B71: 2022 | C71: 66000 | D71: 14000 | E71: kt | F71: 2500 | G71: 900 | H71: Mt | I71: USGS, 2023 | J71: Korea | K71: 0.539 | L71: =D85 -> 0 | M71: Mt | N71: USGS | R71: =D71/C71 -> 0.21212121 | U71: =U70/8760 -> 0.0035280822 | W71: 0.165 | X71: =$V$33 -> 0.2975 | Y71: =$U$70*(W71*'Allocation OPEX CAPEX'!L33+'Allocation OPEX CAPEX'!L18*mining!X71 + (1-mining!W71-mining!X71)) -> 26.886853 | Z71: =Y71/8760 -> 0.0030692755
A72: Mauritania | B72: 2022 | C72: 13000 | D72: 8100 | E72: kt | F72: NA | G72: NA | H72: Mt | I72: USGS, 2023 | J72: RoE | K72: 150.688 | L72: =F84-SUM(L67:L69,L64) -> 1155 | M72: Mt | N72: USGS | R72: =D72/C72 -> 0.62307692 | W72: 0.165 | X72: =AVERAGE(X66,X65,X63,X73) -> 0.2975 | Y72: =$U$70*(W72*'Allocation OPEX CAPEX'!L34+'Allocation OPEX CAPEX'!L19*mining!X72 + (1-mining!W72-mining!X72)) -> 30.944624 | Z72: =Y72/8760 -> 0.0035324913
A73: Mexico | B73: 2022 | C73: 11000 | D73: 6900 | E73: kt | F73: NA | G73: NA | H73: Mt | I73: USGS, 2023 | J73: ROW | K73: 728.994 | L73: =F82-SUM(L63:L72,L74) -> 70810 | M73: Mt | N73: USGS | P73: =0.0059955/0.46 -> 0.013033696 | Q73: kg/kg iron | R73: =D73/C73 -> 0.62727273 | W73: 0.165 | X73: 0.27 | Y73: =$U$70*(W73*'Allocation OPEX CAPEX'!L35+'Allocation OPEX CAPEX'!L20*mining!X73 + (1-mining!W73-mining!X73)) -> 30.906 | Z73: =Y73/8760 -> 0.0035280822
A74: Peru | B74: 2022 | C74: 17000 | D74: 11000 | E74: kt | F74: 2600 | G74: 1200 | H74: Mt | I74: USGS, 2023 | J74: United States | K74: 46 | L74: =F63 -> 3000 | M74: Mt | N74: USGS | R74: =D74/C74 -> 0.64705882 | W74: 0.165 | X74: 0.27 | Y74: =$U$70*(W74*'Allocation OPEX CAPEX'!L36+'Allocation OPEX CAPEX'!L21*mining!X74 + (1-mining!W74-mining!X74)) -> 33.210011 | Z74: =Y74/8760 -> 0.0037910972
A75: Russia | B75: 2022 | C75: 90000 | D75: 63000 | E75: kt | F75: 29000 | G75: 14000 | H75: Mt | I75: USGS, 2023 | R75: =D75/C75 -> 0.7
A76: South Africa | B76: 2022 | C76: 76000 | D76: 48000 | E76: kt | F76: 1000 | G76: 670 | H76: Mt | I76: USGS, 2023 | J76: Price | K76: =104*0.84 -> 87.36 | L76: €/t | M76: https://markets.businessinsider.com/commodities/iron-ore-price | R76: =D76/C76 -> 0.63157895
A77: Sweden | B77: 2022 | C77: 39000 | D77: 28000 | E77: kt | F77: 1300 | G77: 600 | H77: Mt | I77: USGS, 2023 | R77: =D77/C77 -> 0.71794872
A78: Turkey | B78: 2022 | C78: 17000 | D78: 10000 | E78: kt | F78: 130 | G78: 38 | H78: Mt | I78: USGS, 2023 | R78: =D78/C78 -> 0.58823529
A79: Austria | B79: 2021 | C79: 3311 | D79: 840 | E79: kt | F79: 35 | I79: UGS, 2021 https://opac.geologie.ac.at/ais312/dokumente/Uhlig_1910_Eisenerz_Österreich.pdf | R79: =D79/C79 -> 0.25369979
A80: Ukraine | B80: 2022 | C80: 76000 | D80: 47000 | E80: kt | F80: 6500 | G80: 2300 | H80: Mt | I80: USGS, 2023 | R80: =D80/C80 -> 0.61842105
A81: Other countries | B81: 2022 | C81: 59000 | D81: 5000 | E81: kt | F81: 18000 | G81: 9500 | H81: Mt | I81: USGS, 2023 | R81: =D81/C81 -> 0.084745763
A82: World total (rounded) | B82: 2022 | C82: 2600000 | D82: 1600000 | E82: kt | F82: 180000 | G82: 85000 | H82: Mt | I82: USGS, 2023 | R82: =D82/C82 -> 0.61538462
A83: germany | B83: 2015 | C83: 468 | E83: kt | I83: UGS, 2021 | Q83: Averga | R83: =AVERAGE(R63:R82) -> 0.53506884
A84: europe | B84: 2019 | C84: 154467 | E84: kt | F84: =0.014*G82 -> 1190 | H84: mt | I84: USGS,2019 | Q84: Conversion factor | R84: =1/R83 -> 1.8689184 | S84: kg reserves / kg output
A85: south korea | B85: 2021 | C85: 539 | E85: kt | I85: USGS, 2021
A86: czechia | B86: 2022 | C86: 0 | E86: kt | I86: https://worldsteel.org/data/world-steel-in-figures-2024/
A87: japan | B87: 2022 | C87: 0 | E87: kt | I87: https://worldsteel.org/data/world-steel-in-figures-2024/
A88: italy | B88: 2022 | C88: 0 | E88: kt | I88: https://worldsteel.org/data/world-steel-in-figures-2024/

Sheet Tabelle1

Sheet Refinement (material production
A1: Aluminium | K1: Copper | W1: Raw Steel
A2: Input | B2: 4 | D2: t | E2: Bauxite | F2: Source | K2: Input | O2: 1 | P2: t | Q2: Copper Ore | R2: Source | W2: Input | X2: 1.6 | Y2: t | Z2: Source
A3: Output | B3: 1 | D3: t | E3: Aluminium | F3: USGS, 2023 | K3: Output | O3: 6 to 10 | P3: kg | Q3: Copper | R3: https://worldoceanreview.com/en/wor-3/mineral-resources/deposits-and-markets/how-much-metal-does-the-ore-contain/#:~:text=In%20most%20cases%20copper%20ores,to%2010%20kilograms%20of%20copper. | U3: if data fro USGS is used 1 to 1 conversion factor as recoverable copper content in mining | W3: Output | X3: 1 | Y3: t | Z3: https://www.bhp.com/what-we-do/products/iron-ore#
A4: Cost | K4: Price | O4: =9.83*0.84 -> 8.2572 | P4: €/kg | Q4: https://markets.businessinsider.com/commodities/copper-price | W4: Price | X4: =3307*0.84 -> 2777.88 | Y4: €/t | Z4: https://tradingeconomics.com/commodity/steel
A6: Country | B6: year | D6: production | E6: unit | F6: source | G6: Carbon Footprinz | H6: unit | I6: Source | K6: Country | O6: year | P6: production | Q6: unit | R6: source | S6: Source carbon footprint | W6: Country | X6: year | Y6: production | Z6: unit | AA6: kt | AB6: source
A7: Australia | B7: 2022 | D7: 20000 | E7: kt | F7: USGS 2023 | G7: https://static1.squarespace.com/static/5877e86f9de4bb8bce72105c/t/624d11ab5a37a4341fd85a6e/1649217981897/Aluminum+benchmarking+report-+Feb2022+rev2.pdf | K7: Australia | O7: 2022 | P7: 380 | Q7: kt | R7: USGS 2023 | W7: Australia | AA7: 5808 | AB7: USGS 2021
A8: Austria | B8: 2021 | D8: 491 | E8: kt | F8: USGS 2021 | K8: Austria | O8: 2022 | P8: 133 | Q8: kt | R8: USGS, 2021 | W8: Austria | X8: 2021 | Y8: 7.884 | Z8: Mt | AA8: =Y8*1000 -> 7884 | AB8: USGs 2021
A9: Brazil | B9: 2022 | D9: 11000 | E9: kt | F9: USGS 2023 | G9: https://www3.weforum.org/docs/WEF_Decarbonizing_Brazil’s_Steel_Aluminium_and_Aviation_Sectors_2024.pdf | K9: Brazil | O9: 2021 | P9: 133.5 | Q9: kt | R9: USGS 2021 | W9: Brazil | X9: 2022 | Y9: 33 | Z9: Mt | AA9: =Y9*1000 -> 33000 | AB9: USGS 2023 | AC9: https://globalenergymonitor.org/report/forging-a-sustainable-future-brazils-opportunity-to-lead-in-steel-decarbonization/#:~:text=From%20an%20emissions%20perspective%2C%20if,tonne%20crude%20steel%20global%20average.
A10: Canada | B10: 2022 | D10: 1300 | E10: kt | F10: USGS 2023 | K10: Canada | O10: 2022 | P10: 310 | Q10: kt | R10: USGS 2023 | W10: China | X10: 2022 | Y10: 990 | Z10: Mt | AA10: =Y10*1000 -> 990000 | AB10: USGS 2023 | AC10: https://www.sciencedirect.com/science/article/pii/S0921344916301458#:~:text=The%20results%20of%20our%20analysis,the%20U.S.%20One%20of%20the
A11: China | B11: 2022 | D11: 76000 | E11: kt | F11: USGS 2023 | G11: https://static1.squarespace.com/static/5877e86f9de4bb8bce72105c/t/624d11ab5a37a4341fd85a6e/1649217981897/Aluminum+benchmarking+report-+Feb2022+rev2.pdf | K11: Chile | O11: 2022 | P11: 2100 | Q11: kt | R11: USGS 2023 | W11: Czechia | X11: 2021 | Y11: 4.817 | Z11: Mt | AA11: =Y11*1000 -> 4817 | AB11: USGs 2021
A12: czechia | B12: 2021 | D12: 60 | E12: kt | F12: USGS 2021 | K12: China | O12: 2022 | P12: 11000 | Q12: kt | R12: USGS 2023 | S12: https://www.sciencedirect.com/science/article/pii/S0921344922001859#:~:text=According%20to%20our%20calculation%2C%20from,carbon%20emissions%20in%20those%20years. | W12: europe | X12: 2019 | Y12: 299.419 | Z12: Mt | AA12: =Y12*1000 -> 299419 | AB12: USGS,2019 | AC12: https://meg.resourcesregulator.nsw.gov.au/sites/default/files/2022-11/report-reduction-of-ghg-emissions-in-steel-industries.pdf
A13: Europe | B13: 2019 | D13: 8589 | E13: kt | F13: USGS 2022 | G13: https://static1.squarespace.com/static/5877e86f9de4bb8bce72105c/t/624d11ab5a37a4341fd85a6e/1649217981897/Aluminum+benchmarking+report-+Feb2022+rev2.pdf | K13: Congo (Kinshasa) | O13: 2022 | P13: 1700 | Q13: kt | R13: USGS 2023 | W13: Germany | X13: 2022 | Y13: 38 | Z13: Mt | AA13: =Y13*1000 -> 38000 | AB13: USGS 2023 | AC13: https://www.sciencedirect.com/science/article/pii/S0921344916301458#:~:text=The%20results%20of%20our%20analysis,the%20U.S.%20One%20of%20the
A14: Germany | B14: 2022 | D14: 750 | E14: kt | F14: USGS 2023 | K14: czechia | P14: NA | W14: India | X14: 2022 | Y14: 130 | Z14: Mt | AA14: =Y14*1000 -> 130000 | AB14: USGS 2023
A15: Guinea | B15: 2022 | D15: 440 | E15: kt | F15: USGS 2023 | K15: Europe | O15: 2019 | P15: 3429 | Q15: kt | R15: USGS, 2019 | S15: ecoinvent | W15: Iran | X15: 2022 | Y15: 29 | Z15: Mt | AA15: =Y15*1000 -> 29000 | AB15: USGS 2023
A16: India | B16: 2022 | D16: 7400 | E16: kt | F16: USGS 2023 | K16: Germany | O16: 2022 | P16: 620 | Q16: kt | R16: USGS 2023 | W16: Italy | X16: 2022 | Y16: 24 | Z16: Mt | AA16: =Y16*1000 -> 24000 | AB16: USGS 2023 | AC16: https://www.climate-transparency.org/wp-content/uploads/2019/11/B2G_2019_Italy.pdf
A17: Indonesia | B17: 2022 | D17: 1100 | E17: kt | F17: USGS 2023 | K17: Indonesia | O17: 2022 | P17: 300 | Q17: kt | R17: USGS 2023 | W17: italy | X17: 2021 | Y17: 24.4 | Z17: Mt | AA17: =Y17*1000 -> 24400 | AB17: USGs 2021
A18: Ireland | B18: 2022 | D18: 1800 | E18: kt | F18: USGS 2023 | K18: italy | O18: 2021 | P18: 15.4 | Q18: kt | R18: https://rmis.jrc.ec.europa.eu/rmp/Copper | W18: Japan | X18: 2022 | Y18: 97 | Z18: Mt | AA18: =Y18*1000 -> 97000 | AB18: USGS 2023
A19: Italy | B19: 2021 | E19: kt | F19: USGS 2021 | K19: Japan | O19: 2022 | P19: 1600 | Q19: kt | R19: USGS 2023 | W19: Korea, Republic of | X19: 2022 | Y19: 69 | Z19: Mt | AA19: =Y19*1000 -> 69000 | AB19: USGS 2023
A20: Jamaica | B20: 2022 | D20: 480 | E20: kt | F20: USGS 2023 | K20: Japan | O20: 2021 | P20: 1119 | Q20: kt | R20: USGS 2021 | S20: https://www.sciencedirect.com/science/article/pii/S2352550922003037 | W20: Mexico | X20: 2022 | Y20: 17 | Z20: Mt | AA20: =Y20*1000 -> 17000 | AB20: USGS 2023
A21: Japan | B21: 2021 | D21: 30 | E21: kt | F21: USGS 2021 | K21: Kazakhstan | O21: 2022 | P21: 510 | Q21: kt | R21: USGS 2023 | W21: Other countries | X21: 2022 | Y21: 230 | Z21: Mt | AA21: =Y21*1000 -> 230000 | AB21: USGS 2023
A22: Kazakhstan | B22: 2022 | D22: 1400 | E22: kt | F22: USGS 2023 | K22: Korea, Republic of | O22: 2022 | P22: 660 | Q22: kt | R22: USGS 2023 | W22: Russia | X22: 2022 | Y22: 71 | Z22: Mt | AA22: =Y22*1000 -> 71000 | AB22: USGS 2023
A23: Russia | B23: 2022 | D23: 3100 | E23: kt | F23: USGS 2023 | K23: Mexico | O23: 2022 | P23: 470 | Q23: kt | R23: USGS 2023 | W23: south korwa | X23: 2021 | Y23: 70.556 | Z23: Mt | AA23: =Y23*1000 -> 70556 | AB23: USGS,2021 | AC23: https://netzerosteel.org/wp-content/uploads/factsheets/south_korea_summary_profile_netzerosteel_project.pdf
A24: Saudi Arabia | B24: 2022 | D24: 2000 | E24: kt | F24: USGS 2023 | K24: Peru | O24: 2022 | P24: 290 | Q24: kt | R24: USGS 2023 | W24: Taiwan | X24: 2022 | Y24: 23 | Z24: Mt | AA24: =Y24*1000 -> 23000 | AB24: USGS 2023
A25: Spain | B25: 2022 | D25: 1700 | E25: kt | F25: USGS 2023 | K25: Poland | O25: 2022 | P25: 590 | Q25: kt | R25: USGS 2023 | W25: Turkey | X25: 2022 | Y25: 39 | Z25: Mt | AA25: =Y25*1000 -> 39000 | AB25: USGS 2023
A26: Ukraine | B26: 2022 | D26: 740 | E26: kt | F26: USGS 2023 | K26: Russia | O26: 2022 | P26: 1100 | Q26: kt | R26: USGS 2023 | W26: Ukraine | X26: 2022 | Y26: 19 | Z26: Mt | AA26: =Y26*1000 -> 19000 | AB26: USGS 2023
A27: United Arab Emirates | B27: 2022 | D27: 2300 | E27: kt | F27: USGS 2023 | K27: United States | O27: 2022 | P27: 1000 | Q27: kt | R27: USGS 2023 | W27: United States | X27: 2022 | Y27: 82 | Z27: Mt | AA27: =Y27*1000 -> 82000 | AB27: USGS 2023 | AC27: https://www.sciencedirect.com/science/article/pii/S0921344916301458#:~:text=The%20results%20of%20our%20analysis,the%20U.S.%20One%20of%20the
A28: United States | B28: 2022 | D28: 1200 | E28: kt | F28: USGS 2023 | G28: https://static1.squarespace.com/static/5877e86f9de4bb8bce72105c/t/624d11ab5a37a4341fd85a6e/1649217981897/Aluminum+benchmarking+report-+Feb2022+rev2.pdf | K28: Zambia | O28: 2022 | P28: 350 | Q28: kt | R28: USGS 2023 | W28: Vietnam | X28: 2022 | Y28: 23 | Z28: Mt | AA28: =Y28*1000 -> 23000 | AB28: USGS 2023
A29: Vietnam | B29: 2022 | D29: 1500 | E29: kt | F29: USGS 2023 | K29: World | O29: 2022 | P29: 26000 | Q29: kt | R29: USGS 2023 | S29: ecoinvent | W29: World total (rounded) | X29: 2022 | Y29: 1900 | Z29: Mt | AA29: =Y29*1000 -> 1900000 | AB29: USGS 2023 | AC29: https://www.statista.com/statistics/1446826/steel-emissions-intensity-worldwide/
A30: world | B30: 2022 | D30: 68400 | E30: kt | F30: USGS 2024 | G30: https://www.enplusgroup.com/en/media/news/press/low-carbon-aluminium-a-key-ingredient-to-deliver-japan-s-green-growth-strategy/
A31: south kora | G31: https://enplusgroup.com/upload/iblock/5b8/Toward-Zero-Carbon-for-Korean-industry-_-ENG.pdf | W31: https://www.google.com/url?sa=t&source=web&rct=j&opi=89978449&url=https://publications.jrc.ec.europa.eu/repository/bitstream/JRC129297/JRC129297_01.pdf&ved=2ahUKEwiesvq-6I2JAxWg2wIHHcChN1wQFnoECEEQAQ&usg=AOvVaw2fK4Q1YS9OcRGHpLWYkvm6
W33: Node | X33: OPEX av | AB33: Raw Steel | AD33: Carbon Footprint | AE33: CAGR historical | AF33: Auslastung at around 70% | AG33: https://one.oecd.org/document/DSTI/SC(2024)3/FINAL/en/pdf
A34: Country | B34: Aluminium | C34: OPEX | D34: Aluminium capacity | E34: Carbon footprint | F34: OPEX adjusted | K34: Node | L34: Copper | M34: Carbon footprint t/t cu | N34: OPEX data given | O34: adjusted for missing nodes (30% labor, 30% energy) | P34: Share labor | Q34: share energy | W34: AUS | X34: 495.6 | AA34: €/t | AB34: 5.808 | AC34: Mt | AD34: 1.91 | AE34: 0 | AH34: =X34/8760 -> 0.056575342
A35: Australia | B35: 1500 | C35: =1922*0.84 -> 1614.48 | D35: 1700 | E35: 11.5 | G35: =C35/8760 -> 0.18430137 | H35: k€/kt | K35: AUS | L35: 380 | M35: 3.44 | O35: =($D$73)*('Allocation OPEX CAPEX'!L10*P35+'Allocation OPEX CAPEX'!L25*Q35+(1-Q35-P35)) -> 319.34884 | P35: 0.5 | Q35: 0.3 | R35: =O35/8760 -> 0.036455347 | W35: AUT | X35: =590*0.84 -> 495.6 | Z35: https://www.ewi.uni-koeln.de/cms/wp-content/uploads/2022/12/221209_EWI_H2-Steel_Low-carbon-steel.pdf | AA35: €/t | AB35: =Y8 -> 7.884 | AC35: Mt | AD35: 1.15 | AE35: =AE43 -> -0.039 | AH35: =X35/8760 -> 0.056575342
A36: Austria | B36: 491 | C36: =2041*0.84 -> 1714.44 | E36: 5.6 | G36: =C36/8760 -> 0.19571233 | K36: AUT | L36: 133 | M36: 2.77 | O36: =($D$73)*('Allocation OPEX CAPEX'!L11*P36+'Allocation OPEX CAPEX'!L26*Q36+(1-Q36-P36)) -> 352.45595 | P36: 0.5 | Q36: 0.3 | R36: =O36/8760 -> 0.040234697 | W36: BRA | X36: =504*0.84 -> 423.36 | Y36: 2024 | Z36: https://transitionasia.org/green-steel-economics-brazil-factsheet/ | AA36: €/t | AB36: =Y9 -> 33 | AC36: Mt | AD36: 1.55 | AE36: -0.051 | AH36: =X36/8760 -> 0.048328767
A37: Brazil | B37: 811 | C37: =C45 -> 1667.148 | E37: 5.5 | G37: =C37/8760 -> 0.1903137 | K37: BRA | L37: 133.5 | M37: 3.44 | O37: =($D$73)*('Allocation OPEX CAPEX'!L12*P37+'Allocation OPEX CAPEX'!L27*Q37+(1-Q37-P37)) -> 175.50011 | P37: 0.3 | Q37: 0.3 | R37: =O37/8760 -> 0.020034259 | W37: CHN | X37: =570*0.84 -> 478.8 | Y37: 2022 | Z37: https://www.ewi.uni-koeln.de/cms/wp-content/uploads/2022/12/221209_EWI_H2-Steel_Low-carbon-steel.pdf | AA37: €/t | AB37: =Y10 -> 990 | AC37: Mt | AD37: 1.7 | AE37: 0.017 | AH37: =X37/8760 -> 0.054657534
A38: China | B38: 40000 | C38: =1932*0.84 -> 1622.88 | D38: 44000 | E38: 12.75 | G38: =C38/8760 -> 0.18526027 | K38: CHN | L38: 11000 | M38: 1.98 | N38: =D72 -> 203 | O38: =($D$73)*('Allocation OPEX CAPEX'!L13*P38+'Allocation OPEX CAPEX'!L28*Q38+(1-Q38-P38)) -> 167.53328 | P38: 0.3 | Q38: 0.3 | R38: =O38/8760 -> 0.019124803 | W38: CZE | X38: =590*0.84 -> 495.6 | Y38: 2022 | Z38: https://www.ewi.uni-koeln.de/cms/wp-content/uploads/2022/12/221209_EWI_H2-Steel_Low-carbon-steel.pdf | AA38: €/t | AB38: =Y11 -> 4.817 | AC38: Mt | AD38: 1.15 | AE38: =$AE$43 -> -0.039 | AH38: =X38/8760 -> 0.056575342
A39: Czech Republic | B39: 60 | C39: =2041*0.84 -> 1714.44 | E39: 5.6 | G39: =C39/8760 -> 0.19571233 | K39: CZE | L39: 0 | M39: 2.77 | N39: =$D$71 -> 324 | O39: =($D$73)*('Allocation OPEX CAPEX'!L14*P39+'Allocation OPEX CAPEX'!L29*Q39+(1-Q39-P39)) -> 246.11442 | P39: =0.3 -> 0.3 | Q39: 0.3 | R39: =O39/8760 -> 0.028095254 | W39: DEU | X39: =590*0.84 -> 495.6 | Y39: 2022 | Z39: https://www.ewi.uni-koeln.de/cms/wp-content/uploads/2022/12/221209_EWI_H2-Steel_Low-carbon-steel.pdf | AA39: €/t | AB39: =Y13 -> 38 | AC39: Mt | AD39: 1.708 | AE39: =$AE$43 -> -0.039 | AH39: =X39/8760 -> 0.056575342
A40: Germany | B40: 550 | C40: =2041*0.84 -> 1714.44 | D40: 750 | E40: 5.6 | G40: =C40/8760 -> 0.19571233 | K40: DEU | L40: 620 | M40: 2.77 | N40: =$D$71 -> 324 | O40: =($D$73)*('Allocation OPEX CAPEX'!L15*P40+'Allocation OPEX CAPEX'!L30*Q40+(1-Q40-P40)) -> 371.43545 | P40: 0.5 | Q40: 0.3 | R40: =O40/8760 -> 0.042401308 | W40: ITA | X40: =590*0.84 -> 495.6 | Y40: 2022 | Z40: https://www.ewi.uni-koeln.de/cms/wp-content/uploads/2022/12/221209_EWI_H2-Steel_Low-carbon-steel.pdf | AA40: €/t | AB40: =Y16 -> 24 | AC40: Mt | AD40: 0.6 | AE40: =$AE$43 -> -0.039 | AH40: =X40/8760 -> 0.056575342
A41: Italy | B41: 0 | C41: =2041*0.84 -> 1714.44 | E41: 5.6 | G41: =C41/8760 -> 0.19571233 | K41: ITA | L41: 15.4 | M41: 2.77 | N41: =$D$71 -> 324 | O41: =($D$73)*('Allocation OPEX CAPEX'!L16*P41+'Allocation OPEX CAPEX'!L31*Q41+(1-Q41-P41)) -> 348.35838 | P41: 0.5 | Q41: 0.3 | R41: =O41/8760 -> 0.039766938 | W41: JPN | X41: =620*0.84 -> 520.8 | Y41: 2022 | Z41: https://www.ewi.uni-koeln.de/cms/wp-content/uploads/2022/12/221209_EWI_H2-Steel_Low-carbon-steel.pdf | AA41: €/t | AB41: =Y18 -> 97 | AC41: Mt | AD41: 1.65 | AE41: 0.021 | AH41: =X41/8760 -> 0.059452055
A42: Japan | B42: 30 | C42: =C35 -> 1614.48 | E42: 12.6 | G42: =C42/8760 -> 0.18430137 | K42: JPN | L42: 1119 | M42: 0.92 | O42: =($D$73)*('Allocation OPEX CAPEX'!L17*P42+'Allocation OPEX CAPEX'!L32*Q42+(1-Q42-P42)) -> 247.19966 | P42: 0.5 | Q42: 0.3 | R42: =O42/8760 -> 0.028219139 | W42: KOR | X42: =605*0.84 -> 508.2 | Y42: 2024 | Z42: https://transitionasia.org/green-steel-economics-south-korea-factsheet/#:~:text=In%20South%20Korea%2C%20the%20analysis,BF%2DBOF%20cost%20of%20%24605. | AA42: €/t | AB42: =Y19 -> 69 | AC42: Mt | AD42: 1.5 | AE42: 0.021 | AH42: =X42/8760 -> 0.058013699
A43: South Korea | B43: 0 | C43: =C35 -> 1614.48 | E43: 11.4 | G43: =C43/8760 -> 0.18430137 | K43: KOR | L43: 660 | M43: 3.44 | O43: =($D$73)*('Allocation OPEX CAPEX'!L18*P43+'Allocation OPEX CAPEX'!L33*Q43+(1-Q43-P43)) -> 202.9637 | P43: 0.5 | Q43: 0.3 | R43: =O43/8760 -> 0.023169372 | W43: ROE | X43: =590*0.84 -> 495.6 | Y43: 2022 | Z43: https://www.ewi.uni-koeln.de/cms/wp-content/uploads/2022/12/221209_EWI_H2-Steel_Low-carbon-steel.pdf | AA43: €/t | AB43: =Y12-SUM(AB38:AB40,AB35) -> 224.718 | AC43: Mt | AD43: 1.15 | AE43: -0.039 | AH43: =X43/8760 -> 0.056575342
A44: RoE | B44: =D13-SUM(B36,B39,B40,B41) -> 7488 | C44: =2041*0.84 -> 1714.44 | E44: 5.6 | G44: =C44/8760 -> 0.19571233 | K44: ROE | L44: 2676 | M44: 2.77 | N44: =$D$71 -> 324 | O44: =($D$73)*('Allocation OPEX CAPEX'!L19*P44+'Allocation OPEX CAPEX'!L34*Q44+(1-Q44-P44)) -> 263.83207 | P44: 0.3 | Q44: 0.3 | R44: =O44/8760 -> 0.030117816 | W44: ROW | X44: =AVERAGE(X34:X43,X45) -> 490.17818 | AA44: €/t | AB44: =Y29-SUM(AB34:AB43,AB45) -> 323.773 | AC44: Mt | AD44: 1.91 | AE44: 0.023 | AH44: =X44/8760 -> 0.055956413
A45: RoW | B45: =D30-SUM(B35:B44,B46:B46) -> 16610 | C45: =AVERAGE(C38:C44,C46,C35:C36) -> 1667.148 | D45: 28950 | E45: 12.6 | G45: =C45/8760 -> 0.1903137 | K45: ROW | L45: 8278.5 | M45: 3.44 | O45: =($D$73)*('Allocation OPEX CAPEX'!L20*P45+'Allocation OPEX CAPEX'!L35*Q45+(1-Q45-P45)) -> 263.5 | P45: 0.3 | Q45: 0.3 | R45: =O45/8760 -> 0.030079909 | W45: USA | X45: =580*0.84 -> 487.2 | Z45: https://www.ewi.uni-koeln.de/cms/wp-content/uploads/2022/12/221209_EWI_H2-Steel_Low-carbon-steel.pdf | AA45: €/t | AB45: =Y27 -> 82 | AC45: Mt | AD45: 0.9 | AE45: 0.035 | AH45: =X45/8760 -> 0.055616438
A46: USA | B46: 860 | C46: =1944*0.84 -> 1632.96 | D46: 1600 | E46: 9.5 | G46: =C46/8760 -> 0.18641096 | K46: USA | L46: 1000 | M46: 3.44 | O46: =($D$73)*('Allocation OPEX CAPEX'!L21*P46+'Allocation OPEX CAPEX'!L36*Q46+(1-Q46-P46)) -> 300.29784 | P46: 0.5 | Q46: 0.3 | R46: =O46/8760 -> 0.034280575
W47: Year | X47: AUS | Y47: AUT | Z47: BRA | AA47: CHN | AB47: CZE | AC47: DEU | AD47: ITA | AE47: JPN | AF47: KOR | AG47: ROE | AH47: ROW | AI47: USA
K48: Country | L48: CAPEX | N48: unit | O48: Source | P48: OPEX | Q48: unit | R48: Source | S48: Supply 2050 | W48: 2022 | X48: 5.808 | Y48: 7.884 | Z48: 33 | AA48: 990 | AB48: 4.817 | AC48: 38 | AD48: 24 | AE48: 97 | AF48: 69 | AG48: 224.718 | AH48: 323.773 | AI48: 82
K49: Europe Copper | L49: 5000 | N49: Eur/t | O49: https://internationalcopper.org/wp-content/uploads/2023/03/Copper_The-Pathway-to-Net-Zero_Focus-on-Europe_final.pdf | W49: 2023 | X49: =X$48*(1+$AE$34)^($W49-$W$48) -> 5.808 | Y49: =Y$48*(1+$AE$35)^($W49-$W$48) -> 7.576524 | Z49: =Z$48*(1+$AE$36)^($W49-$W$48) -> 31.317 | AA49: =AA$48*(1+$AE$37)^($W49-$W$48) -> 1006.83 | AB49: =AB$48*(1+$AE$38)^($W49-$W$48) -> 4.629137 | AC49: =AC$48*(1+$AE$39)^($W49-$W$48) -> 36.518 | AD49: =AD$48*(1+$AE$40)^($W49-$W$48) -> 23.064 | AE49: =AE$48*(1+$AE$41)^($W49-$W$48) -> 99.037 | AF49: =AF$48*(1+$AE$42)^($W49-$W$48) -> 70.449 | AG49: =AG$48*(1+$AE$43)^($W49-$W$48) -> 215.954 | AH49: =AH$48*(1+$AE$44)^($W49-$W$48) -> 331.21978 | AI49: =AI$48*(1+$AE$45)^($W49-$W$48) -> 84.87
K50: LatAm Copper | L50: 5000 | N50: Eur/t | O50: https://internationalcopper.org/wp-content/uploads/2023/04/20230419-Pathway-to-Net-Zero-LatAm-ENGLISH.pdf | S50: 4.23 | T50: Mio. t Cu | W50: 2024 | X50: =X$48*(1+$AE$34)^($W50-$W$48) -> 5.808 | Y50: =Y$48*(1+$AE$35)^($W50-$W$48) -> 7.2810396 | Z50: =Z$48*(1+$AE$36)^($W50-$W$48) -> 29.719833 | AA50: =AA$48*(1+$AE$37)^($W50-$W$48) -> 1023.9461 | AB50: =AB$48*(1+$AE$38)^($W50-$W$48) -> 4.4486007 | AC50: =AC$48*(1+$AE$39)^($W50-$W$48) -> 35.093798 | AD50: =AD$48*(1+$AE$40)^($W50-$W$48) -> 22.164504 | AE50: =AE$48*(1+$AE$41)^($W50-$W$48) -> 101.11678 | AF50: =AF$48*(1+$AE$42)^($W50-$W$48) -> 71.928429 | AG50: =AG$48*(1+$AE$43)^($W50-$W$48) -> 207.53179 | AH50: =AH$48*(1+$AE$44)^($W50-$W$48) -> 338.83783 | AI50: =AI$48*(1+$AE$45)^($W50-$W$48) -> 87.84045
K51: Global Copper investemnt | L51: =AVERAGE(90,210)*0.19 -> 28.5 | N51: Bio USD | O51: Technology perpsective, 2023 | P51: needed investemnt for NZE scenario until 2030 | W51: 2025 | X51: =X$48*(1+$AE$34)^($W51-$W$48) -> 5.808 | Y51: =Y$48*(1+$AE$35)^($W51-$W$48) -> 6.997079 | Z51: =Z$48*(1+$AE$36)^($W51-$W$48) -> 28.204122 | AA51: =AA$48*(1+$AE$37)^($W51-$W$48) -> 1041.3532 | AB51: =AB$48*(1+$AE$38)^($W51-$W$48) -> 4.2751052 | AC51: =AC$48*(1+$AE$39)^($W51-$W$48) -> 33.72514 | AD51: =AD$48*(1+$AE$40)^($W51-$W$48) -> 21.300088 | AE51: =AE$48*(1+$AE$41)^($W51-$W$48) -> 103.24023 | AF51: =AF$48*(1+$AE$42)^($W51-$W$48) -> 73.438926 | AG51: =AG$48*(1+$AE$43)^($W51-$W$48) -> 199.43805 | AH51: =AH$48*(1+$AE$44)^($W51-$W$48) -> 346.6311 | AI51: =AI$48*(1+$AE$45)^($W51-$W$48) -> 90.914866
K52: Global nickel investment | L52: =AVERAGE(90,210)*0.55 -> 82.5 | N52: Bio USD | O52: Technology perpsective, 2024 | P52: needed investemnt for NZE scenario until 2031 | W52: 2026 | X52: =X$48*(1+$AE$34)^($W52-$W$48) -> 5.808 | Y52: =Y$48*(1+$AE$35)^($W52-$W$48) -> 6.7241929 | Z52: =Z$48*(1+$AE$36)^($W52-$W$48) -> 26.765711 | AA52: =AA$48*(1+$AE$37)^($W52-$W$48) -> 1059.0562 | AB52: =AB$48*(1+$AE$38)^($W52-$W$48) -> 4.1083761 | AC52: =AC$48*(1+$AE$39)^($W52-$W$48) -> 32.409859 | AD52: =AD$48*(1+$AE$40)^($W52-$W$48) -> 20.469385 | AE52: =AE$48*(1+$AE$41)^($W52-$W$48) -> 105.40827 | AF52: =AF$48*(1+$AE$42)^($W52-$W$48) -> 74.981143 | AG52: =AG$48*(1+$AE$43)^($W52-$W$48) -> 191.65997 | AH52: =AH$48*(1+$AE$44)^($W52-$W$48) -> 354.60362 | AI52: =AI$48*(1+$AE$45)^($W52-$W$48) -> 94.096886
K53: Anticipated investemnt | L53: 70 - 160 | N53: Bio USD | O53: Technology perpsective, 2025 | W53: 2027 | X53: =X$48*(1+$AE$34)^($W53-$W$48) -> 5.808 | Y53: =Y$48*(1+$AE$35)^($W53-$W$48) -> 6.4619494 | Z53: =Z$48*(1+$AE$36)^($W53-$W$48) -> 25.40066 | AA53: =AA$48*(1+$AE$37)^($W53-$W$48) -> 1077.0602 | AB53: =AB$48*(1+$AE$38)^($W53-$W$48) -> 3.9481495 | AC53: =AC$48*(1+$AE$39)^($W53-$W$48) -> 31.145875 | AD53: =AD$48*(1+$AE$40)^($W53-$W$48) -> 19.671079 | AE53: =AE$48*(1+$AE$41)^($W53-$W$48) -> 107.62185 | AF53: =AF$48*(1+$AE$42)^($W53-$W$48) -> 76.555747 | AG53: =AG$48*(1+$AE$43)^($W53-$W$48) -> 184.18523 | AH53: =AH$48*(1+$AE$44)^($W53-$W$48) -> 362.7595 | AI53: =AI$48*(1+$AE$45)^($W53-$W$48) -> 97.390277
K54: pf which is in China | L54: =AVERAGE(70,160)*0.7 -> 80.5 | N54: Bio USD | O54: Technology perpsective, 2026 | W54: 2028 | X54: =X$48*(1+$AE$34)^($W54-$W$48) -> 5.808 | Y54: =Y$48*(1+$AE$35)^($W54-$W$48) -> 6.2099334 | Z54: =Z$48*(1+$AE$36)^($W54-$W$48) -> 24.105226 | AA54: =AA$48*(1+$AE$37)^($W54-$W$48) -> 1095.3702 | AB54: =AB$48*(1+$AE$38)^($W54-$W$48) -> 3.7941716 | AC54: =AC$48*(1+$AE$39)^($W54-$W$48) -> 29.931186 | AD54: =AD$48*(1+$AE$40)^($W54-$W$48) -> 18.903907 | AE54: =AE$48*(1+$AE$41)^($W54-$W$48) -> 109.88191 | AF54: =AF$48*(1+$AE$42)^($W54-$W$48) -> 78.163418 | AG54: =AG$48*(1+$AE$43)^($W54-$W$48) -> 177.00201 | AH54: =AH$48*(1+$AE$44)^($W54-$W$48) -> 371.10297 | AI54: =AI$48*(1+$AE$45)^($W54-$W$48) -> 100.79894
W55: 2029 | X55: =X$48*(1+$AE$34)^($W55-$W$48) -> 5.808 | Y55: =Y$48*(1+$AE$35)^($W55-$W$48) -> 5.967746 | Z55: =Z$48*(1+$AE$36)^($W55-$W$48) -> 22.87586 | AA55: =AA$48*(1+$AE$37)^($W55-$W$48) -> 1113.9915 | AB55: =AB$48*(1+$AE$38)^($W55-$W$48) -> 3.6461989 | AC55: =AC$48*(1+$AE$39)^($W55-$W$48) -> 28.76387 | AD55: =AD$48*(1+$AE$40)^($W55-$W$48) -> 18.166654 | AE55: =AE$48*(1+$AE$41)^($W55-$W$48) -> 112.18943 | AF55: =AF$48*(1+$AE$42)^($W55-$W$48) -> 79.80485 | AG55: =AG$48*(1+$AE$43)^($W55-$W$48) -> 170.09893 | AH55: =AH$48*(1+$AE$44)^($W55-$W$48) -> 379.63834 | AI55: =AI$48*(1+$AE$45)^($W55-$W$48) -> 104.3269
W56: 2030 | X56: =X$48*(1+$AE$34)^($W56-$W$48) -> 5.808 | Y56: =Y$48*(1+$AE$35)^($W56-$W$48) -> 5.7350039 | Z56: =Z$48*(1+$AE$36)^($W56-$W$48) -> 21.709191 | AA56: =AA$48*(1+$AE$37)^($W56-$W$48) -> 1132.9293 | AB56: =AB$48*(1+$AE$38)^($W56-$W$48) -> 3.5039972 | AC56: =AC$48*(1+$AE$39)^($W56-$W$48) -> 27.642079 | AD56: =AD$48*(1+$AE$40)^($W56-$W$48) -> 17.458155 | AE56: =AE$48*(1+$AE$41)^($W56-$W$48) -> 114.5454 | AF56: =AF$48*(1+$AE$42)^($W56-$W$48) -> 81.480752 | AG56: =AG$48*(1+$AE$43)^($W56-$W$48) -> 163.46507 | AH56: =AH$48*(1+$AE$44)^($W56-$W$48) -> 388.37002 | AI56: =AI$48*(1+$AE$45)^($W56-$W$48) -> 107.97834
W57: 2031 | X57: =X$48*(1+$AE$34)^($W57-$W$48) -> 5.808 | Y57: =Y$48*(1+$AE$35)^($W57-$W$48) -> 5.5113387 | Z57: =Z$48*(1+$AE$36)^($W57-$W$48) -> 20.602022 | AA57: =AA$48*(1+$AE$37)^($W57-$W$48) -> 1152.1891 | AB57: =AB$48*(1+$AE$38)^($W57-$W$48) -> 3.3673413 | AC57: =AC$48*(1+$AE$39)^($W57-$W$48) -> 26.564038 | AD57: =AD$48*(1+$AE$40)^($W57-$W$48) -> 16.777287 | AE57: =AE$48*(1+$AE$41)^($W57-$W$48) -> 116.95086 | AF57: =AF$48*(1+$AE$42)^($W57-$W$48) -> 83.191848 | AG57: =AG$48*(1+$AE$43)^($W57-$W$48) -> 157.08993 | AH57: =AH$48*(1+$AE$44)^($W57-$W$48) -> 397.30253 | AI57: =AI$48*(1+$AE$45)^($W57-$W$48) -> 111.75758
W58: 2032 | X58: =X$48*(1+$AE$34)^($W58-$W$48) -> 5.808 | Y58: =Y$48*(1+$AE$35)^($W58-$W$48) -> 5.2963965 | Z58: =Z$48*(1+$AE$36)^($W58-$W$48) -> 19.551319 | AA58: =AA$48*(1+$AE$37)^($W58-$W$48) -> 1171.7763 | AB58: =AB$48*(1+$AE$38)^($W58-$W$48) -> 3.236015 | AC58: =AC$48*(1+$AE$39)^($W58-$W$48) -> 25.52804 | AD58: =AD$48*(1+$AE$40)^($W58-$W$48) -> 16.122973 | AE58: =AE$48*(1+$AE$41)^($W58-$W$48) -> 119.40683 | AF58: =AF$48*(1+$AE$42)^($W58-$W$48) -> 84.938876 | AG58: =AG$48*(1+$AE$43)^($W58-$W$48) -> 150.96342 | AH58: =AH$48*(1+$AE$44)^($W58-$W$48) -> 406.44049 | AI58: =AI$48*(1+$AE$45)^($W58-$W$48) -> 115.6691
W59: 2033 | X59: =X$48*(1+$AE$34)^($W59-$W$48) -> 5.808 | Y59: =Y$48*(1+$AE$35)^($W59-$W$48) -> 5.0898371 | Z59: =Z$48*(1+$AE$36)^($W59-$W$48) -> 18.554202 | AA59: =AA$48*(1+$AE$37)^($W59-$W$48) -> 1191.6965 | AB59: =AB$48*(1+$AE$38)^($W59-$W$48) -> 3.1098104 | AC59: =AC$48*(1+$AE$39)^($W59-$W$48) -> 24.532447 | AD59: =AD$48*(1+$AE$40)^($W59-$W$48) -> 15.494177 | AE59: =AE$48*(1+$AE$41)^($W59-$W$48) -> 121.91437 | AF59: =AF$48*(1+$AE$42)^($W59-$W$48) -> 86.722593 | AG59: =AG$48*(1+$AE$43)^($W59-$W$48) -> 145.07585 | AH59: =AH$48*(1+$AE$44)^($W59-$W$48) -> 415.78862 | AI59: =AI$48*(1+$AE$45)^($W59-$W$48) -> 119.71752
W60: 2034 | X60: =X$48*(1+$AE$34)^($W60-$W$48) -> 5.808 | Y60: =Y$48*(1+$AE$35)^($W60-$W$48) -> 4.8913334 | Z60: =Z$48*(1+$AE$36)^($W60-$W$48) -> 17.607938 | AA60: =AA$48*(1+$AE$37)^($W60-$W$48) -> 1211.9554 | AB60: =AB$48*(1+$AE$38)^($W60-$W$48) -> 2.9885278 | AC60: =AC$48*(1+$AE$39)^($W60-$W$48) -> 23.575681 | AD60: =AD$48*(1+$AE$40)^($W60-$W$48) -> 14.889904 | AE60: =AE$48*(1+$AE$41)^($W60-$W$48) -> 124.47457 | AF60: =AF$48*(1+$AE$42)^($W60-$W$48) -> 88.543767 | AG60: =AG$48*(1+$AE$43)^($W60-$W$48) -> 139.41789 | AH60: =AH$48*(1+$AE$44)^($W60-$W$48) -> 425.35176 | AI60: =AI$48*(1+$AE$45)^($W60-$W$48) -> 123.90763
W61: 2035 | X61: =X$48*(1+$AE$34)^($W61-$W$48) -> 5.808 | Y61: =Y$48*(1+$AE$35)^($W61-$W$48) -> 4.7005714 | Z61: =Z$48*(1+$AE$36)^($W61-$W$48) -> 16.709933 | AA61: =AA$48*(1+$AE$37)^($W61-$W$48) -> 1232.5586 | AB61: =AB$48*(1+$AE$38)^($W61-$W$48) -> 2.8719752 | AC61: =AC$48*(1+$AE$39)^($W61-$W$48) -> 22.65623 | AD61: =AD$48*(1+$AE$40)^($W61-$W$48) -> 14.309198 | AE61: =AE$48*(1+$AE$41)^($W61-$W$48) -> 127.08854 | AF61: =AF$48*(1+$AE$42)^($W61-$W$48) -> 90.403186 | AG61: =AG$48*(1+$AE$43)^($W61-$W$48) -> 133.98059 | AH61: =AH$48*(1+$AE$44)^($W61-$W$48) -> 435.13485 | AI61: =AI$48*(1+$AE$45)^($W61-$W$48) -> 128.2444
B66: CAPEX | C66: unit | D66: OPEX | F66: unit
A67: Aluminium | B67: 5800 | C67: USD / tyr | D67: 1500 | F67: USD/t | G67: https://documents1.worldbank.org/curated/en/099222003082337952/pdf/P1740030ce87ae0650ad6c0f93f0b5f9c91.pdf
B68: =B67*0.84 -> 4872 | C68: €/(t/yr) | D68: =D67*0.84 -> 1260 | F68: €/t | G68: Electricity costs are a key part of OPEX – e.g., approx. 30% of costs of Chinese production (S&P Global, 2021)
A69: Steel | B69: 100 | C69: €/(t/yr) | D69: 415 | F69: €/t | G69: https://www.sciencedirect.com/science/article/pii/S0959652618335224
A70: Copper | D70: 0.4 | E70: €/kg | G70: https://www.teck.com/media/CESL-Publication-Copper-On-Site-vs-Cu-Con-Sales-Alta-2005.pdf
A71: EU | D71: =279+45 -> 324 | E71: €/t Cu | G71: https://www.sciencedirect.com/science/article/pii/S0301420716300824
A72: china | D72: =23+180 -> 203 | E72: €/t Cu
A73: Average | D73: =AVERAGE(D71:D72) -> 263.5
A74: Prices per material | G74: per kg
A75: Copper | B75: 16.7 | C75: USD/kW | D75: Enel 2023 | E75: =B75*$B$80 -> 14.028 | F75: Euro/kW | H75: €/kt
A76: Nickel | B76: 6.8 | C76: USD/kW | D76: Enel 2024 | E76: =B76*$B$80 -> 5.712 | F76: Euro/kW
A77: Steel | B77: 4.1 | C77: USD/kW | D77: Enel 2025 | E77: =B77*$B$80 -> 3.444 | F77: Euro/kW
A78: Aluminium | B78: 2.2 | C78: USD/kW | D78: Enel 2026 | E78: =B78*$B$80 -> 1.848 | F78: Euro/kW | G78: =2351 -> 2351 | H78: k€/kt | I78: https://markets.businessinsider.com/commodities/aluminum-price/euro
A80: converion factor USD in Euro | B80: 0.84 | C80: EURO/USD | D80: Source: IEA 2023 energy technology perspectives

Sheet Transportation
A1: Destination_Label | B1: 2021_Transport_cost_intensity_in_US_per_tonkm_Value | C1: Source: | D1: origin china s this is most often orimary producer
A2: Australia | B2: 0.091 | C2: https://unctadstat.unctad.org/datacentre/dataviewer/US.TransportCosts | D2: Electrical machinery and equipment and parts thereof; sound recorders and reproducers; television image and sound recorders and reproducers, parts and accessories of such articles
A3: Austria | B3: 0.141 | C3: https://unctadstat.unctad.org/datacentre/dataviewer/US.TransportCosts | D3: Electrical machinery and equipment and parts thereof; sound recorders and reproducers; television image and sound recorders and reproducers, parts and accessories of such articles
A4: Brazil | B4: 0.042 | C4: https://unctadstat.unctad.org/datacentre/dataviewer/US.TransportCosts | D4: Electrical machinery and equipment and parts thereof; sound recorders and reproducers; television image and sound recorders and reproducers, parts and accessories of such articles
A5: China | B5: 0.596 | C5: https://unctadstat.unctad.org/datacentre/dataviewer/US.TransportCosts | D5: Electrical machinery and equipment and parts thereof; sound recorders and reproducers; television image and sound recorders and reproducers, parts and accessories of such articles
A6: Czechia | B6: 0.217 | C6: https://unctadstat.unctad.org/datacentre/dataviewer/US.TransportCosts | D6: Electrical machinery and equipment and parts thereof; sound recorders and reproducers; television image and sound recorders and reproducers, parts and accessories of such articles
A7: Germany | B7: 0.144 | C7: https://unctadstat.unctad.org/datacentre/dataviewer/US.TransportCosts | D7: Electrical machinery and equipment and parts thereof; sound recorders and reproducers; television image and sound recorders and reproducers, parts and accessories of such articles
A8: Italy | B8: 0.091 | C8: https://unctadstat.unctad.org/datacentre/dataviewer/US.TransportCosts | D8: Electrical machinery and equipment and parts thereof; sound recorders and reproducers; television image and sound recorders and reproducers, parts and accessories of such articles
A9: Japan | B9: 0.374 | C9: https://unctadstat.unctad.org/datacentre/dataviewer/US.TransportCosts | D9: Electrical machinery and equipment and parts thereof; sound recorders and reproducers; television image and sound recorders and reproducers, parts and accessories of such articles
A10: Korea, Republic of | B10: 0.674 | C10: https://unctadstat.unctad.org/datacentre/dataviewer/US.TransportCosts | D10: Electrical machinery and equipment and parts thereof; sound recorders and reproducers; television image and sound recorders and reproducers, parts and accessories of such articles
A11: United States of America | B11: 0.107 | C11: https://unctadstat.unctad.org/datacentre/dataviewer/US.TransportCosts | D11: Electrical machinery and equipment and parts thereof; sound recorders and reproducers; television image and sound recorders and reproducers, parts and accessories of such articles
A13: Australia | B13: 0.004 | C13: https://unctadstat.unctad.org/datacentre/dataviewer/US.TransportCosts | D13: Copper ores and concentrates | E13: =B13*0.84 -> 0.00336 | H13: refrigerant | I13: Halogenated derivatives of hydrocarbons
A14: Austria | B14: 0.265 | C14: https://unctadstat.unctad.org/datacentre/dataviewer/US.TransportCosts | D14: Copper ores and concentrates | E14: =B14*0.84 -> 0.2226 | H14: Australia | I14: 0.017
A15: Brazil | B15: 0.005 | C15: https://unctadstat.unctad.org/datacentre/dataviewer/US.TransportCosts | D15: Copper ores and concentrates | E15: =B15*0.84 -> 0.0042 | H15: Austria | I15: 0.107
A16: China | B16: 0.111 | C16: https://unctadstat.unctad.org/datacentre/dataviewer/US.TransportCosts | D16: Copper ores and concentrates | E16: =B16*0.84 -> 0.09324 | H16: Brazil | I16: 0.008
A17: Czechia | B17: 0.009 | C17: https://unctadstat.unctad.org/datacentre/dataviewer/US.TransportCosts | D17: Copper ores and concentrates | E17: =B17*0.84 -> 0.00756 | H17: China | I17: 0.034
A18: Germany | B18: 0.002 | C18: https://unctadstat.unctad.org/datacentre/dataviewer/US.TransportCosts | D18: Copper ores and concentrates | E18: =B18*0.84 -> 0.00168 | H18: Czechia | I18: 0.037
A19: Italy | B19: 0.138 | C19: https://unctadstat.unctad.org/datacentre/dataviewer/US.TransportCosts | D19: Copper ores and concentrates | E19: =B19*0.84 -> 0.11592 | H19: Germany | I19: 0.059
A20: Japan | B20: 0.114 | C20: https://unctadstat.unctad.org/datacentre/dataviewer/US.TransportCosts | D20: Copper ores and concentrates | E20: =B20*0.84 -> 0.09576 | H20: Italy | I20: 0.081
